Workbook

Sheet 00_总览
A2: 汴梁游记 成员2数据工作簿 v1.1
A4: 本工作簿依据新的项目总体设计、数据需求和四人任务分工重建，服务于成员2的第一轮工作：建立统一表结构、字段字典、ID与格式规范，并为自动校验、异常清单、增量导入和质量报告提供可执行基础。
A7: 核心数据表 | B7: 12 | D7: 第一轮放行条件
A8: 字段定义 | B8: 228 | D8: 12张核心表、字段字典、媒体权限与状态取值已定版。
A9: 成员2首轮任务 | B9: 10 | D9: 成员1/3/4提交的数据能按统一ID导入，并被定位到原始来源。
A10: 校验规则 | B10: 21 | D10: 自动校验能发现重复、缺失、无效坐标、时间冲突和跨表断链。
A11: 状态码 | B11: 61 | D11: 所有异常都有记录ID、处理状态、负责人和变更日志。
D12: 报告分别统计候选数据与已核实数据，不合并成一个成功数量。
A14: 输入依据
A15: 项目总体设计 | B15: 全项目任务与交付路线图 | C15: 2026-10-20版本 | D15: 确认产品闭环、M0/M1边界和C/D/E数据任务
A16: 项目所需要的数据 | B16: 城市旅游智能体数据收集与实施清单 | C16: 14页 | D16: 确认10张核心表、字段、来源、时效与验收规则
A17: 任务分工 | B17: 四人数据采集任务书与质量验收标准 | C17: 7页 | D17: 确认成员2职责、第一轮目标、交付物与3天节奏
A19: 使用顺序：先由成员1/3/4按工作表中的候选/核验状态录数；成员2只做结构整合、关联检查、问题登记和版本管理。程序校验不能替代入口、场次、路网、商家供应的现场或官方核实。
A22: v1.1更新：新增22_media_assets与23_media_relations；修正“当前候选数”只统计candidate状态；将供应关系的verified_at改为条件必填；新增89_初筛报告。成员1和成员4原填写内容保留。

Sheet 01_成员2任务
A1: 成员2第一轮任务
A2: 按三天试采节奏拆分。状态由成员2维护，完成时必须在证据列填写可定位文件、命令或链接。
A4: 任务ID | B4: 第一轮动作 | C4: 产出物 | D4: 验收标准 | E4: 依赖与协作 | F4: 建议完成日 | G4: 状态 | H4: 证据链接/文件
A5: M2-R1-01 | B5: 冻结第一轮10张核心表与字段字典 | C5: 统一Excel模板、字段字典、状态取值表 | D5: 表名、字段名、类型和必填规则一致，可直接分工填写 | E5: 成员2；依赖成员1/3/4口径 | F5: 第1天 | G5: 进行中 | H5: 本工作簿
A6: M2-R1-02 | B6: 制定唯一ID和关联规则 | C6: ID规则说明、跨表外键关系 | D6: 景点、入口、规则、节目、场次、商家、菜品、来源均有稳定ID | E6: 成员2 | F6: 第1天 | G6: 进行中 | H6: 字段字典/使用说明
A7: M2-R1-03 | B7: 统一时间、坐标、单位与状态格式 | C7: 格式校验约束 | D7: 日期含日期与时区，坐标必须带CRS，距离米、耗时秒、价格人民币 | E7: 成员2；成员3核对CRS | F7: 第1天 | G7: 进行中 | H7: 99_使用说明
A8: M2-R1-04 | B8: 建立自动校验规则集 | C8: 90_校验规则、后续校验脚本 | D8: 覆盖重复ID、重复记录、必填缺失、无效坐标、时间逻辑和跨表断链 | E8: 成员2 | F8: 第2天 | G8: 待开始 | H8: 90_校验规则
A9: M2-R1-05 | B9: 建立异常清单处理状态 | C9: 问题表字段规范、处理状态 | D9: 每个异常可定位到记录ID、负责人和处理结论 | E9: 成员2 | F9: 第2天 | G9: 待开始 | H9: 91_状态与取值
A10: M2-R1-06 | B10: 完成第一批数据导入试跑 | C10: 导入记录、错误清单、修复前后对照 | D10: 同一批数据重复运行结果一致，不覆盖原始版本 | E10: 成员2；成员1/3/4提交数据 | F10: 第2天 | G10: 待开始 | H10: 导入后补证据
A11: M2-R1-07 | B11: 生成本轮数据质量报告 | C11: 候选数、已核实数、缺失率、重复数、冲突数、关联率 | D11: 候选与已核实分开统计，不以格式正确替代事实核实 | E11: 成员2 | F11: 第3天 | G11: 待开始 | H11: 质量报告
A12: M2-R1-08 | B12: 交付第一轮数据包并保留变更日志 | C12: 工作簿、原始证据索引、问题清单、版本记录 | D12: 原始数据未被覆盖或丢弃，可追溯到来源 | E12: 成员2；全组验收 | F12: 第3天 | G12: 待开始 | H12: 最终归档
A13: M2-R1-09 | B13: 冻结图片、视频等媒体资产结构 | C13: 媒体资产表、媒体关联表、权限和隐私字段 | D13: 成员1/4可登记图片视频，不再改动原有地点和商家字段 | E13: 成员2；需成员1/4确认媒体来源与权限 | F13: 第4天 | G13: 完成 | H13: 22/23工作表与字段字典
A14: M2-R1-10 | B14: 发布初筛报告与最新版模板 | C14: v1.1工作簿、初筛报告、问题清单 | D14: 839条现有记录保留，重复/格式/断链有结论，媒体结构已补齐 | E14: 成员2；全组复核 | F14: 第4天 | G14: 完成 | H14: v1.1工作簿与89_初筛报告

Sheet 02_字段字典
A1: 字段字典
A2: 第一轮字段口径。字段名用于程序与跨表关联，中文名称用于团队填写和审核。
A3: 序号 | B3: 工作表 | C3: 字段名 | D3: 中文名称 | E3: 数据类型 | F3: 必填 | G3: 格式示例 | H3: 允许值/约束 | I3: 说明
A4: 1 | B4: 10_places | C4: place_id | D4: 地点ID | E4: string | F4: Y | G4: pl_000001 | H4: 唯一稳定ID；不得用名称代替 | I4: 地点主键。
A5: 2 | B5: 10_places | C5: name | D5: 标准名称 | E5: string | F5: Y | G5: 地点标准名称 | I5: 游客可识别的正式名称。
A6: 3 | B6: 10_places | C6: place_type | D6: 地点类别 | E6: enum | F6: Y | G6: scenic_spot | H6: scenic_spot|night_market|food_street|transport_hub|stage|service_point | I6: 城市景点、夜市、餐饮街区、交通枢纽、舞台等。
A7: 4 | B7: 10_places | C7: parent_place_id | D7: 上级地点ID | E7: string | F7: N | G7: pl_000010 | I7: 景区归属或街区归属；用于层级关系。
A8: 5 | B8: 10_places | C8: address | D8: 地址 | E8: string | F8: N | G8: 详细地址 | I8: 公开地址或核实结果。
A9: 6 | B9: 10_places | C9: lng | D9: 经度 | E9: number | F9: N | G9: 114.3500000 | H9: [-180,180] | I9: WGS84/GCJ-02等须与crs一致。
A10: 7 | B10: 10_places | C10: lat | D10: 纬度 | E10: number | F10: N | G10: 34.8100000 | H10: [-90,90] | I10: WGS84/GCJ-02等须与crs一致。
A11: 8 | B11: 10_places | C11: crs | D11: 坐标系 | E11: enum | F11: N | G11: WGS84 | H11: WGS84|GCJ-02|BD-09|pixel | I11: 坐标为空时可为空；存在坐标时必填。
A12: 9 | B12: 10_places | C12: aliases | D12: 别名 | E12: string | F12: N | G12: 别名1；别名2 | I12: 多个别名用分号分隔。
A13: 10 | B13: 10_places | C13: external_poi_id | D13: 外部POI ID | E13: string | F13: N | G13: provider_id | I13: 高德等外部地点ID；注明来源。
A14: 11 | B14: 10_places | C14: indoor_outdoor | D14: 室内外属性 | E14: enum | F14: N | G14: outdoor | H14: indoor|outdoor|mixed|unknown | I14: 用于体验与天气判断。
A15: 12 | B15: 10_places | C15: suggested_stay_min | D15: 建议停留分钟 | E15: integer | F15: N | G15: 90 | H15: >=0 | I15: 首轮可为空；有来源时填写。
A16: 13 | B16: 10_places | C16: description | D16: 简介 | E16: string | F16: N | G16: 简要介绍 | I16: 避免无来源的文化故事。
A17: 14 | B17: 10_places | C17: source_id | D17: 来源ID | E17: string | F17: Y | G17: src_000001 | I17: 关联18_source_records。
A18: 15 | B18: 10_places | C18: validation_status | D18: 校验状态 | E18: enum | F18: Y | G18: candidate | H18: candidate|pending_review|verified|conflict|stale|expired|cancelled|mock|rejected | I18: 候选与已核实必须分开。
A19: 16 | B19: 10_places | C19: verified_at | D19: 核实时间 | E19: datetime | F19: N | G19: 例：2026-10-21T10:00:00+08:00 | H19: ISO 8601 +08:00 | I19: 人工核实时间。
A20: 17 | B20: 10_places | C20: valid_from | D20: 有效期起 | E20: date | F20: N | G20: 例：2026-10-21 | H20: YYYY-MM-DD | I20: 记录适用起始日。
A21: 18 | B21: 10_places | C21: valid_to | D21: 有效期止 | E21: date | F21: N | G21: 例：2026-12-31 | H21: YYYY-MM-DD | I21: 过期后需降级。
A22: 19 | B22: 10_places | C22: reviewer | D22: 核验人 | E22: string | F22: N | G22: 成员3 | I22: 真实负责人或组内代号。
A23: 20 | B23: 10_places | C23: version | D23: 版本 | E23: integer | F23: Y | G23: 1 | H23: >=1 | I23: 每次实质性修改递增。
A24: 21 | B24: 10_places | C24: notes | D24: 备注 | E24: string | F24: N | G24: 待补充说明 | I24: 只写复现所需信息。
A25: 22 | B25: 11_place_entrances | C25: entrance_id | D25: 入口ID | E25: string | F25: Y | G25: ent_000001 | H25: 唯一稳定ID | I25: 入口主键。
A26: 23 | B26: 11_place_entrances | C26: place_id | D26: 地点ID | E26: string | F26: Y | G26: pl_000001 | I26: 关联10_places。
A27: 24 | B27: 11_place_entrances | C27: name | D27: 入口名称 | E27: string | F27: Y | G27: 入口名称 | I27: 官方名称或现场标识。
A28: 25 | B28: 11_place_entrances | C28: entrance_type | D28: 入口类型 | E28: enum | F28: Y | G28: main_entrance | H28: main_entrance|secondary_entrance|area_entrance|exit|unknown | I28: 景区中心点不能代替入口。
A29: 26 | B29: 11_place_entrances | C29: lng | D29: 经度 | E29: number | F29: N | G29: 114.3500000 | H29: [-180,180] | I29: 有坐标时必填。
A30: 27 | B30: 11_place_entrances | C30: lat | D30: 纬度 | E30: number | F30: N | G30: 34.8100000 | H30: [-90,90] | I30: 有坐标时必填。
A31: 28 | B31: 11_place_entrances | C31: crs | D31: 坐标系 | E31: enum | F31: N | G31: WGS84 | H31: WGS84|GCJ-02|BD-09|pixel | I31: 与坐标同时填写。
A32: 29 | B32: 11_place_entrances | C32: is_main_entrance | D32: 是否主入口 | E32: boolean | F32: N | G32: true | H32: true|false|unknown | I32: 未知不要填false。
A33: 30 | B33: 11_place_entrances | C33: access_rules | D33: 通行规则 | E33: string | F33: N | G33: 仅游客入口 | I33: 门禁、员工通道等说明。
A34: 31 | B34: 11_place_entrances | C34: stop_entry_before | D34: 最晚入园 | E34: time | F34: N | G34: 例：20:30 | H34: HH:MM | I34: 必须附带时区。
A35: 32 | B35: 11_place_entrances | C35: open_rule_id | D35: 开放规则ID | E35: string | F35: N | G35: or_000001 | I35: 关联12_open_rules。
A36: 33 | B36: 11_place_entrances | C36: source_id | D36: 来源ID | E36: string | F36: Y | G36: src_000001 | I36: 关联18_source_records。
A37: 34 | B37: 11_place_entrances | C37: validation_status | D37: 校验状态 | E37: enum | F37: Y | G37: candidate | H37: candidate|pending_review|verified|conflict|stale|expired|cancelled|mock|rejected | I37: 候选与已核实分开。
A38: 35 | B38: 11_place_entrances | C38: verified_at | D38: 核实时间 | E38: datetime | F38: N | G38: 例：2026-10-21T10:00:00+08:00 | H38: ISO 8601 +08:00 | I38: 人工核实时间。
A39: 36 | B39: 11_place_entrances | C39: notes | D39: 备注 | E39: string | F39: N | G39: 待补充说明 | I39: 记录冲突或位置精度。
A40: 37 | B40: 12_open_rules | C40: open_rule_id | D40: 规则ID | E40: string | F40: Y | G40: or_000001 | H40: 唯一稳定ID | I40: 规则主键。
A41: 38 | B41: 12_open_rules | C41: place_id | D41: 地点ID | E41: string | F41: Y | G41: pl_000001 | I41: 关联10_places。
A42: 39 | B42: 12_open_rules | C42: rule_name | D42: 规则名称 | E42: string | F42: Y | G42: 工作日规则 | I42: 便于识别规则用途。
A43: 40 | B43: 12_open_rules | C43: rule_type | D43: 规则类型 | E43: enum | F43: Y | G43: date_range | H43: daily|date_range|holiday|event|special | I43: 不同日期规则分开。
A44: 41 | B44: 12_open_rules | C44: effective_from | D44: 生效日期起 | E44: date | F44: N | G44: 例：2026-10-21 | H44: YYYY-MM-DD | I44: 长期规则可为空并说明。
A45: 42 | B45: 12_open_rules | C45: effective_to | D45: 生效日期止 | E45: date | F45: N | G45: 例：2026-12-31 | H45: YYYY-MM-DD | I45: 到期后不得继续作为事实。
A46: 43 | B46: 12_open_rules | C46: weekdays | D46: 适用星期 | E46: string | F46: N | G46: 1;2;3;4;5 | H46: ISO 1-7，分号分隔 | I46: 周一=1，周日=7。
A47: 44 | B47: 12_open_rules | C47: open_time | D47: 开放时间 | E47: time | F47: Y | G47: 例：09:00 | H47: HH:MM | I47: 与timezone同时使用。
A48: 45 | B48: 12_open_rules | C48: close_time | D48: 关闭时间 | E48: time | F48: Y | G48: 例：22:00 | H48: HH:MM | I48: 跨日规则需备注。
A49: 46 | B49: 12_open_rules | C49: last_entry_time | D49: 最晚入园 | E49: time | F49: N | G49: 例：20:30 | H49: HH:MM | I49: 没有依据时留空。
A50: 47 | B50: 12_open_rules | C50: timezone | D50: 时区 | E50: string | F50: Y | G50: Asia/Shanghai (+08:00) | I50: 禁止只写时间不写时区。
A51: 48 | B51: 12_open_rules | C51: ticket_scope | D51: 票种范围 | E51: string | F51: N | G51: 日场票 | I51: 适用范围未确认则标为待核实。
A52: 49 | B52: 12_open_rules | C52: reservation_required | D52: 是否需预约 | E52: enum | F52: N | G52: unknown | H52: true|false|unknown | I52: 未知不得推断为false。
A53: 50 | B53: 12_open_rules | C53: reentry_allowed | D53: 是否可二次入园 | E53: enum | F53: N | G53: unknown | H53: true|false|unknown | I53: 未知不得推断为false。
A54: 51 | B54: 12_open_rules | C54: special_rules | D54: 特殊限制 | E54: string | F54: N | G54: 节假日调整规则 | I54: 停止入园、年龄、证件等。
A55: 52 | B55: 12_open_rules | C55: source_id | D55: 来源ID | E55: string | F55: Y | G55: src_000001 | I55: 关联18_source_records。
A56: 53 | B56: 12_open_rules | C56: validation_status | D56: 校验状态 | E56: enum | F56: Y | G56: candidate | H56: candidate|pending_review|verified|conflict|stale|expired|cancelled|mock|rejected | I56: 候选与已核实分开。
A57: 54 | B57: 12_open_rules | C57: verified_at | D57: 核实时间 | E57: datetime | F57: N | G57: 例：2026-10-21T10:00:00+08:00 | H57: ISO 8601 +08:00 | I57: 人工核实时间。
A58: 55 | B58: 12_open_rules | C58: version | D58: 版本 | E58: integer | F58: Y | G58: 1 | H58: >=1 | I58: 规则修改后递增。
A59: 56 | B59: 12_open_rules | C59: notes | D59: 备注 | E59: string | F59: N | G59: 来源冲突说明 | I59: 记录例外和替代来源。
A60: 57 | B60: 13_programs | C60: program_id | D60: 节目ID | E60: string | F60: Y | G60: prg_000001 | H60: 唯一稳定ID | I60: 节目主键。
A61: 58 | B61: 13_programs | C61: park_place_id | D61: 景区地点ID | E61: string | F61: Y | G61: pl_000001 | I61: 关联10_places，指向景区。
A62: 59 | B62: 13_programs | C62: stage_place_id | D62: 舞台地点ID | E62: string | F62: N | G62: pl_000020 | I62: 关联10_places；舞台未核实可空。
A63: 60 | B63: 13_programs | C63: name | D63: 节目名称 | E63: string | F63: Y | G63: 节目标准名称 | I63: 不同场次共用此名称。
A64: 61 | B64: 13_programs | C64: category | D64: 节目类别 | E64: enum | F64: Y | G64: performance | H64: performance|exhibition|route|cinema|attraction|other | I64: 用于筛选与排序。
A65: 62 | B65: 13_programs | C65: description | D65: 节目简介 | E65: string | F65: N | G65: 节目简介 | I65: 必须有介绍来源。
A66: 63 | B66: 13_programs | C66: arrival_buffer_min | D66: 建议提前到场分钟 | E66: integer | F66: N | G66: 15 | H66: >=0 | I66: 没有依据时留空。
A67: 64 | B67: 13_programs | C67: ticket_scope | D67: 适用票种 | E67: string | F67: N | G67: 景区日票 | I67: 未确认则标记待核实。
A68: 65 | B68: 13_programs | C68: source_id | D68: 来源ID | E68: string | F68: Y | G68: src_000001 | I68: 关联18_source_records。
A69: 66 | B69: 13_programs | C69: validation_status | D69: 校验状态 | E69: enum | F69: Y | G69: candidate | H69: candidate|pending_review|verified|conflict|stale|expired|cancelled|mock|rejected | I69: 候选与已核实分开。
A70: 67 | B70: 13_programs | C70: valid_from | D70: 有效期起 | E70: date | F70: N | G70: 例：2026-10-21 | H70: YYYY-MM-DD | I70: 节目适用开始日期。
A71: 68 | B71: 13_programs | C71: valid_to | D71: 有效期止 | E71: date | F71: N | G71: 例：2026-12-31 | H71: YYYY-MM-DD | I71: 过期节目不再推荐。
A72: 69 | B72: 13_programs | C72: reviewer | D72: 核验人 | E72: string | F72: N | G72: 成员1 | I72: 真实负责人或组内代号。
A73: 70 | B73: 13_programs | C73: version | D73: 版本 | E73: integer | F73: Y | G73: 1 | H73: >=1 | I73: 节目资料修改后递增。
A74: 71 | B74: 13_programs | C74: notes | D74: 备注 | E74: string | F74: N | G74: 待核实说明 | I74: 记录来源矛盾。
A75: 72 | B75: 14_show_sessions | C75: session_id | D75: 场次ID | E75: string | F75: Y | G75: ses_000001 | H75: 唯一稳定ID | I75: 场次主键；一场一行。
A76: 73 | B76: 14_show_sessions | C76: program_id | D76: 节目ID | E76: string | F76: Y | G76: prg_000001 | I76: 关联13_programs。
A77: 74 | B77: 14_show_sessions | C77: park_place_id | D77: 景区地点ID | E77: string | F77: Y | G77: pl_000001 | I77: 关联10_places。
A78: 75 | B78: 14_show_sessions | C78: stage_place_id | D78: 舞台地点ID | E78: string | F78: N | G78: pl_000020 | I78: 关联10_places。
A79: 76 | B79: 14_show_sessions | C79: session_date | D79: 演出日期 | E79: date | F79: Y | G79: 例：2026-10-22 | H79: YYYY-MM-DD | I79: 不得把常规节目单推成每日场次。
A80: 77 | B80: 14_show_sessions | C80: starts_at | D80: 开始时间 | E80: datetime | F80: Y | G80: 例：2026-10-22T19:30:00+08:00 | H80: ISO 8601 +08:00 | I80: 必须含日期和时区。
A81: 78 | B81: 14_show_sessions | C81: ends_at | D81: 结束时间 | E81: datetime | F81: N | G81: 例：2026-10-22T20:10:00+08:00 | H81: ISO 8601 +08:00 | I81: 未知则留空并备注。
A82: 79 | B82: 14_show_sessions | C82: timezone | D82: 时区 | E82: string | F82: Y | G82: Asia/Shanghai (+08:00) | I82: 与时间字段一致。
A83: 80 | B83: 14_show_sessions | C83: session_status | D83: 场次状态 | E83: enum | F83: Y | G83: scheduled | H83: scheduled|verified|delayed|cancelled|unknown|mock | I83: 状态必须反映来源当前事实。
A84: 81 | B84: 14_show_sessions | C84: ticket_scope | D84: 适用票种 | E84: string | F84: N | G84: 景区日票 | I84: 未确认则留空。
A85: 82 | B85: 14_show_sessions | C85: source_id | D85: 来源ID | E85: string | F85: Y | G85: src_000001 | I85: 关联18_source_records。
A86: 83 | B86: 14_show_sessions | C86: checked_at | D86: 核对时间 | E86: datetime | F86: Y | G86: 例：2026-10-21T10:00:00+08:00 | H86: ISO 8601 +08:00 | I86: 与场次日期分开记录。
A87: 84 | B87: 14_show_sessions | C87: valid_until | D87: 有效截止 | E87: datetime | F87: N | G87: 例：2026-10-22T23:59:59+08:00 | H87: ISO 8601 +08:00 | I87: 过期后自动降级。
A88: 85 | B88: 14_show_sessions | C88: validation_status | D88: 校验状态 | E88: enum | F88: Y | G88: candidate | H88: candidate|pending_review|verified|conflict|stale|expired|cancelled|mock|rejected | I88: 候选与已核实分开。
A89: 86 | B89: 14_show_sessions | C89: reviewer | D89: 核验人 | E89: string | F89: N | G89: 成员1 | I89: 真实负责人或组内代号。
A90: 87 | B90: 14_show_sessions | C90: version | D90: 版本 | E90: integer | F90: Y | G90: 1 | H90: >=1 | I90: 场次变更后递增。
A91: 88 | B91: 14_show_sessions | C91: notes | D91: 备注 | E91: string | F91: N | G91: 结束时间未核实 | I91: 记录取消、延期或冲突。
A92: 89 | B92: 15_food_items | C92: food_id | D92: 菜品ID | E92: string | F92: Y | G92: food_000001 | H92: 唯一稳定ID | I92: 菜品主键。
A93: 90 | B93: 15_food_items | C93: name | D93: 标准名称 | E93: string | F93: Y | G93: 菜品名称 | I93: 开封特色美食正式名称。
A94: 91 | B94: 15_food_items | C94: aliases | D94: 别名 | E94: string | F94: N | G94: 别名1；别名2 | I94: 别名用分号分隔。
A95: 92 | B95: 15_food_items | C95: category | D95: 菜品类别 | E95: string | F95: N | G95: 小吃 | I95: 用于筛选与展示。
A96: 93 | B96: 15_food_items | C96: flavor_tags | D96: 口味标签 | E96: string | F96: N | G96: 甜；酥；咸香 | I96: 分号分隔。
A97: 94 | B97: 15_food_items | C97: dietary_tags | D97: 饮食标签 | E97: string | F97: N | G97: 素食可选；含花生 | I97: 无证据时不得宣称适用过敏人群。
A98: 95 | B98: 15_food_items | C98: intro | D98: 简介 | E98: string | F98: N | G98: 菜品简介 | I98: 文化介绍须有来源。
A99: 96 | B99: 15_food_items | C99: intro_source_id | D99: 介绍来源ID | E99: string | F99: N | G99: src_000001 | I99: 关联18_source_records。
A100: 97 | B100: 15_food_items | C100: validation_status | D100: 校验状态 | E100: enum | F100: Y | G100: candidate | H100: candidate|pending_review|verified|conflict|stale|expired|cancelled|mock|rejected | I100: 候选与已核实分开。
...

Sheet 03_首轮目标
A1: 首轮数量目标与实时进度
A2: 候选数和已核实数分开统计。数字目标来自三人/四人分工中的第一轮建议，未给数字的对象按覆盖范围核验。
A4: 数据表 | B4: 首轮对象 | C4: 候选目标下限 | D4: 核实目标下限 | E4: 当前候选数 | F4: 当前已核实数 | G4: 候选进度 | H4: 核实进度 | I4: 状态 | J4: 说明
A5: 10_places | B5: 城市与景区地点候选 | C5: 30 | E5: =COUNTIF('10_places'!O4:O503,"candidate") | F5: =COUNTIF('10_places'!O4:O503,"verified") | G5: =IF(OR(C5="",E5=0),"",E5/C5) | H5: =IF(OR(D5="",F5=0),"",F5/D5) | I5: =IF(AND(C5="",D5=""),"按覆盖核验",IF(COUNTA('10_places'!A4:A503)=0,"待录入",IF(AND(C5<>"",E5>=C5,OR(D5="",F5>=D5)),"达到候选目标","进行中"))) | J5: 30–50个候选是首轮扩展目标；先保证可关联
A6: 11_place_entrances | B6: 重点目的地入口 | C6: 10 | E6: =COUNTIF('11_place_entrances'!M4:M503,"candidate") | F6: =COUNTIF('11_place_entrances'!M4:M503,"verified") | G6: =IF(OR(C6="",E6=0),"",E6/C6) | H6: =IF(OR(D6="",F6=0),"",F6/D6) | I6: =IF(AND(C6="",D6=""),"按覆盖核验",IF(COUNTA('11_place_entrances'!A4:A503)=0,"待录入",IF(AND(C6<>"",E6>=C6,OR(D6="",F6>=D6)),"达到候选目标","进行中"))) | J6: 首轮先采10–15个重点目的地入口
A7: 12_open_rules | B7: 开放与入场规则 | C7: 10 | E7: =COUNTIF('12_open_rules'!Q4:Q503,"candidate") | F7: =COUNTIF('12_open_rules'!Q4:Q503,"verified") | G7: =IF(OR(C7="",E7=0),"",E7/C7) | H7: =IF(OR(D7="",F7=0),"",F7/D7) | I7: =IF(AND(C7="",D7=""),"按覆盖核验",IF(COUNTA('12_open_rules'!A4:A503)=0,"待录入",IF(AND(C7<>"",E7>=C7,OR(D7="",F7>=D7)),"达到候选目标","进行中"))) | J7: 先覆盖已有入口的重点目的地
A8: 13_programs | B8: 两大重点景区节目 | E8: =COUNTIF('13_programs'!J4:J503,"candidate") | F8: =COUNTIF('13_programs'!J4:J503,"verified") | G8: =IF(OR(C8="",E8=0),"",E8/C8) | H8: =IF(OR(D8="",F8=0),"",F8/D8) | I8: =IF(AND(C8="",D8=""),"按覆盖核验",IF(COUNTA('13_programs'!A4:A503)=0,"待录入",IF(AND(C8<>"",E8>=C8,OR(D8="",F8>=D8)),"达到候选目标","进行中"))) | J8: 覆盖两大景区代表性试采节目
A9: 14_show_sessions | B9: 已公布且日期明确的场次 | E9: =COUNTIF('14_show_sessions'!N4:N503,"candidate") | F9: =COUNTIF('14_show_sessions'!N4:N503,"verified") | G9: =IF(OR(C9="",E9=0),"",E9/C9) | H9: =IF(OR(D9="",F9=0),"",F9/D9) | I9: =IF(AND(C9="",D9=""),"按覆盖核验",IF(COUNTA('14_show_sessions'!A4:A503)=0,"待录入",IF(AND(C9<>"",E9>=C9,OR(D9="",F9>=D9)),"达到候选目标","进行中"))) | J9: 覆盖首轮节目；不得用常规节目单推算未来场次
A10: 15_food_items | B10: 开封特色菜品候选 | C10: 20 | E10: =COUNTIF('15_food_items'!I4:I503,"candidate") | F10: =COUNTIF('15_food_items'!I4:I503,"verified") | G10: =IF(OR(C10="",E10=0),"",E10/C10) | H10: =IF(OR(D10="",F10=0),"",F10/D10) | I10: =IF(AND(C10="",D10=""),"按覆盖核验",IF(COUNTA('15_food_items'!A4:A503)=0,"待录入",IF(AND(C10<>"",E10>=C10,OR(D10="",F10>=D10)),"达到候选目标","进行中"))) | J10: 首轮建议20–25种
A11: 16_food_vendors | B11: 经核实商家候选 | C11: 30 | E11: =COUNTIF('16_food_vendors'!P4:P503,"candidate") | F11: =COUNTIF('16_food_vendors'!P4:P503,"verified") | G11: =IF(OR(C11="",E11=0),"",E11/C11) | H11: =IF(OR(D11="",F11=0),"",F11/D11) | I11: =IF(AND(C11="",D11=""),"按覆盖核验",IF(COUNTA('16_food_vendors'!A4:A503)=0,"待录入",IF(AND(C11<>"",E11>=C11,OR(D11="",F11>=D11)),"达到候选目标","进行中"))) | J11: 首轮建议30–50家候选
A12: 17_vendor_foods | B12: 菜品—商家关系候选 | C12: 30 | E12: =COUNTIF('17_vendor_foods'!G4:G503,"candidate") | F12: =COUNTIF('17_vendor_foods'!G4:G503,"verified") | G12: =IF(OR(C12="",E12=0),"",E12/C12) | H12: =IF(OR(D12="",F12=0),"",F12/D12) | I12: =IF(AND(C12="",D12=""),"按覆盖核验",IF(COUNTA('17_vendor_foods'!A4:A503)=0,"待录入",IF(AND(C12<>"",E12>=C12,OR(D12="",F12>=D12)),"达到候选目标","进行中"))) | J12: 首轮建议30–50条关系候选
A13: 18_source_records | B13: 来源证据记录 | C13: 1 | E13: =COUNTIF('18_source_records'!M4:M503,"candidate") | F13: =COUNTIF('18_source_records'!M4:M503,"verified") | G13: =IF(OR(C13="",E13=0),"",E13/C13) | H13: =IF(OR(D13="",F13=0),"",F13/D13) | I13: =IF(AND(C13="",D13=""),"按覆盖核验",IF(COUNTA('18_source_records'!A4:A503)=0,"待录入",IF(AND(C13<>"",E13>=C13,OR(D13="",F13>=D13)),"达到候选目标","进行中"))) | J13: 每条首批候选至少有一个可定位来源
A14: 19_change_log | B14: 变更记录 | E14: =COUNTIF('19_change_log'!N4:N503,"candidate") | F14: =COUNTIF('19_change_log'!N4:N503,"verified") | G14: =IF(OR(C14="",E14=0),"",E14/C14) | H14: =IF(OR(D14="",F14=0),"",F14/D14) | I14: =IF(AND(C14="",D14=""),"按覆盖核验",IF(COUNTA('19_change_log'!A4:A503)=0,"待录入",IF(AND(C14<>"",E14>=C14,OR(D14="",F14>=D14)),"达到候选目标","进行中"))) | J14: 有修改、合并或降级时必须记录
A15: 22_media_assets | B15: 图片、视频等媒体素材 | E15: =COUNTIF('22_media_assets'!AH4:AH503,"candidate") | F15: =COUNTIF('22_media_assets'!AH4:AH503,"verified") | I15: 按覆盖核验 | J15: 成员1负责地点/节目/入口媒体，成员4负责菜品/商家媒体；一个文件一行
A16: 23_media_relations | B16: 媒体与业务对象关联 | E16: =COUNTIF('23_media_relations'!I4:I503,"candidate") | F16: =COUNTIF('23_media_relations'!I4:I503,"verified") | I16: 按覆盖核验 | J16: 同一媒体可关联多个对象；主媒体、排序和用途必须可追溯

Sheet 04_现有资产接入
A1: 现有资产接入判断
A2: 现有采集包可提供种子数据，但旧字段不能直接替代新项目事实。接入时必须重新标记状态、来源、有效期和跨表ID。
A4: 当前资产 | B4: 现有规模 | C4: 建议目标表 | D4: 可复用部分 | E4: 主要缺口 | F4: 接入动作
A5: 现有 scenics.csv | B5: 5个景区摘要 | C5: 10_places | D5: 可作为景区级种子候选 | E5: 缺少城市景点、夜市、餐饮街区和交通枢纽样本 | F5: 仅导入为candidate，补齐30–50个候选
A6: 现有 entrances.csv | B6: 10条入口/区入口名称 | C6: 11_place_entrances | D6: 可建立入口候选 | E6: 缺精确入口坐标，precise_navigation_eligible=false | F6: 由成员3逐条核验真实入口和坐标
A7: 现有 information_facts.csv | B7: 67条带来源字段主张 | C7: 12_open_rules | D7: 可提取开放时间、票价、预约规则候选 | E7: 同字段存在冲突，不能直接生成确定规则 | F7: 保留多个来源，状态标pending_review/conflict
A8: 现有清园/万岁山节目资料 | B8: 清园153个节目；万岁山41条介绍 | C8: 13_programs | D8: 可整理节目、舞台和说明候选 | E8: 万岁山未取得日期明确场次；舞台坐标不足 | F8: 成员1补场次，成员3补舞台地点关联
A9: 现有 shows.csv | B9: 463个2026-10-20开始时刻 | C9: 14_show_sessions | D9: 结构可直接转化为独立场次 | E9: 全部缺结束时间，仅为历史日期快照 | F9: 作为样例/历史快照，不作为未来场次保证
A10: 现有食品数据 | B10: 无 | C10: 15_food_items / 16_food_vendors / 17_vendor_foods | D10: 暂无 | E10: 菜品、商家、供应关系均缺失 | F10: 由成员4按首轮目标新建候选池
A11: 现有 sources.csv | B11: 72个来源/响应 | C11: 18_source_records | D11: 可建立来源证据基线 | E11: 授权状态不完整、部分页面抓取失败 | F11: 建立rights_status和证据路径，不默认可再发布
A12: 现有 data_issues.csv / validation报告 | B12: 60条问题项，9项结构校验 | C12: 19_change_log + 校验规则 | D12: 可复用异常分类和结构校验思路 | E12: 旧表结构与本轮10张核心表不同 | F12: 迁移为统一问题代码并保留变更历史
A15: 本次填写后的数据规模（2026-10-22初筛）
A16: 数据表 | B16: 总记录 | C16: 候选 | D16: 待审/冲突/过期 | E16: 已核实 | F16: 初筛结论
A17: 10_places | B17: 16 | C17: 8 | D17: 8 | E17: 0 | F17: 已有候选，但尚无verified记录
A18: 11_place_entrances | B18: 20 | C18: 18 | D18: 2 | E18: 0 | F18: 已有候选，但尚无verified记录
A19: 12_open_rules | B19: 19 | C19: 6 | D19: 13 | E19: 0 | F19: 已有候选，但尚无verified记录
A20: 13_programs | B20: 98 | C20: 93 | D20: 5 | E20: 0 | F20: 已有候选，但尚无verified记录
A21: 14_show_sessions | B21: 0 | C21: 0 | D21: 0 | E21: 0 | F21: 空表，存在关键覆盖缺口
A22: 15_food_items | B22: 26 | C22: 26 | D22: 0 | E22: 0 | F22: 已有候选，但尚无verified记录
A23: 16_food_vendors | B23: 32 | C23: 12 | D23: 20 | E23: 0 | F23: 已有候选，但尚无verified记录
A24: 17_vendor_foods | B24: 48 | C24: 42 | D24: 6 | E24: 0 | F24: 已有候选，但尚无verified记录
A25: 18_source_records | B25: 116 | C25: 112 | D25: 4 | E25: 0 | F25: 已有候选，但尚无verified记录
A26: 19_change_log | B26: 464 | C26: 0 | D26: 464 | E26: 0 | F26: 已有候选，但尚无verified记录

Sheet 10_places
A1: 地点主表 places
A2: 仅收集候选与核实数据；不得把格式正确误判为事实真实。导入前请运行校验脚本。
A3: place_id | B3: name | C3: place_type | D3: parent_place_id | E3: address | F3: lng | G3: lat | H3: crs | I3: aliases | J3: external_poi_id | K3: indoor_outdoor | L3: suggested_stay_min | M3: description | N3: source_id | O3: validation_status | P3: verified_at | Q3: valid_from | R3: valid_to | S3: reviewer | T3: version | U3: notes
A4: pl_000001 | B4: 清明上河园 | C4: scenic_spot | E4: 河南省开封市龙亭西路5号 | I4: 清园 | K4: unknown | M4: 国家5A级旅游景区，以《清明上河图》为蓝本1:1复原的大型宋代历史文化主题公园，占地超过540亩。 | N4: src_000004 | O4: candidate | S4: 成员1 | T4: 1 | U4: 官网地址与介绍；官网另提到端门、丹凤门等门名，未明确为游客入口；坐标未取得，待成员3核验。
A5: pl_000002 | B5: 万岁山武侠城 | C5: scenic_spot | E5: 河南省开封市龙亭区东京大道中段 | I5: 万岁山；大宋武侠城 | K5: unknown | M5: 以武侠文化为核心的景区，包含江湖狂欢艺术区、武侠影视街区、山水田园区、仙侠奇境区、水浒区、十里洋场区等主题区。 | N5: src_000010 | O5: candidate | S5: 成员1 | T5: 1 | U5: 官网首页地址；入口名单见 src_000011；坐标未取得，待成员3核验；官网首页标注 8:00~21:00 检票时间。
A6: pl_000003 | B6: 开封府 | C6: scenic_spot | E6: 河南省开封市鼓楼区包公东湖北岸 | I6: 开封府景区；南衙 | K6: unknown | M6: 国家4A级旅游景区，北宋管理国都及京畿地区的重要机构复原，被誉为“天下首府”。 | N6: src_000015 | O6: candidate | S6: 成员1 | T6: 1 | U6: 官网地址；日间/夜游时间与票价见 src_000015/000016；入口只确认府门，其他入口待核验；坐标待成员3。
A7: pl_000004 | B7: 龙亭景区 | C7: scenic_spot | E7: 开封市宋都御街北段 | I7: 龙亭公园；开封市龙亭景区 | K7: unknown | M7: 国家AAAA级旅游景区，集皇家园林、历史文物和秀美风光于一体，历史上曾是六个朝代的皇宫所在地，距今1200多年。 | N7: src_000019 | O7: candidate | S7: 成员1 | T7: 1 | U7: 官网地址/介绍；开放时间、票价、入口见 src_000018；坐标待成员3；节目时间待公众号节目单。
A8: pl_000005 | B8: 大相国寺 | C8: scenic_spot | E8: 河南省开封市鼓楼区自由路西段36号 | I8: 相国寺；开封大相国寺 | K8: unknown | M8: 中国汉传佛教十大名寺之一，国家4A级旅游景区，始建于北齐天保六年（555年），北宋时期为皇家寺院。 | N8: src_000023 | O8: pending_review | S8: 成员1 | T8: 1 | U8: 官方官网域名已失效；政府名录确认4A（src_000021）、省退役军人事务厅确认鼓楼区（src_000022）；地址/时间/票价来自OTA（src_000023/000024），待官方核实。入口/坐标未找到官方来源。
A9: pl_000006 | B9: 铁塔景区 | C9: scenic_spot | E9: 河南省开封市顺河回族区北门大街210号 | I9: 铁塔公园；开封铁塔 | K9: unknown | M9: 国家4A级旅游景区，以现存铁塔（开宝寺塔）为核心的名胜古迹公园；铁塔为全国重点文物保护单位，高55.08米、八角十三层。 | N9: src_000026 | O9: pending_review | S9: 成员1 | T9: 1 | U9: 政府名录确认4A（src_000021）；地址/活动来自本地宝（src_000027）；时间/票价来自河南交通广播转述的景区公告（src_000026）；官网 kaifengtieta.com 无法访问，待官方核实。
A10: pl_000007 | B10: 中国翰园碑林 | C10: scenic_spot | E10: 河南省开封市龙亭区龙亭北路15号 | I10: 翰园碑林；中国翰园 | K10: unknown | M10: 国家4A级旅游景区，集书画碑刻艺术与古典园林建筑于一体的文化园林，占地120亩，刻碑4000多块。 | N10: src_000030 | O10: candidate | S10: 成员1 | T10: 1 | U10: 官网地址/电话/开放时间（src_000030）；介绍（src_000028）；入口（src_000029）；票价来自OTA（src_000031），待官方；坐标待成员3。
A11: pl_000008 | B11: 包公祠 | C11: scenic_spot | E11: 河南省开封市鼓楼区向阳路1号 | I11: 开封包公祠；包公祠景区 | K11: unknown | M11: 国家4A级旅游景区，纪念北宋名臣包拯的祠堂，位于包公湖西畔，占地1公顷多，由大殿、二殿、东西配殿、半壁廊、碑亭组成。 | N11: src_000032 | O11: candidate | S11: 成员1 | T11: 1 | U11: 政府/旅游网确认4A、地址、介绍（src_000032/000034）；季节时间和线上票价来自大河票务（src_000033），待官方；入口/坐标待核实。
A12: pl_000009 | B12: 天波杨府 | C12: scenic_spot | E12: 河南省开封市龙亭区龙亭北路14号 | I12: 开封天波杨府；天波府 | K12: unknown | M12: 北宋抗辽名将杨业府邸的仿宋重建建筑群，国家4A级旅游景区，由中院府衙、西院花园、东院演兵场组成。 | N12: src_000035 | O12: pending_review | S12: 成员1 | T12: 1 | U12: 政府名录确认4A（src_000021）、省退役军人事务厅确认龙亭区（src_000036）；地址/时间/介绍来自去哪儿（src_000035）；电话/旧信息来自河南景区详情（src_000037）；官网多个候选域名均无法解析；坐标/入口待核实。
A13: pl_000010 | B13: 开封城墙 | C13: scenic_spot | E13: 河南省开封市龙亭区大梁路与内顺城路交叉口 | I13: 开封城墙景区；宋都城墙 | K13: mixed | M13: 全国重点文物保护单位，开封城墙景区开放大梁门至安远门段，含古马道遗址、大梁门、玻璃栈道等。 | N13: src_000038 | O13: candidate | S13: 成员1 | T13: 1 | U13: 官网游玩指南：夏8:30-22:00/冬8:30-21:30，票价40/20，四个登城口；政府A级名录为3A，另有2024年升4A说法待核实；坐标待成员3。
A14: pl_000011 | B14: 山陕甘会馆 | C14: scenic_spot | E14: 河南省开封市龙亭区徐府街85号 | I14: 开封山陕甘会馆 | K14: unknown | M14: 全国重点文物保护单位，清代晋陕甘三省商帮会馆，以砖、石、木雕“三绝”著称，现存照壁、戏楼、牌楼、正殿等。 | N14: src_000040 | O14: candidate | S14: 成员1 | T14: 1 | U14: 政府页确认地址/介绍（src_000040）、省退役军人事务厅确认龙亭区/优待免票（src_000041）；开放时间和票价来自大河票务（src_000042），待官方；政府A级名录为2A，第三方称4A，待核实；入口/坐标待补。
A15: pl_000012 | B15: 延庆观 | C15: scenic_spot | E15: 河南省开封市鼓楼区观前街53号 | I15: 开封延庆观；重阳观 | K15: unknown | M15: 全国重点文物保护单位，元代玉皇阁为开封现存唯一元代建筑，与北京白云观、四川常道观并称中国三大名观。 | N15: src_000044 | O15: pending_review | S15: 成员1 | T15: 1 | U15: 政府A级名录为2A（src_000021）；忆起追迹称2012年AAA，待核实；地址/时间/票价来自忆起追迹/要出发（src_000043/000045），待官方；入口/坐标待补。
... A19: pl_000016 | B19: 汴梁小宋城 | C19: food_street | E19: 河南省开封市大梁路西段（郑开大道与夷山大街交汇处附近） | I19: 小宋城；开封小宋城 | K19: mixed | M19: 由原东京艺术中心改造的文商旅综合体，约5万平方米，其中2万平方米为特色民俗餐饮街区，汇集开封及各地小吃，并有《千回大宋》演出。 | N19: src_000057 | O19: pending_review | S19: 成员1 | T19: 1 | U19: 媒体/OTA：面积、餐饮街区、演出；地址来自永安/大河（src_000058/000059）；区划有金明区/龙亭区说法；官方独立网站未找到；坐标/入口待补。

Sheet 11_place_entrances
A1: 入口表 place_entrances
A2: 仅收集候选与核实数据；不得把格式正确误判为事实真实。导入前请运行校验脚本。
A3: entrance_id | B3: place_id | C3: name | D3: entrance_type | E3: lng | F3: lat | G3: crs | H3: is_main_entrance | I3: access_rules | J3: stop_entry_before | K3: open_rule_id | L3: source_id | M3: validation_status | N3: verified_at | O3: notes
A4: ent_000001 | B4: pl_000001 | C4: 迎宾门 | D4: main_entrance | H4: true | I4: 游客入口；东大门；每天9:00开园迎宾仪式地点 | K4: or_000001 | L4: src_000004 | M4: candidate | O4: 官方称东大门、开园迎宾；坐标为空白，待成员3核验。
A5: ent_000002 | B5: pl_000001 | C5: 金水门 | D5: secondary_entrance | H5: unknown | I5: 游客入口；西门 | K5: or_000001 | L5: src_000004 | M5: candidate | O5: 官方称与迎宾门对应的西门；是否主入口未明确；坐标待核验。
A6: ent_000003 | B6: pl_000002 | C6: 西大门 | D6: main_entrance | H6: unknown | I6: 游客入口；官方公告建议优先从东门、西门、中门进入（客流量较小） | K6: or_000002 | L6: src_000011 | M6: candidate | O6: 官方2025-12-19《一个景区有七个入口》文章；名单来自文中地图图片；坐标待成员3核验。
A7: ent_000004 | B7: pl_000002 | C7: 南大门 | D7: main_entrance | H7: unknown | I7: 游客入口；园区大门之一 | K7: or_000002 | L7: src_000011 | M7: candidate | O7: 官方2025-12-19《一个景区有七个入口》文章；名单来自文中地图图片；坐标待成员3核验。
A8: ent_000005 | B8: pl_000002 | C8: 中门 | D8: main_entrance | H8: unknown | I8: 游客入口；官方公告建议优先从东门、西门、中门进入（客流量较小） | K8: or_000002 | L8: src_000011 | M8: candidate | O8: 官方2025-12-19《一个景区有七个入口》文章；名单来自文中地图图片；坐标待成员3核验。
A9: ent_000006 | B9: pl_000002 | C9: 东大门 | D9: main_entrance | H9: unknown | I9: 游客入口；官方公告建议优先从东门、西门、中门进入（客流量较小） | K9: or_000002 | L9: src_000011 | M9: candidate | O9: 官方2025-12-19《一个景区有七个入口》文章；名单来自文中地图图片；坐标待成员3核验。
A10: ent_000007 | B10: pl_000002 | C10: 水浒区入口 | D10: area_entrance | H10: unknown | I10: 游客入口；按行程选择最近入口 | K10: or_000002 | L10: src_000011 | M10: candidate | O10: 官方2025-12-19《一个景区有七个入口》文章；名单来自文中地图图片；坐标待成员3核验。
A11: ent_000008 | B11: pl_000002 | C11: 仙侠区入口 | D11: area_entrance | H11: unknown | I11: 游客入口；按行程选择最近入口 | K11: or_000002 | L11: src_000011 | M11: candidate | O11: 官方2025-12-19《一个景区有七个入口》文章；名单来自文中地图图片；坐标待成员3核验。
A12: ent_000009 | B12: pl_000002 | C12: 江湖艺术区入口 | D12: area_entrance | H12: unknown | I12: 游客入口；按行程选择最近入口 | K12: or_000002 | L12: src_000011 | M12: candidate | O12: 官方2025-12-19《一个景区有七个入口》文章；名单来自文中地图图片；坐标待成员3核验。
A13: ent_000010 | B13: pl_000003 | C13: 府门 | D13: main_entrance | H13: true | I13: 游客入口；凭身份证刷府门入口闸机入园 | K13: or_000003 | L13: src_000016 | M13: candidate | O13: 官方预约购票页明确“府门入口处闸机”；其他入口未在官网找到，待核验。
A14: ent_000011 | B14: pl_000004 | C14: 南门 | D14: main_entrance | H14: unknown | I14: 游客入口；南门及相邻停车场 | K14: or_000005 | L14: src_000018 | M14: candidate | O14: 官方游园指南明确南门、北门均可进入；坐标为空白，待成员3核验。
A15: ent_000012 | B15: pl_000004 | C15: 北门 | D15: main_entrance | H15: unknown | I15: 游客入口；北门及相邻停车场 | K15: or_000005 | L15: src_000018 | M15: candidate | O15: 官方游园指南明确南门、北门均可进入；坐标为空白，待成员3核验。
... A23: ent_000020 | B23: pl_000010 | C23: 安远门登城口 | D23: secondary_entrance | H23: unknown | I23: 游客登城口；安远门 | K23: or_000013 | L23: src_000038 | M23: candidate | O23: 官方游玩指南列出；坐标待成员3。

Sheet 12_open_rules
A1: 开放与入场规则 open_rules
A2: 仅收集候选与核实数据；不得把格式正确误判为事实真实。导入前请运行校验脚本。
A3: open_rule_id | B3: place_id | C3: rule_name | D3: rule_type | E3: effective_from | F3: effective_to | G3: weekdays | H3: open_time | I3: close_time | J3: last_entry_time | K3: timezone | L3: ticket_scope | M3: reservation_required | N3: reentry_allowed | O3: special_rules | P3: source_id | Q3: validation_status | R3: verified_at | S3: version | T3: notes
A4: or_000001 | B4: pl_000001 | C4: 常规开放时间 | D4: daily | G4: 1;2;3;4;5;6;7 | H4: 09:00 | I4: 22:00 | K4: Asia/Shanghai (+08:00) | L4: 白天门票（全价票/半价票） | M4: true | N4: unknown | O4: 雨雪等天气节目可能临时更改或停演，以景区当天广播预报和微信演出通知为准；半价票适用6-18岁未成年人、全日制学生、60岁以上老人，凭有效证件。 | P4: src_000002 | Q4: pending_review | S4: 1 | T4: 开放时间09:00-22:00来自官网FAQ；实名制分时预约见 src_000007；票价全价120元/半价60元（12表无价格字段，暂记备注）；二次入园冲突：商品详情称仅限购买当天使用，2026-10-05新闻称一票游3天，待核实。
A5: or_000002 | B5: pl_000002 | C5: 常规检票/开放时间（官网首页） | D5: daily | G5: 1;2;3;4;5;6;7 | H5: 08:00 | I5: 23:00 | J5: 21:00 | K5: Asia/Shanghai (+08:00) | L5: 成人票、儿童/学生/老人/退役军人票、大马戏票、汴河游船联票、城墙观光车联票（官方公众号购票入口） | M5: unknown | N5: true | O5: 官网首页标注“8:00~21:00 检票时间”；官方公众号购票入口显示：万岁山武侠城入园时间08:00-21:00，园区开放至23:00；自核销当日起3个自然日内不限次入园；下单后不支持改期。停车换乘：复兴三号换乘停车场周一至周五 8:00-22:00，周末及节假日 8:00-23:00；景区门口提供免费接驳车（约每15分钟一班，招手即停）。 | P5: src_000013 | Q5: pending_review | S5: 1 | T5: 官网首页：8:00~21:00 检票时间。官方公众号“购票”入口跳转美团页面：列表页显示08:00-23:00开放、最晚21:00入园；成人票详情显示万岁山入园时间08:00-21:00、自核销当日起3个自然日内不限次入园、无需换票、未使用可随时全额退款、过期后1天自动退款、下单后不支持改期。票价：成人100起/优惠50起/大马戏118或80起/汴河游船联票128或68起/城墙观光车联票120或70起。预约规则未展示。
A6: or_000003 | B6: pl_000003 | C6: 日场常规（官网参观导览） | D6: daily | G6: 1;2;3;4;5;6;7 | H6: 07:30 | I6: 19:00 | J6: 17:30 | K6: Asia/Shanghai (+08:00) | L6: 日间票（成人65元/学生32元） | M6: unknown | N6: unknown | O6: 冬季 7:30–17:30；官网另有夏季 7:00–19:00、入园时间 07:00–19:00（冬季 7:30–18:30）等口径，存在冲突；夜游 17:00 开售、22:00 闭园；节目变动以当天预告为准。 | P6: src_000016 | Q6: conflict | S6: 1 | T6: 官网首页：7:30–19:00（春、夏、秋）、7:30–17:30（冬）；预约购票页：7:30–22:00、17:30停止入园；参观指南：夏季7:00–19:00、冬季7:30–18:30。先按日场7:30–19:00、17:30停止入园记录，冲突待核实。
A7: or_000004 | B7: pl_000003 | C7: 夜游《南衙千秋月》 | D7: daily | G7: 1;2;3;4;5;6;7 | H7: 17:00 | I7: 22:00 | K7: Asia/Shanghai (+08:00) | L7: 夜游票（成人90元/半价45元，全天不限次入园） | M7: unknown | N7: true | O7: 各类优惠证件不可使用，需购全价票入园；夜游22:00闭园。 | P7: src_000015 | Q7: candidate | S7: 1 | T7: 官网首页/预约购票页：夜游17:00开售、22:00闭园，门票90元/半价45元，全天不限次入园；是否每日开放待确认。
A8: or_000005 | B8: pl_000004 | C8: 常规开放时间（官网游园指南） | D8: daily | G8: 1;2;3;4;5;6;7 | H8: 08:00 | I8: 21:30 | K8: Asia/Shanghai (+08:00) | L8: 全票45元/半价22元（节会期间按实际票价） | M8: unknown | N8: unknown | O8: 节会期间门票按实际票价；南门、北门均可入园；节目单需关注龙亭景区公众号，官网未列具体时间。 | P8: src_000018 | Q8: candidate | S8: 1 | T8: 官网游园指南：开放08:00-21:30，全票45/半价22；免票/半票规则见页面；节目单需公众号。
A9: or_000006 | B9: pl_000005 | C9: 夏季开放时间（OTA口径，待官方核实） | D9: daily | G9: 1;2;3;4;5;6;7 | H9: 08:00 | I9: 18:00 | J9: 18:00 | K9: Asia/Shanghai (+08:00) | L9: 成人40元/半价20元（官方小程序） | M9: unknown | N9: unknown | O9: 官方小程序：无需取票，二维码/身份证刷闸机入园；门票仅限当日有效；未使用可随时退，刷码后不退；半价票适用6-18岁未成年人、全日制学生、教师等（凭证件）。 | P9: src_000051 | Q9: candidate | S9: 1 | T9: 官方小程序购票须知：开放8:00-18:00，票价40/20，当日有效。
A10: or_000007 | B10: pl_000005 | C10: 冬季开放时间（OTA口径，待官方核实） | D10: date_range | E10: 2026-11-01 | F10: 2027-03-10 | G10: 1;2;3;4;5;6;7 | H10: 08:00 | I10: 18:00 | J10: 17:00 | K10: Asia/Shanghai (+08:00) | L10: 成人约40元/优待约20元（OTA线上37.5/19，待官方） | M10: unknown | N10: unknown | O10: 夏季 3/11-10/31 08:00-18:30，18:00停止入园；春秋季 08:00-18:00、17:30停止入园（去哪儿口径）；以景区当日公告为准。 | P10: src_000023 | Q10: expired | S10: 1 | T10: 官方小程序统一8:00-18:00；原OTA冬季规则作废。
A11: or_000008 | B11: pl_000006 | C11: 常规营业时间（景区公告，待官方核实） | D11: daily | G11: 1;2;3;4;5;6;7 | H11: 08:30 | I11: 21:00 | K11: Asia/Shanghai (+08:00) | L11: 成人30元/半价15元（官方门票公示牌） | M11: unknown | N11: unknown | O11: 节假日/特殊活动另行通知；铁塔光影秀已暂停演出，恢复时间另行通知；登塔另收费/是否开放待核实。 | P11: src_000055 | Q11: candidate | S11: 1 | T11: 景区客服回复：当前8:30-21:00；《五灵寻禅》10:00-17:00，周一NPC休息；门票公示牌全价30/半价15；节目以当天广播为准。
A12: or_000009 | B12: pl_000007 | C12: 常规开放时间（官网页脚） | D12: daily | G12: 1;2;3;4;5;6;7 | H12: 08:00 | I12: 22:00 | K12: Asia/Shanghai (+08:00) | L12: 成人40元/优待20元（OTA口径，待官方） | M12: unknown | N12: unknown | O12: 菊花文化节、春节庙会等节会期间活动和时间另行公告；南大门、北大门均可入园。 | P12: src_000030 | Q12: candidate | S12: 1 | T12: 官网全站页脚：开放8:00-22:00；票价来自大河票务（成人40/优待20），待官方；第三方称21:00停止入园，官网未写。
A13: or_000010 | B13: pl_000008 | C13: 春夏秋季开放时间（OTA口径，待官方） | D13: date_range | E13: 2026-04-01 | F13: 2026-10-31 | G13: 1;2;3;4;5;6;7 | H13: 07:00 | I13: 19:00 | K13: Asia/Shanghai (+08:00) | L13: 成人线上27元/门市约30元（OTA口径，待官方） | M13: unknown | N13: unknown | O13: 冬季 11/1-3/31 07:30-17:30；政府/旅游网旧页面写7:00-19:00、门票20元；以景区当日公告为准。 | P13: src_000033 | Q13: pending_review | S13: 1 | T13: 大河票务2025-06-05；官网 kfbgc.cn 返回403打不开；政府/旅游网信息较旧。
A14: or_000011 | B14: pl_000008 | C14: 冬季开放时间（OTA口径，待官方） | D14: date_range | E14: 2026-11-01 | F14: 2027-03-31 | G14: 1;2;3;4;5;6;7 | H14: 07:30 | I14: 17:30 | K14: Asia/Shanghai (+08:00) | L14: 成人线上27元/门市约30元（OTA口径，待官方） | M14: unknown | N14: unknown | O14: 春夏秋季 4/1-10/31 07:00-19:00；政府/旅游网旧页面写7:00-19:00、门票20元；以景区当日公告为准。 | P14: src_000033 | Q14: pending_review | S14: 1 | T14: 大河票务2025-06-05；官网 kfbgc.cn 返回403打不开；政府/旅游网信息较旧。
A15: or_000012 | B15: pl_000009 | C15: 常规开放时间（OTA口径，待官方） | D15: daily | G15: 1;2;3;4;5;6;7 | H15: 08:00 | I15: 22:00 | J15: 21:30 | K15: Asia/Shanghai (+08:00) | L15: 成人约30-40元/优待约20元（OTA口径不一致，待官方） | M15: unknown | N15: unknown | O15: 去哪儿标08:00-22:00、21:30停止入园；其他平台有08:00-18:30、夜游延至22:00等口径；以景区当日公告为准。 | P15: src_000035 | Q15: pending_review | S15: 1 | T15: 官网 tianboyangfu.com、tianbo.kf.cn、tbyf.cn 均无法解析；时间来自去哪儿/其他OTA，待官方核实。
A16: or_000013 | B16: pl_000010 | C16: 常规开放时间（官网游玩指南） | D16: daily | G16: 1;2;3;4;5;6;7 | H16: 08:30 | I16: 22:00 | K16: Asia/Shanghai (+08:00) | L16: 全价40元/半价20元 | M16: unknown | N16: unknown | O16: 冬季 08:30-21:30；季节起止以景区公告为准；四个登城口开放时间可能不同；《微梦大梁门》是否另收费，官网未写。 | P16: src_000038 | Q16: candidate | S16: 1 | T16: 官网游玩指南：夏8:30-22:00，冬8:30-21:30；票价40/20；登城口四个；微梦/古马道为景区内影片。
A17: or_000014 | B17: pl_000011 | C17: 常规开放时间（OTA口径，待官方） | D17: daily | G17: 1;2;3;4;5;6;7 | H17: 08:00 | I17: 18:00 | K17: Asia/Shanghai (+08:00) | L17: 成人约22-25元（OTA口径，待官方） | M17: unknown | N17: unknown | O17: 冬季约 08:00-17:30；季节起止和票价以景区当日公告为准；优待证持证人免门票（省退役军人事务厅）。 | P17: src_000042 | Q17: pending_review | S17: 1 | T17: 大河票务：全年08:00-18:00/08:00-17:30；政府页未给时间；待官方核实。
A18: or_000015 | B18: pl_000012 | C18: 常规开放时间（网络资料，待官方） | D18: daily | G18: 1;2;3;4;5;6;7 | H18: 08:00 | I18: 18:30 | K18: Asia/Shanghai (+08:00) | L18: 成人约15-35元（口径不一，待官方） | M18: unknown | N18: unknown | O18: 另有09:00-17:30口径；票价有15/30/35三种说法；以景区当日公告为准。 | P18: src_000043 | Q18: pending_review | S18: 1 | T18: 忆起追迹/要出发写8:00-18:30；相约久久/百度写9:00-17:30；无独立官网，待官方核实。
A19: or_000016 | B19: pl_000013 | C19: 夜市营业时间（平台口径，待现场核实） | D19: daily | G19: 1;2;3;4;5;6;7 | H19: 10:00 | I19: 22:00 | K19: Asia/Shanghai (+08:00) | L19: 免费进入（摊位消费） | M19: unknown | N19: unknown | O19: 携程标全年10:00-22:00；实际夜市约傍晚开始至午夜，以现场摊位为准。 | P19: src_000049 | Q19: pending_review | S19: 1 | T19: 携程页面；实际营业时间与平台标注可能不同。
A20: or_000017 | B20: pl_000014 | C20: 夜市营业时间（第三方口径，待现场核实） | D20: daily | G20: 1;2;3;4;5;6;7 | H20: 17:30 | I20: 23:30 | K20: Asia/Shanghai (+08:00) | L20: 免费进入（摊位消费） | M20: unknown | N20: unknown | O20: 百家号写“天黑而聚，凌晨而散”；第三方攻略称17:30-23:30，早餐约6:00-9:30；以现场摊位为准。 | P20: src_000050 | Q20: pending_review | S20: 1 | T20: 百家号没有精确时间；17:30-23:30来自第三方攻略口径，待现场核实。
A21: or_000018 | B21: pl_000015 | C21: 夜市营业时间（第三方口径，待现场核实） | D21: daily | G21: 1;2;3;4;5;6;7 | H21: 18:30 | I21: 01:00 | K21: Asia/Shanghai (+08:00) | L21: 免费进入（摊位消费） | M21: unknown | N21: unknown | O21: 跨日营业（18:30-次日1:00）；实际收摊时间以摊位为准；本地宝未写具体时间，时间为第三方攻略口径。 | P21: src_000056 | Q21: pending_review | S21: 1 | T21: 第三方攻略/百度百科称18:30-次日1:00；本地宝只写地址/规模；待现场核实。
A22: or_000019 | B22: pl_000016 | C22: 营业时间（第三方口径，待官方） | D22: daily | G22: 1;2;3;4;5;6;7 | H22: 10:00 | I22: 23:30 | K22: Asia/Shanghai (+08:00) | L22: 免费入场（餐饮/演出另付） | M22: unknown | N22: unknown | O22: 《千回大宋》每晚20:00-21:20，票面188/288元；节假日/演出调整以现场为准。 | P22: src_000059 | Q22: pending_review | S22: 1 | T22: 第三方平台称10:00-23:30；永安页面未列具体时间；待官方核实。

Sheet 13_programs
A1: 节目表 programs
A2: 仅收集候选与核实数据；不得把格式正确误判为事实真实。导入前请运行校验脚本。
A3: program_id | B3: park_place_id | C3: stage_place_id | D3: name | E3: category | F3: description | G3: arrival_buffer_min | H3: ticket_scope | I3: source_id | J3: validation_status | K3: valid_from | L3: valid_to | M3: reviewer | N3: version | O3: notes
A4: prg_000001 | B4: pl_000001 | D4: 包公迎宾 | E4: performance | F4: 开封府尹包拯奉旨领文武百官，设皇家仪仗，行开园大典，迎四海宾客。 | H4: 待核实 | I4: src_000002 | J4: candidate | M4: 成员1 | N4: 1 | O4: 官方情景展示时间表：09:00；地点：迎宾门外广场；常规节目，官方未公布逐日场次，按工作簿规则不建14表场次。介绍见 src_000003。
A5: prg_000002 | B5: pl_000001 | D5: 包公巡视汴河漕运 | E5: performance | F5: 以北宋汴河漕运为背景的水上巡游演出。 | H5: 待核实 | I5: src_000002 | J5: candidate | M5: 成员1 | N5: 1 | O5: 时间：09:20；地点：虹桥两侧水面；常规节目，未公布逐日场次。介绍见 src_000003。
A6: prg_000003 | B6: pl_000001 | D6: 宋廷梦乐 | E6: performance | F6: 以宋词为引子，融合箫、笛、埙、古琴、古筝、编磬等宋朝主流乐器的皇家乐典。 | H6: 待核实 | I6: src_000002 | J6: candidate | M6: 成员1 | N6: 1 | O6: 时间：10:20,11:40,14:50,16:35；地点：宣德殿二层；常规节目，未公布逐日场次。介绍见 src_000003。
A7: prg_000004 | B7: pl_000001 | D7: 王员外招婿 | E7: performance | F7: 王员外搭绣楼为女儿招亲的互动演出。 | H7: 待核实 | I7: src_000002 | J7: candidate | M7: 成员1 | N7: 1 | O7: 时间：11:45,15:40,16:50；地点：王员外家；常规节目，未公布逐日场次。介绍见 src_000003。
A8: prg_000005 | B8: pl_000001 | D8: 岳飞枪挑小梁王 | E8: performance | F8: 以岳飞武举科考为背景的实景演出。 | H8: 待核实 | I8: src_000002 | J8: candidate | M8: 成员1 | N8: 1 | O8: 时间：10:50,16:10；地点：大宋·校场；常规节目，未公布逐日场次。介绍见 src_000003。
A9: prg_000006 | B9: pl_000001 | D9: 大宋·东京保卫战 | E9: performance | F9: 运用火药、威亚、攻城、跳河等电影特效的战争实景演出。 | H9: 待核实 | I9: src_000002 | J9: candidate | M9: 成员1 | N9: 1 | O9: 时间：10:00,17:20；地点：九龙桥西南水面；常规节目，未公布逐日场次。介绍见 src_000003。
A10: prg_000007 | B10: pl_000001 | D10: 清明上河园大巡游 | E10: performance | F10: 园区大型巡游演出。 | H10: 待核实 | I10: src_000002 | J10: candidate | M10: 成员1 | N10: 1 | O10: 时间：14:00；路线：虹桥南广场至双宣殿；常规节目，未公布逐日场次。
A11: prg_000008 | B11: pl_000001 | D11: 打铁花之盛世大宋 | E11: performance | F11: 国家级非物质文化遗产打铁花表演。 | H11: 待核实 | I11: src_000002 | J11: candidate | M11: 成员1 | N11: 1 | O11: 时间：21:00；地点：九龙桥西南水面；常规节目，未公布逐日场次。介绍见 src_000003。
A12: prg_000009 | B12: pl_000001 | D12: 大宋·东京梦华 | E12: performance | F12: 大型水上实景演出，全剧70分钟，700多名演员参与，以八阕宋词和《清明上河图》串联。 | H12: 《大宋·东京梦华》演出票（是否含景区门票待核实） | I12: src_000009 | J12: candidate | M12: 成员1 | N12: 1 | O12: 官方时间表标注“以景区公示为准”，未给固定时间；地点：景龙湖水面；未公布逐日场次，不建14表场次。介绍来源 src_000009；时间表来源 src_000002。
A13: prg_000010 | B13: pl_000002 | D13: 打铁花 | E13: performance | F13: 流传于豫晋地区的国家级非物质文化遗产，起源于北宋；艺人将生铁熔化成约1600℃的铁水，击打后形成火树银花。 | H13: 待核实 | I13: src_000012 | J13: candidate | M13: 成员1 | N13: 1 | O13: 官方节目单（水浒区·城寨沙场）：19:30/21:00/22:15（待定），30分钟，需预约；常规时刻，不是逐日场次。介绍来源 src_000012；节目单来源 src_000014。
A14: prg_000011 | B14: pl_000002 | D14: 三打祝家庄 | E14: performance | F14: 大型水浒实景剧，地点在城寨沙场，演出时长约30分钟，融合马战、步兵战、攻城战、全景式爆破、飞火流星、云梯炮战等实景特效，上百名演员、十几匹马参与。 | H14: 待核实 | I14: src_000012 | J14: candidate | M14: 成员1 | N14: 1 | O14: 官方节目单（水浒区·城寨沙场）：11:00/14:00（待定）/17:00，30分钟，需预约；常规时刻，不是逐日场次。介绍来源 src_000012；节目单来源 src_000014。
A15: prg_000012 | B15: pl_000002 | D15: 王婆说媒 | E15: performance | F15: 无剧本、无托儿的沉浸互动相亲类演出，由王婆扮演者赵梅主持，现场随机招募单身男女嘉宾。 | H15: 待核实 | I15: src_000012 | J15: candidate | M15: 成员1 | N15: 1 | O15: 官方节目单：水浒区页面显示“今日停演”；仙侠奇境区·魔力广场 16:30，90分钟。常规时刻，不是逐日场次。介绍来源 src_000012；节目单来源 src_000014。
... A19: prg_000016 | B19: pl_000002 | D19: 室内三大剧场 | E19: performance | F19: 戏剧剧场演绎《贵妃醉酒》《坐宫》等；T台剧场呈现《抽象行走》《量子纠缠》《花语走秀》等；粮仓剧场上演《岳飞的呐喊》和沙画。 | H19: 待核实 | I19: src_000012 | J19: candidate | M19: 成员1 | N19: 1 | O19: 官方节目单按戏曲剧场/舞秀剧场/音乐广场分列；代表场次：剪韵华裳15:35/16:35/17:30/20:00/20:50/21:25；花语走秀18:30/19:15；量子纠缠09:45/10:45/11:50/12:50/14:10/16:00/17:00。常规时刻，不是逐日场次。介绍来源 src_000012；节目单来源 src_000014。
A20: prg_000017 | B20: pl_000002 | D20: 祭火迎神 | E20: performance | H20: 待核实 | I20: src_000010 | J20: candidate | M20: 成员1 | N20: 1 | O20: 官方节目单（水浒区·武侠广场）：19:30（待定）/21:00（待定）/22:15（待定），10分钟；常规时刻，不是逐日场次。介绍来源 src_000010；节目单来源 src_000014。
A21: prg_000018 | B21: pl_000002 | D21: 林冲战杨志 | E21: performance | H21: 待核实 | I21: src_000010 | J21: candidate | M21: 成员1 | N21: 1 | O21: 官方节目单（水浒区·水浒街）：10:15，10分钟；常规时刻，不是逐日场次。介绍来源 src_000010；节目单来源 src_000014。
A22: prg_000019 | B22: pl_000002 | D22: 二娘的秀 | E22: performance | H22: 待核实 | I22: src_000010 | J22: candidate | M22: 成员1 | N22: 1 | O22: 官方节目单（水浒区·武侠广场）：17:30，90分钟；常规时刻，不是逐日场次。介绍来源 src_000010；节目单来源 src_000014。
A23: prg_000020 | B23: pl_000003 | D23: 开衙迎宾 | E23: performance | F23: 开封府开衙迎宾仪式。 | H23: 日间票 | I23: src_000016 | J23: candidate | M23: 成员1 | N23: 1 | O23: 官方节目单：09:00；地点：府门广场；常规时刻，不是逐日场次。节目单来源 src_000016。
A24: prg_000021 | B24: pl_000003 | D24: 包公断案（铡美案） | E24: performance | F24: 包公断案实景演出《铡美案》。 | H24: 日间票 | I24: src_000016 | J24: candidate | M24: 成员1 | N24: 1 | O24: 官方节目单：09:30；地点：大堂；常规时刻，不是逐日场次。节目单来源 src_000016。
A25: prg_000022 | B25: pl_000003 | D25: 《闸口盘车案》影院版 | E25: performance | F25: 全息影院版《闸口盘车案》。 | H25: 日间票 | I25: src_000016 | J25: candidate | M25: 成员1 | N25: 1 | O25: 官方节目单：09:40/11:55/16:30；地点：全息剧场；常规时刻，不是逐日场次。节目单来源 src_000016。 需提前到全息剧场门口预约取票。
A26: prg_000023 | B26: pl_000003 | D26: 太子迎驾 | E26: performance | F26: 太子迎驾情景演出。 | H26: 日间票 | I26: src_000016 | J26: candidate | M26: 成员1 | N26: 1 | O26: 官方节目单：10:00；地点：太子读书台；常规时刻，不是逐日场次。节目单来源 src_000016。
A27: prg_000024 | B27: pl_000003 | D27: 榜前捉婿 | E27: performance | F27: 明礼院榜前捉婿互动演出。 | H27: 日间票 | I27: src_000016 | J27: candidate | M27: 成员1 | N27: 1 | O27: 官方节目单：10:30/15:30；地点：明礼院；常规时刻，不是逐日场次。节目单来源 src_000016。
A28: prg_000025 | B28: pl_000003 | D28: 《闸口盘车案》剧场版 | E28: performance | F28: 全息剧场版《闸口盘车案》。 | H28: 日间票 | I28: src_000016 | J28: candidate | M28: 成员1 | N28: 1 | O28: 官方节目单：11:00/14:30/17:30；地点：全息剧场；常规时刻，不是逐日场次。节目单来源 src_000016。
A29: prg_000026 | B29: pl_000003 | D29: 太极功夫 | E29: performance | F29: 天庆观太极功夫表演。 | H29: 日间票 | I29: src_000016 | J29: candidate | M29: 成员1 | N29: 1 | O29: 官方节目单：11:00/15:00；地点：天庆观；常规时刻，不是逐日场次。节目单来源 src_000016。
A30: prg_000027 | B30: pl_000003 | D30: 演武迎宾 | E30: performance | F30: 英武楼演武迎宾表演。 | H30: 日间票 | I30: src_000016 | J30: candidate | M30: 成员1 | N30: 1 | O30: 官方节目单：11:35/16:40；地点：英武楼；常规时刻，不是逐日场次。节目单来源 src_000016。
A31: prg_000028 | B31: pl_000003 | D31: 包公巡衙之巧遇苏轼 | E31: performance | F31: 包公巡衙途中巧遇苏轼的情景演出。 | H31: 日间票 | I31: src_000016 | J31: candidate | M31: 成员1 | N31: 1 | O31: 官方节目单：12:30/17:00；地点：街道司；常规时刻，不是逐日场次。节目单来源 src_000016。
A32: prg_000029 | B32: pl_000003 | D32: 包公断案（铡赵王） | E32: performance | F32: 包公断案实景演出《铡赵王》。 | H32: 日间票 | I32: src_000016 | J32: candidate | M32: 成员1 | N32: 1 | O32: 官方节目单：14:00；地点：大堂；常规时刻，不是逐日场次。节目单来源 src_000016。
A33: prg_000030 | B33: pl_000003 | D33: 水月云天舞+音乐喷泉秀 | E33: performance | F33: 明镜湖水月云天舞与音乐喷泉秀。 | H33: 夜游票《南衙千秋月》 | I33: src_000016 | J33: candidate | M33: 成员1 | N33: 1 | O33: 官方节目单：18:00；地点：明镜湖；常规时刻，不是逐日场次。节目单来源 src_000016。
A34: prg_000031 | B34: pl_000003 | D34: 一座府·天下首府 | E34: performance | F34: 大堂夜间实景演出《一座府·天下首府》。 | H34: 夜游票《南衙千秋月》 | I34: src_000016 | J34: candidate | M34: 成员1 | N34: 1 | O34: 官方节目单：19:20；地点：大堂；常规时刻，不是逐日场次。节目单来源 src_000016。
A35: prg_000032 | B35: pl_000004 | D35: 太祖大典 | E35: performance | H35: 日间票 | I35: src_000019 | J35: candidate | M35: 成员1 | N35: 1 | O35: 官方节目单：16:30；地点：龙亭大殿；常规时刻，不是逐日场次。节目单来源 src_000025。
A36: prg_000033 | B36: pl_000004 | D36: 皇城司 | E36: performance | H36: 日间票 | I36: src_000019 | J36: candidate | M36: 成员1 | N36: 1 | O36: 官方节目单：11:30/17:05；地点：宣和殿；常规时刻，不是逐日场次。节目单来源 src_000025。
A37: prg_000034 | B37: pl_000004 | D37: 江山乐舞 | E37: performance | H37: 日间票 | I37: src_000019 | J37: candidate | M37: 成员1 | N37: 1 | O37: 官方节目单：14:45；地点：皇冠舞台；常规时刻，不是逐日场次。节目单来源 src_000025。
A38: prg_000035 | B38: pl_000004 | D38: 大宋科举 | E38: performance | H38: 待核实 | I38: src_000019 | J38: candidate | M38: 成员1 | N38: 1 | O38: 官方节目单未列，可能已调整/停演；待核实。
A39: prg_000036 | B39: pl_000004 | D39: 宫廷迎宾 | E39: performance | H39: 待核实 | I39: src_000019 | J39: candidate | M39: 成员1 | N39: 1 | O39: 官方节目单未列；可能与“大宋金戈·迎宾盛礼”对应，待核实。
A40: prg_000037 | B40: pl_000004 | D40: 大宋金戈·迎宾盛礼 | E40: performance | H40: 日间票 | I40: src_000025 | J40: candidate | M40: 成员1 | N40: 1 | O40: 白天：09:30；地点：午门广场。 常规时刻，不是逐日场次。节目单来源 src_000025。
A41: prg_000038 | B41: pl_000004 | D41: 金甲舞蹈 | E41: performance | H41: 日间票 | I41: src_000025 | J41: candidate | M41: 成员1 | N41: 1 | O41: 白天：09:40（御道）、11:50（皇冠舞台）。 常规时刻，不是逐日场次。节目单来源 src_000025。
A42: prg_000039 | B42: pl_000004 | D42: 金甲巡游 | E42: performance | H42: 日间票 | I42: src_000025 | J42: candidate | M42: 成员1 | N42: 1 | O42: 白天：09:40/10:30/11:20/14:30/17:10；地点：御道/园内。 常规时刻，不是逐日场次。节目单来源 src_000025。
A43: prg_000040 | B43: pl_000004 | D43: 菊风乐舞 | E43: performance | H43: 日间票 | I43: src_000025 | J43: candidate | M43: 成员1 | N43: 1 | O43: 白天：09:40（龙亭大殿）、11:40（皇冠舞台）。 常规时刻，不是逐日场次。节目单来源 src_000025。
A44: prg_000041 | B44: pl_000004 | D44: 大宋儒生 | E44: performance | H44: 日间票 | I44: src_000025 | J44: candidate | M44: 成员1 | N44: 1 | O44: 白天：10:10/15:30；地点：宣和殿。 常规时刻，不是逐日场次。节目单来源 src_000025。
A45: prg_000042 | B45: pl_000004 | D45: 女官礼韵 | E45: performance | H45: 日间票 | I45: src_000025 | J45: candidate | M45: 成员1 | N45: 1 | O45: 白天：10:15/11:45/15:35/17:20；地点：宣和殿/皇冠舞台。 常规时刻，不是逐日场次。节目单来源 src_000025。
A46: prg_000043 | B46: pl_000004 | D46: 醉揽清风 | E46: performance | H46: 日间票 | I46: src_000025 | J46: candidate | M46: 成员1 | N46: 1 | O46: 白天：10:20/15:40；地点：宣和殿。 常规时刻，不是逐日场次。节目单来源 src_000025。
... A66: prg_000063 | B66: pl_000004 | D66: 宫灯巡游 | E66: performance | H66: 夜游票 | I66: src_000025 | J66: candidate | M66: 成员1 | N66: 1 | O66: 夜游：20:20；路线：朝门-环湖-御道。 常规时刻，不是逐日场次。节目单来源 src_000025。
A67: prg_000064 | B67: pl_000006 | D67: 纳土归宋 | E67: performance | F67: 实景历史剧，还原吴越王钱弘俶纳土归宋历史。 | H67: 待核实 | I67: src_000053 | J67: pending_review | K67: 2026-09-10 | L67: 2026-11-30 | M67: 成员1 | N67: 1 | O67: 官方节目单：11:10-11:20/14:15-14:25/15:55-16:05；地点：接引殿；类型：实景剧；常规时刻，不是逐日场次。节目单来源 src_000053。
A68: prg_000065 | B68: pl_000006 | D68: 铁塔匠心 | E68: performance | F68: 以北宋建筑工匠喻皓及弟子传承为主线的实景剧。 | H68: 待核实 | I68: src_000053 | J68: pending_review | K68: 2026-09-10 | L68: 2026-11-30 | M68: 成员1 | N68: 1 | O68: 官方节目单：10:10-10:20/11:45-11:55/13:30-13:40/15:20-15:30/17:20-17:30；地点：福胜院；类型：实景剧；常规时刻，不是逐日场次。节目单来源 src_000053。
A69: prg_000066 | B69: pl_000006 | D69: 五灵寻境 | E69: performance | F69: 依托铁塔实景的真人NPC仙侠剧情闯关/沉浸剧本游。 | H69: 待核实 | I69: src_000053 | J69: pending_review | K69: 2026-09-19 | L69: 2026-11-30 | M69: 成员1 | N69: 1 | O69: 官方节目单：10:00-12:30/13:30-16:30；地点：全园；类型：实景游；常规时刻，不是逐日场次。客服另称10:00-17:00、周一NPC休息。节目单来源 src_000053。
A70: prg_000067 | B70: pl_000006 | D70: 把菊吟诗 | E70: performance | F70: 融合中秋赏月赏菊与诗词文化的沉浸式活动。 | H70: 待核实 | I70: src_000027 | J70: pending_review | K70: 2026-09-25 | L70: 2026-10-17 | M70: 成员1 | N70: 1 | O70: 本次官方节目单未列；原本地宝档期9/25-10/17；待核实。
A71: prg_000068 | B71: pl_000010 | D71: 《古马道》 | E71: cinema | F71: 沉浸式裸眼3D影片，再现开封城摞城、墙摞墙、马道摞马道等奇观。 | H71: 待核实 | I71: src_000039 | J71: candidate | M71: 成员1 | N71: 1 | O71: 官方微梦大梁门页：9:00-21:00；地点：古马道遗址展馆内；常规循环播放，不是逐日场次。节目单来源 src_000039。
A72: prg_000069 | B72: pl_000010 | D72: 《微梦大梁门》 | E72: cinema | F72: 全沉浸影片，再现北宋东京城盛世繁华与城墙文化奇观。 | H72: 待核实 | I72: src_000039 | J72: candidate | M72: 成员1 | N72: 1 | O72: 官方微梦大梁门页：9:15-21:15；地点：大梁门城门一楼；常规循环播放，不是逐日场次。节目单来源 src_000039。
A73: prg_000070 | B73: pl_000001 | D73: 中华巨马展演 | E73: performance | H73: 待核实 | I73: src_000052 | J73: candidate | M73: 成员1 | N73: 1 | O73: 官方节目单：08:40/09:40/11:30/15:10/17:10/18:00/19:40/20:40；地点：迎宾门外广场；常规时刻，不是逐日场次。每周一检修；节目单来源 src_000052。
A74: prg_000071 | B74: pl_000001 | D74: 大宋百戏·迎宾互动演出 | E74: performance | H74: 待核实 | I74: src_000052 | J74: candidate | M74: 成员1 | N74: 1 | O74: 官方节目单：08:40/10:10/15:20/16:50/18:10；地点：迎宾门外广场；常规时刻，不是逐日场次。节目单来源 src_000052。
A75: prg_000072 | B75: pl_000001 | D75: 御剑飞行飞天秀 | E75: performance | H75: 待核实 | I75: src_000052 | J75: candidate | M75: 成员1 | N75: 1 | O75: 官方节目单：08:50/10:10/12:00/12:30/13:20/14:40/15:00/15:30/17:30；地点：东京码头上方；常规时刻，不是逐日场次。节目单来源 src_000052。
A76: prg_000073 | B76: pl_000001 | D76: 大宋百戏·快乐小丑 | E76: performance | H76: 待核实 | I76: src_000052 | J76: candidate | M76: 成员1 | N76: 1 | O76: 官方节目单：09:00/10:30/14:00/15:15/16:30/18:00；地点：端门内广场；常规时刻，不是逐日场次。节目单来源 src_000052。
A77: prg_000074 | B77: pl_000001 | D77: 球幕影院《飞越清明上河图》 | E77: cinema | H77: 待核实 | I77: src_000052 | J77: candidate | M77: 成员1 | N77: 1 | O77: 官方节目单：09:00起；游乐设施9:00-20:00，每30分钟一场；地点：球幕影院；常规时刻，不是逐日场次。节目单来源 src_000052。
A78: prg_000075 | B78: pl_000001 | D78: 大宋百戏·水上漂 | E78: performance | H78: 待核实 | I78: src_000052 | J78: candidate | M78: 成员1 | N78: 1 | O78: 官方节目单：09:00/10:30/11:20/14:00/15:30/16:20；地点：九龙桥西南水面；常规时刻，不是逐日场次。节目单来源 src_000052。
A79: prg_000076 | B79: pl_000001 | D79: 盘鼓 | E79: performance | H79: 待核实 | I79: src_000052 | J79: candidate | M79: 成员1 | N79: 1 | O79: 官方节目单：09:05；地点：迎宾门内广场；常规时刻，不是逐日场次。节目单来源 src_000052。
A80: prg_000077 | B80: pl_000001 | D80: 气功喷火 | E80: performance | H80: 待核实 | I80: src_000052 | J80: candidate | M80: 成员1 | N80: 1 | O80: 官方节目单：09:10/10:05/11:10/12:50/14:40/15:30/16:50/17:40；地点：东京食坊南口；常规时刻，不是逐日场次。节目单来源 src_000052。
A81: prg_000078 | B81: pl_000001 | D81: 大宋百戏·群宠献艺 | E81: performance | H81: 待核实 | I81: src_000052 | J81: candidate | M81: 成员1 | N81: 1 | O81: 官方节目单：09:10/11:40/15:00/18:20；地点：傀儡文化广场；常规时刻，不是逐日场次。节目单来源 src_000052。
A82: prg_000079 | B82: pl_000001 | D82: 天女散花飞天秀 | E82: performance | H82: 待核实 | I82: src_000052 | J82: candidate | M82: 成员1 | N82: 1 | O82: 官方节目单：09:10/10:40/11:20/13:00/13:50/14:20/15:55/16:30/17:10；地点：东京码头上方；常规时刻，不是逐日场次。节目单来源 src_000052。
A83: prg_000080 | B83: pl_000001 | D83: 机甲武士展演 | E83: performance | H83: 待核实 | I83: src_000052 | J83: candidate | M83: 成员1 | N83: 1 | O83: 官方节目单：09:10/11:00/12:40/14:20/15:40/16:50；地点：大宋沉浸式体验馆；常规时刻，不是逐日场次。节目单来源 src_000052。
A84: prg_000081 | B84: pl_000001 | D84: 真人秀提线木偶 | E84: performance | H84: 待核实 | I84: src_000052 | J84: candidate | M84: 成员1 | N84: 1 | O84: 官方节目单：09:20/11:10/12:50/14:30/15:50/17:00；地点：大宋沉浸式体验馆；常规时刻，不是逐日场次。节目单来源 src_000052。
... A100: prg_000097 | B100: pl_000006 | D100: 聚灵拍卖会 | E100: other | H100: 待核实 | I100: src_000053 | J100: candidate | M100: 成员1 | N100: 1 | O100: 官方节目单：17:30-18:00；地点：铁塔市集；常规时刻，不是逐日场次。类型：拍卖会；节目单来源 src_000053。
A101: prg_000098 | B101: pl_000016 | D101: 《千回大宋》 | E101: performance | F101: 大型室内歌舞剧，以宋文化和开封历史为主线，约80分钟，200名演员。 | H101: 演出票188/288元（另计） | I101: src_000058 | J101: pending_review | M101: 成员1 | N101: 1 | O101: 大河票务：每晚20:00-21:20；另有16:00/20:00说法；待官方核实。常规演出，不建14表。节目来源 src_000058。

Sheet 14_show_sessions
A1: 演出场次 show_sessions
A2: 仅收集候选与核实数据；不得把格式正确误判为事实真实。导入前请运行校验脚本。
A3: session_id | B3: program_id | C3: park_place_id | D3: stage_place_id | E3: session_date | F3: starts_at | G3: ends_at | H3: timezone | I3: session_status | J3: ticket_scope | K3: source_id | L3: checked_at | M3: valid_until | N3: validation_status | O3: reviewer | P3: version | Q3: notes

Sheet 15_food_items
A1: 美食菜品表 food_items
A2: 仅收集候选与核实数据；不得把格式正确误判为事实真实。导入前请运行校验脚本。
A3: food_id | B3: name | C3: aliases | D3: category | E3: flavor_tags | F3: dietary_tags | G3: intro | H3: intro_source_id | I3: validation_status | J3: reviewer | K3: version | L3: notes
A4: food_000001 | B4: 灌汤包 | C4: 开封灌汤包；小笼灌汤包；灌汤包子 | D4: 面点小吃 | G4: 携程餐厅页面将灌汤包列为第一楼总店推荐菜。此条用于建立菜品候选，不代表所有商家均供应或当前仍在售。 | H4: src_000064 | I4: candidate | K4: 1 | L4: 后续核实具体商家、分店和实时菜单；不同店铺馅料及配方可能不同。
A5: food_000002 | B5: 鲤鱼焙面 | C5: 糖醋鲤鱼焙面；糖醋软熘鲤鱼焙面 | D5: 传统豫菜/鱼类名菜 | E5: 软嫩鲜香；焙面酥脆；糖醋风味 | F5: 含鱼类；含小麦（焙面，具体配方待核实） | G5: 开封市鼓楼区政府的美食介绍称，鲤鱼焙面由糖醋熘鱼与焙龙须面配制，介绍了鱼肉软嫩鲜香、焙面蓬松酥脆等特点。 | H5: src_000060 | I5: candidate | K5: 1 | L5: 简介来自地方政府文化介绍；具体门店供应及配料需单独核实。
A6: food_000003 | B6: 桶子鸡 | C6: 开封桶子鸡；桶子鸡（部分平台写作筒子鸡） | D6: 传统熟食/地方名菜 | E6: 咸香；嫩脆；肥而不腻 | F6: 含鸡肉（具体配方待核实） | G6: 商务部老字号数字博物馆的福兴斋品牌页面介绍桶子鸡产品及其传统卤制工艺，并描述其皮脆肉嫩、肥而不腻等特点。 | H6: src_000062 | I6: candidate | K6: 1 | L6: 品牌资料支持菜品候选与文化介绍，不证明其他商家或分店当前供应。
A7: food_000004 | B7: 炒凉粉 | C7: 汴梁炒凉粉；汴京炒凉粉；铁板炒凉粉 | D7: 地方小吃 | E7: 外焦里嫩；豆豉酱香 | G7: 开封市鼓楼区政府的美食介绍将炒凉粉列为地方传统小吃，并介绍其以红薯凉粉和调料炒制，口感外焦里嫩。 | H7: src_000060 | I7: candidate | K7: 1 | L7: 平台菜单中可能出现铁板凉粉等近似名称，是否属于同一具体菜品仍需人工确认。
A8: food_000005 | B8: 杏仁茶 | C8: 汴京杏仁茶；八宝杏仁茶 | D8: 传统饮品/小吃 | F8: 可能含坚果/种子类配料；具体过敏原以商家配方为准 | G8: 携程餐厅页面将杏仁茶列为第一楼总店推荐菜；不同店铺的配料、名称和做法可能存在差异。 | H8: src_000064 | I8: candidate | K8: 1 | L8: 不得仅凭菜名断言完整配方或过敏原；后续按具体商家菜单核对。
A9: food_000006 | B9: 花生糕 | C9: 兴盛德传统花生糕 | D9: 传统糕点 | F9: 含花生（名称所示） | G9: 携程页面将兴盛德传统花生糕列为兴盛德花生老店的推荐商品之一。 | H9: src_000071 | I9: candidate | K9: 1 | L9: 商品配方、包装规格和当前库存需另行核实；花生为需关注的过敏原。
A10: food_000007 | B10: 羊肉炕馍 | C10: 炕馍 | D10: 面食小吃 | F10: 含羊肉（名称所示；其他配料待核实） | G10: 携程楼中楼酒店（汴梁小宋城店）页面将羊肉炕馍列为推荐菜。 | H10: src_000067 | I10: candidate | K10: 1 | L10: 菜品配方、实际供应和价格需按具体商家核实。
A11: food_000008 | B11: 锅贴 | C11: 开封锅贴 | D11: 面点小吃 | G11: 携程稻香居锅贴（宋都御街店）页面将锅贴列为推荐菜；高德榜单也将邢家锅贴老店列为锅贴候选商家。 | H11: src_000070 | I11: candidate | K11: 1 | L11: 不同店铺馅料和做法不同，暂不标注素食或具体过敏原。
A12: food_000009 | B12: 三狠汤 | C12: 开封三狠汤；三狠汤（酸辣咸） | D12: 汤类/地方小吃 | E12: 酸；辣；咸（平台/菜单名称描述） | G12: 携程第一楼总店及中兴楼页面均将三狠汤列入推荐菜。 | H12: src_000064 | I12: candidate | K12: 1 | L12: 具体配方、辣度和食材需按商家核实。
A13: food_000010 | B13: 黄焖鱼 | C13: 汴梁黄焖鱼；开封黄焖鱼 | D13: 鱼类菜肴 | F13: 含鱼类（名称所示；具体鱼种待核实） | G13: 携程黄家老店（宋城路店）页面将汴梁黄焖鱼列为推荐菜。 | H13: src_000065 | I13: candidate | K13: 1 | L13: 不同店铺鱼种、做法和配料可能不同；正式推荐前核实菜单。
A14: food_000011 | B14: 朱仙镇豆干丝 | C14: 朱仙镇豆腐干丝；豆干丝 | D14: 豆制品/小吃 | F14: 含大豆（菜品名称所示；调味料待核实） | G14: 携程黄家老店（宋城路店）页面将朱仙镇豆干丝列为推荐菜。 | H14: src_000065 | I14: candidate | K14: 1 | L14: 不同商家的产品和调味配方可能不同。
A15: food_000012 | B15: 炸八块 | C15: 汴梁炸八块 | D15: 传统豫菜 | G15: 携程第一楼总店及梅利汴京烤鸭店页面均将炸八块/汴梁炸八块列为推荐菜。 | H15: src_000064 | I15: candidate | K15: 1 | L15: 与菜单中出现的“炸八件”分开建项，避免未经证实地合并名称。
A16: food_000013 | B16: 炸八件 | D16: 传统豫菜 | G16: 携程中兴楼（汴京路店）页面将炸八件列为推荐菜。 | H16: src_000068 | I16: candidate | K16: 1 | L16: 与“炸八块”分开建项；二者是否为同一菜品/地方叫法待核实。
A17: food_000014 | B17: 炒红薯泥 | C17: 红薯泥；明炉灼红薯泥（菜单名称近似，待核实） | D17: 地方菜/小吃 | G17: 携程稻香居锅贴页面将炒红薯泥列为推荐菜，楼中楼酒店页面也列有红薯泥。 | H17: src_000070 | I17: candidate | K17: 1 | L17: 近似菜名是否属于同一做法待核实；此条先作为候选项。
A18: food_000015 | B18: 胡辣汤 | C18: 清真胡辣汤 | D18: 汤食/早餐小吃 | G18: 携程李小记羊肉胡辣汤（清真店）页面将清真胡辣汤列为推荐菜。 | H18: src_000072 | I18: candidate | K18: 1 | L18: 不同店铺的配方可能不同，不据此推断具体食材。
A19: food_000016 | B19: 羊双肠 | D19: 汤食/早餐小吃 | G19: 携程开封美食列表列出西门郑羊双肠（大梁路店），并将其描述为本地早餐类候选。 | H19: src_000073 | I19: candidate | K19: 1 | L19: “羊双肠”的具体构成和配料未从该列表充分确认，正式介绍前需补充可靠菜品资料。
A20: food_000017 | B20: 五香豆沫 | C20: 豆沫 | D20: 汤食/早餐小吃 | G20: 携程开封美食列表列有李记五香豆沫，可作为开封早餐小吃候选。 | H20: src_000073 | I20: candidate | K20: 1 | L20: 具体原料、是否含坚果/芝麻或动物性成分均待商家菜单核实。
A21: food_000018 | B21: 驴肉汤 | C21: 驴肉汤（餐馆菜品候选） | D21: 汤食/早餐小吃 | F21: 含驴肉（名称所示；其他配料待核实） | G21: 携程开封美食列表列出化三驴肉汤馆（总店），页面描述其驴肉汤为候选特色菜。 | H21: src_000073 | I21: candidate | K21: 1 | L21: 具体供应、配方和营业信息需按商家核实。
A22: food_000019 | B22: 麻辣花生 | C22: 兴盛德麻辣花生 | D22: 零食/坚果 | E22: 麻辣；焦香酥脆（平台榜单描述） | F22: 含花生（名称所示） | G22: 高德开封美食榜和携程兴盛德花生老店页面均提到麻辣花生/兴盛德花生商品。 | H22: src_000071 | I22: candidate | K22: 1 | L22: 配料、辣度和包装商品当前库存需核实；花生为需关注的过敏原。
A23: food_000020 | B23: 汴京果木烤鸭 | C23: 果木烤鸭（梅利店菜单名称） | D23: 烤制菜肴 | F23: 含鸭肉（名称所示；具体配方待核实） | G23: 携程梅利汴京烤鸭（东司门店）页面将汴京果木烤鸭列为推荐菜。 | H23: src_000069 | I23: candidate | K23: 1 | L23: 此名称来自该店平台菜单，不代表所有开封餐馆均供应。
A24: food_000021 | B24: 四味菜 | C24: 开封四味菜 | D24: 地方菜/烩菜 | G24: 携程餐厅详情页将李记四味菜馆（书店街店）的特色菜列为“四味烩菜”；本项目暂将“四味菜”作为候选标准名称，名称对应关系仍需人工确认。 | H24: src_000085 | I24: candidate | K24: 2 | L24: 来源菜单使用“四味烩菜”而非完全相同的标准名称“四味菜”；暂作为候选，正式推荐前需核对命名和具体做法。
A25: food_000022 | B25: 羊肉胡辣汤 | C25: 传统羊肉胡辣汤 | D25: 汤食/早餐小吃 | F25: 含羊肉（名称所示；其他配料待核实） | G25: 携程李小记羊肉胡辣汤（清真店）页面将传统羊肉胡辣汤列为推荐菜。 | H25: src_000072 | I25: candidate | K25: 1 | L25: 具体配方、供应状态和过敏原信息需按商家核实。
A26: food_000023 | B26: 玉米糁 | D26: 粥/早餐 | G26: 携程李小记羊肉胡辣汤（清真店）页面将玉米糁列为推荐菜。 | H26: src_000072 | I26: candidate | K26: 1 | L26: 具体制作方法和当前供应需按商家核实。
A27: food_000024 | B27: 鸡蛋布袋 | C27: 鸡蛋袋（菜单近似名称，待核实） | D27: 面点/早餐小吃 | F27: 可能含鸡蛋及面制品；实际配方待商家核实 | G27: 携程李小记羊肉胡辣汤（清真店）页面列有鸡蛋布袋和鸡蛋袋等近似名称。 | H27: src_000072 | I27: candidate | K27: 1 | L27: “鸡蛋布袋”与“鸡蛋袋”是否为同一菜品待核实，暂保留候选关系，不标已核实。
A28: food_000025 | B28: 宫廷豌豆糕 | C28: 豌豆糕（近似名称，待核实） | D28: 传统糕点 | G28: 携程第一楼总店页面将宫廷豌豆糕列为推荐菜。 | H28: src_000064 | I28: candidate | K28: 1 | L28: 与其他商家菜单中的“桂花豌豆糕”分开核对，暂不假定配方和名称完全相同。
A29: food_000026 | B29: 开封传统米线 | C29: 米线（平台榜单描述，待核实） | D29: 主食/小吃 | E29: 香浓入味（平台榜单描述） | G29: 高德开封美食榜将三胜街田庆辉田记米线列为候选店铺，并描述其米线搭配豆皮、海带、鹌鹑蛋、咖喱粉和麻油；具体配方仍需商家确认。 | H29: src_000081 | I29: candidate | K29: 1 | L29: 描述来自地图平台榜单而非商家官方菜单；配料和当前供应需复核。

Sheet 16_food_vendors
A1: 商家表 food_vendors
A2: 仅收集候选与核实数据；不得把格式正确误判为事实真实。导入前请运行校验脚本。
A3: vendor_id | B3: place_id | C3: name | D3: aliases | E3: address | F3: lng | G3: lat | H3: crs | I3: external_poi_id | J3: business_hours | K3: price_band | L3: dine_in | M3: takeaway | N3: inside_scenic | O3: source_id | P3: validation_status | Q3: verified_at | R3: reviewer | S3: version | T3: notes
A4: ven_000001 | C4: 第一楼·中华老字号（寺后街总店） | D4: 第一楼；第一楼灌汤包总店 | E4: 河南省开封市鼓楼区寺后街8号 | F4: 114.35192 | G4: 34.794059 | H4: GCJ-02 | I4: B017A00HWY | J4: 10:30-14:00；17:30-21:00 | K4: 60-70元/人 | L4: true | M4: unknown | N4: unknown | O4: src_000106 | P4: candidate | S4: 3 | T4: 地址、营业时间和人均消费来自携程页面；非商家实时官方确认，推荐前复核。 营业时间为平台页面展示值，正式推荐前需复核。 平台页面显示人均约64元，仅为参考消费，不是单道菜价格。 第三轮核查（2026-10-22）：高德地点页直接支持寺后街8号、坐标34.794059/114.351924及POI B017A00HWY；携程另有可访问餐厅详情页支持营业时段。高德评价较早，当前营业状态仍需电话确认。
A5: ven_000002 | C5: 黄家老店（宋城路店） | D5: 黄家老店宋城路店 | E5: 河南省开封市宋城路凤凰城1号楼 | F5: 114.32478 | G5: 34.785167 | H5: GCJ-02 | I5: B017A00L40 | J5: 10:00-21:30 | K5: 50-60元/人 | L5: true | M5: unknown | N5: unknown | O5: src_000107 | P5: candidate | S5: 3 | T5: 营业时间、价格和推荐菜来自携程页面；当前状态需再次确认。 营业时间为平台页面展示值，正式推荐前需复核。 平台页面显示人均约53元，仅为参考消费，不是单道菜价格。 第三轮核查（2026-10-22）：高德地点页直接支持宋城路凤凰城1号楼地址、坐标34.785167/114.324778及POI B017A00L40。可见评价较早，当前营业状态仍需确认。
A6: ven_000003 | C6: 黄家老店（晋安路店） | D6: 黄家老店晋安路店 | E6: 河南省开封市晋安路中段宏泰怡园1号楼底商（武夷夜市南头） | J6: 10:30-21:00 | K6: 50-60元/人 | L6: true | M6: unknown | N6: unknown | O6: src_000112 | P6: candidate | S6: 3 | T6: 营业时间、价格和推荐菜来自携程页面；当前状态需再次确认。 营业时间为平台页面展示值，正式推荐前需复核。 平台页面显示人均约59元，仅为参考消费，不是单道菜价格。 第三轮核查（2026-10-22）：Trip.com页面再次列出晋安路中段宏泰怡园1号楼底商（武夷夜市南头）、10:30-21:00及电话0371-23858988；本轮未取得可靠坐标，未推算经纬度。
A7: ven_000004 | C7: 楼中楼酒店（汴梁小宋城店） | D7: 楼中楼酒店小宋城店 | E7: 河南省开封市大梁路汴梁小宋城小吃城一楼擂台东侧6号/7号附近 | J7: 10:00-14:00；17:00-21:00 | K7: 60-70元/人 | L7: true | M7: unknown | N7: unknown | O7: src_000067 | P7: candidate | S7: 2 | T7: 地址描述来自携程页面，门牌及当前营业信息仍需复核。 营业时间为平台页面展示值，正式推荐前需复核。 平台页面显示人均约61元，仅为参考消费，不是单道菜价格。
A8: ven_000005 | C8: 中兴楼（汴京路店） | D8: 中兴楼汴京路店 | E8: 河南省开封市顺河回族区汴京路43号（汴京公园旁西约30米） | F8: 114.37032 | G8: 34.793215 | H8: GCJ-02 | I8: B017A000DA | J8: 10:30-14:00；17:00-21:00 | K8: 70-80元/人 | L8: true | M8: unknown | N8: unknown | O8: src_000108 | P8: candidate | S8: 3 | T8: 地址、营业时间和人均消费来自携程页面；非商家实时官方确认。 营业时间为平台页面展示值，正式推荐前需复核。 平台页面显示人均约77元，仅为参考消费，不是单道菜价格。 第三轮核查（2026-10-22）：高德地点页直接支持汴京路43号、坐标34.793215/114.370321及POI B017A000DA；携程页面支持营业时段10:30-14:00、17:00-21:00。高德评价较早，营业状态仍需电话确认。
A9: ven_000006 | C9: 梅利汴京烤鸭·开封豫菜地标店（东司门店） | D9: 梅利汴京烤鸭东司门店 | E9: 河南省开封市解放路与曹门大街交叉口东约60米路南 | J9: 10:00-21:00 | K9: 50-60元/人 | L9: true | M9: unknown | N9: unknown | O9: src_000069 | P9: candidate | S9: 3 | T9: 地址、营业时间和人均消费来自携程页面；当前营业与菜单需复核。 营业时间为平台页面展示值，正式推荐前需复核。 平台页面显示人均约56元，仅为参考消费，不是单道菜价格。 第三轮核查（2026-10-22）：携程支持本记录“东司门店”位于解放路与曹门大街交叉口东约60米路南，营业时段10:00-21:00。高德检索到的“梅利烤鸭店（东大街店）”在财政厅东街29号附1号，属于名称不同的另一分店，不得将其地址/坐标填入本记录；本轮仍未取得东司门店的可靠高德坐标。
A10: ven_000007 | C10: 稻香居锅贴（宋都御街店） | D10: 稻香居锅贴 | E10: 河南省开封市宋都御街73号 | F10: 114.35201 | G10: 34.800888 | H10: GCJ-02 | I10: B017A00K1Y | J10: 10:00-20:00 | K10: 40-50元/人 | L10: true | M10: unknown | N10: unknown | O10: src_000109 | P10: candidate | S10: 3 | T10: 地址、营业时间和人均消费来自携程页面；当前营业与菜单需复核。 营业时间为平台页面展示值，正式推荐前需复核。 平台页面显示人均约44元，仅为参考消费，不是单道菜价格。 第三轮核查（2026-10-22）：高德地点页直接支持宋都御街73号、坐标34.800888/114.352005及POI B017A00K1Y。可见评价较早，当前营业状态仍需复核。
A11: ven_000008 | C11: 兴盛德花生老店（中山路店） | D11: 兴盛德花生老店 | E11: 河南省开封市相国寺街道中山路北段84号 | J11: 08:00-21:00 | K11: 20-30元/人 | L11: unknown | M11: unknown | N11: unknown | O11: src_000071 | P11: candidate | S11: 2 | T11: 该页主要用于店铺/商品候选；商品零售形式、库存及当前营业需复核。 营业时间为平台页面展示值，正式推荐前需复核。 平台页面显示人均约29元，仅为参考消费，不是单道菜价格。
A12: ven_000009 | C12: 李小记羊肉胡辣汤（清真店） | D12: 李小记羊肉胡辣汤 | E12: 河南省开封市顺河回族区苹果园东路与苹果园中路交叉口往南约20米路东（高德POI地址描述为劳动路苹东社区，需确认同一入口） | F12: 114.38036 | G12: 34.807061 | H12: GCJ-02 | I12: B017A0NJMD | J12: 06:00-10:00 | K12: 0-10元/人 | L12: true | M12: unknown | N12: unknown | O12: src_000110 | P12: pending_review | S12: 3 | T12: 营业时间为早餐时段，来自携程页面；清真标识与菜品配方需以商家当前信息为准。 营业时间为平台页面展示值，正式推荐前需复核。 平台页面显示人均约7元，仅为参考消费，不是单道菜价格。 第三轮核查（2026-10-22）：携程与高德页面的电话均为13938618226，支持同一商家的可能性；携程给出苹果园东路/中路交叉口详细位置，高德给出劳动路苹东社区和坐标34.807061/114.380358。因地址表述不完全一致，保留坐标但标记待人工核对入口。
A13: ven_000010 | C13: 邢家锅贴老店（大梁门总店） | D13: 邢家锅贴大梁门总店 | E13: 河南省开封市龙亭区西门大街198号（大梁门东约50米路北） | F13: 114.33517 | G13: 34.801001 | H13: GCJ-02 | I13: B0FFG9U3L7 | L13: true | M13: unknown | N13: unknown | O13: src_000075 | P13: candidate | S13: 3 | T13: 地址/坐标来自高德地点页；平台列表价格为人均参考；营业时间待查。 初步核查：当前高德来源只支持门店名称、地址和坐标；原人均约58元未找到对应来源，已清空待核实。 第三轮核查（2026-10-22）：重新打开高德地点页，地址及坐标与现有记录一致（西门大街198号、大梁门东约50米路北；34.801001/114.335170；POI B0FFG9U3L7）。可见评价较早，当前营业状态仍需复核。
A14: ven_000011 | C14: 邢家锅贴老店（苹果园店） | D14: 邢家锅贴苹果园店 | E14: 河南省开封市顺河回族区东环北路40号 | F14: 114.37405 | G14: 34.807511 | H14: GCJ-02 | I14: B017A0NNWI | L14: unknown | M14: unknown | N14: unknown | O14: src_000076 | P14: pending_review | S14: 2 | T14: 高德页面提供地址与坐标，但未提供完整营业时间、价格和当前菜品信息；需进一步核实。 第三轮核查（2026-10-22）：重新打开高德地点页确认东环北路40号；现有坐标34.807511/114.374048来自此前记录，本轮页面渲染只显示地址、未重新展示坐标，因此坐标仍需在高德App地图针上人工复核。携程页面另显示10:00-14:00、17:00-21:00。
A15: ven_000012 | C15: 宋都禾源灌汤包子（鼎立店） | D15: 宋都禾源灌汤包子鼎立店 | E15: 河南省开封市龙亭区黄河路北段鼎立·国际城 | F15: 114.3224 | G15: 34.81801 | H15: GCJ-02 | I15: B0FFK26VO8 | L15: unknown | M15: unknown | N15: unknown | O15: src_000077 | P15: pending_review | S15: 2 | T15: 高德页面提供地址与坐标，营业时间、价格及当前供应菜品待核实。 第三轮核查（2026-10-22）：高德地点页支持黄河路北段鼎立·国际城、坐标34.818010/114.322401及POI B0FFK26VO8；未显示完整营业时段，且可见评价较早，需确认当前营业。
A16: ven_000013 | C16: 宋园灌汤小笼包子（集英街店） | D16: 宋园灌汤小笼包集英街店 | E16: 河南省开封市龙亭区汉兴路与集英街交叉口路西 | F16: 114.29026 | G16: 34.792195 | H16: GCJ-02 | I16: B0FFIIMUD7 | L16: unknown | M16: unknown | N16: unknown | O16: src_000078 | P16: candidate | S16: 2 | T16: 高德页面提供地址与坐标；高德2025美食榜将其列为热门店铺，但当前营业与菜单仍需核实。 第三轮核查（2026-10-22）：高德地点页支持汉兴路与集英街交叉口路西、坐标34.792195/114.290257及POI B0FFIIMUD7；公开评价较早，当前营业状态需复核。
A17: ven_000014 | C17: 闫记灌汤包 | E17: 河南省开封市龙亭区金耀路186-187号 | F17: 114.33394 | G17: 34.812002 | H17: GCJ-02 | I17: B0IBFS1EZM | L17: unknown | M17: unknown | N17: unknown | O17: src_000079 | P17: pending_review | S17: 2 | T17: 高德页面提供地址与坐标；营业时间、价格和当前菜单未显示，需核实。 第三轮核查（2026-10-22）：高德地点页支持金耀路186-187号、坐标34.812002/114.333943及POI B0IBFS1EZM；可见评价较早，当前营业状态需复核。
A18: ven_000015 | C18: 马豫兴桶子鸡（金玉斋牛肉万宝店） | D18: 马豫兴桶子鸡万宝店 | E18: 河南省开封市龙亭区大梁路省四队103队1-1-2号 | F18: 114.32437 | G18: 34.80186 | H18: GCJ-02 | I18: B0FFF5UIZH | L18: unknown | M18: unknown | N18: unknown | O18: src_000080 | P18: candidate | S18: 2 | T18: 高德页面提供地址与坐标；榜单将其列为桶子鸡候选商家，营业时间和当前商品需核实。 第三轮核查（2026-10-22）：高德地点页支持大梁路省四队103队1-1-2号、坐标34.801860/114.324365及POI B0FFF5UIZH；可见评价日期为2023年，当前营业状态需复核。
A19: ven_000016 | C19: 黄家老店（西司店） | D19: 黄家老店西司店 | E19: 河南省开封市鼓楼区西司门街16号 | J19: 10:30-21:00 | K19: 50-60元/人 | L19: unknown | M19: unknown | N19: unknown | O19: src_000113 | P19: pending_review | S19: 4 | T19: 携程列表显示店名、鼓楼广场附近位置和人均参考价；精确门牌、营业时间和当前菜单待核实。 初步核查：携程列表显示人均约55元、10:30营业；仅有开门时间，关门时间及精确门牌仍待核实。 地址重点核查（2026-10-22）：去哪儿页面列出西司门街16号；坐标未找到可靠的高德精确POI，暂留空。 第三轮核查（2026-10-22）：Trip.com与去哪儿均列西司门街16号、电话0371-25662988；Trip.com显示10:30-21:00。第三方POI镜像以同一电话列省府西街16号，地址文字存在差异；没有可靠坐标，先保留两平台一致的西司门街16号并待高德App核对。
A20: ven_000017 | C20: 张记逍遥胡辣汤（大坑沿街店） | D20: 张记逍遥胡辣汤 | E20: 河南省开封市鼓楼区西司门街道大坑沿街80号（省府前街与大坑沿街交叉口向北约150米路东） | J20: 06:30-12:00 | K20: 10-20元/人 | L20: unknown | M20: unknown | N20: unknown | O20: src_000089 | P20: pending_review | S20: 5 | T20: 携程列表支持店名及早餐类候选；具体门牌、完整营业时段及当前菜单待核实。 携程列表显示06:30营业，仅显示开门时间。 平台页面显示人均约11元/人，仅供消费预算参考，不是单道菜价格。 地址与营业时段核查（2026-10-22）：携程详情页列出大坑沿街80号及06:30-12:00；平台展示值，需商家确认。 第三轮核查（2026-10-22）：携程页面再次支持大坑沿街80号、06:30-12:00及电话13271147781，页面有2025-09-05用户评价；本轮未找到可确认该分店的高德精确坐标，不能从门牌地址推算坐标。
A21: ven_000018 | C21: 化三驴肉汤馆（总店） | D21: 化三驴肉汤 | E21: 河南省开封市龙亭区金耀路首座时代（园林小区大门对面；第三方目录另列金耀路59号，门牌待确认） | J21: 06:30-15:30 | K21: 30-40元/人 | L21: unknown | M21: unknown | N21: unknown | O21: src_000090 | P21: pending_review | S21: 5 | T21: 携程列表支持店名及驴肉汤候选；精确地址、完整营业时段和当前供应待核实。 携程列表显示06:30营业，仅显示开门时间。 平台页面显示人均约36元/人，仅供消费预算参考，不是单道菜价格。 地址交叉核查（2026-10-22）：携程页面支持“金耀路首座时代、园林小区大门对面”地标，查号吧列出金耀路59号及相对位置；门牌号来自第三方目录，需在高德/商家处复核。 第三轮核查（2026-10-22）：携程页面支持“金耀路首座时代（园林小区大门对面）”、06:30-15:30，页面电话为17303784449；查号吧另列金耀路59号和电话0371-28888886。两来源位置描述相容，但电话不同且精确门牌只由第三方目录提供，因此地址降为地标级描述，门牌及当前联系方式需确认。
A22: ven_000019 | C22: 西门郑羊双肠（大梁路店） | D22: 西门郑羊双肠 | E22: 河南省开封市龙亭区大梁路1号（梁园市场西门附近；Trip.com页面使用历史行政区称“金明区”） | J22: 06:30-14:00 | K22: 20-30元/人 | L22: unknown | M22: unknown | N22: unknown | O22: src_000111 | P22: pending_review | S22: 5 | T22: 携程列表支持店名及羊双肠早餐候选；精确门牌、营业时段和菜品构成待核实。 携程列表显示06:30营业，仅显示开门时间。 平台页面显示人均约23元/人，仅供消费预算参考，不是单道菜价格。 地址核查（2026-10-22）：Trip.com页面列出大梁路1号及06:30-14:00；未找到可靠坐标，坐标字段继续留空。 第三轮核查（2026-10-22）：携程页面显示大梁路1号（梁园市场西门附近）、06:30-14:00、电话13353811330；页面有2025-09至2025-11用户评价。未找到该分店的高德精确坐标，坐标不填猜测值。
A23: ven_000020 | C23: 李记五香豆沫 | D23: 李记豆沫 | E23: 河南省开封市鼓楼区张老五羊肉鲜汤北门东约250米（携程列表另写丁角街2号，门牌待核实） | F23: 114.33825 | G23: 34.794724 | H23: GCJ-02 | I23: B0FFFPFWQH | J23: 05:30开门（关门时间未显示） | K23: 0-10元/人 | L23: unknown | M23: unknown | N23: unknown | O23: src_000093 | P23: conflict | S23: 6 | T23: 携程列表支持店名和豆沫候选；精确地址、完整营业时段和配方待核实。 携程列表显示05:30营业，仅显示开门时间。 平台页面显示人均约9元/人，仅供消费预算参考，不是单道菜价格。 地址/坐标交叉核查（2026-10-22）：携程列表列丁角街2号；高德页面提供相邻地标及坐标（GCJ-02，来源src_000093）。建议打开高德地图复核具体门牌。 二次核查（2026-10-22）：携程列表写“丁角街2号”，高德地点页只给附近地标和坐标34.794724,114.338246；该坐标与高德“西司广场夜市”（丁角街83号，坐标34.794594,114.338268，来源src_000105）约相距14-15米。地址门牌与POI坐标是否对应尚未确认，暂不把此坐标视为已核实的商家精确位置。 第三轮核查（2026-10-22）：高德直接POI支持附近地标与坐标34.794724/114.338246；携程列表写丁角街2号，但该坐标与高德西司广场夜市（丁角街83号，34.794594/114.338268）约相距14-15米。未能证明门牌与坐标完全对应，地址改为地标描述并标记conflict，导航前需在高德App核对地图针。
A24: ven_000021 | C24: 宋园灌汤小笼包（黄河路店） | D24: 宋园灌汤小笼包央视报道品牌黄河路店 | E24: 河南省开封市龙亭区黄河大街北段81号阳光新天地小区1号楼临街房 | J24: 11:30-14:00；17:30-21:00 | K24: 50-70元/人 | L24: unknown | M24: unknown | N24: unknown | O24: src_000095 | P24: pending_review | S24: 6 | T24: 携程列表显示店名、龙亭区位置和人均参考价；精确门牌、完整营业时段和当前菜单待核实。 携程列表显示11:30营业，仅显示开门时间。 平台页面显示人均约60元/人，仅供消费预算参考，不是单道菜价格。 地址核查（2026-10-22）：Trip.com详情页列出黄河大街北段81号及完整营业时段；抖音评论仅提供黄河大街北段的宽泛线索，不作为精确地址证据。 二次核查（2026-10-22）：Trip.com另一可见版本明确列“黄河大街北段81号、阳光新天地小区1号楼临街房”；携程详情页显示“黄河大街星光天地对面”。两者为详细地址与地标描述，基本相容，但尚未找到该分店的高德精确POI坐标，仍需人工复核门牌/入口。 第三轮核查（2026-10-22）：Trip.com页面支持黄河大街北段81号、阳光新天地1号楼临街房、11:30-14:00及17:30-21:00；页面可见2026-09-29用户点评。尚未找到能独立确认该分店坐标的高德POI，地址可作候选但地图针仍待核。
A25: ven_000022 | C25: 宋风雅宴·宋文化餐厅（双龙巷店） | D25: 宋风雅宴（双龙巷店）；宋风雅宴·宋文化地标餐厅（双龙巷店） | E25: 河南省开封市顺河回族区双龙巷历史文化区A7号院（宋风雅宴/杜孟模博物馆内） | F25: 114.36225 | G25: 34.801763 | H25: GCJ-02 | I25: B0JKPHTQWF | J25: 11:00-14:00；17:00-21:00 | K25: 70-90元/人 | L25: unknown | M25: unknown | N25: unknown | O25: src_000083 | P25: pending_review | S25: 3 | T25: 地址、坐标和电话来自高德地点页src_000083；营业时段11:00-14:00、17:00-21:00及人均约80元来自Trip.com页面src_000086。两个来源均为平台公开信息，非商家实时确认；正式推荐前复核。 第三轮核查（2026-10-22）：高德地点页支持双龙巷历史文化区A7号院、坐标34.801763/114.362246及POI B0JKPHTQWF；可见评价为2024年，当前营业状态仍需确认。
A26: ven_000023 | C26: 李记四味菜馆（书店街店） | D26: 李记四味菜馆 | E26: 河南省开封市龙亭区北书店街59号 | F26: 114.35623 | G26: 34.79904 | H26: GCJ-02 | I26: B017A0N74G | J26: 06:30-13:30 | K26: 10-20元/人 | L26: unknown | M26: unknown | N26: unknown | O26: src_000084 | P26: pending_review | S26: 3 | T26: 地址、坐标和电话来自高德地点页src_000084；携程餐厅详情页src_000085显示营业时间06:30-13:30、人均约19元，特色菜含“四味烩菜”。平台信息仍需正式推荐前复核。 第三轮核查（2026-10-22）：高德地点页支持北书店街59号、坐标34.799040/114.356232及POI B017A0N74G；携程页面有2026-09-29近期评价并列出四味烩菜等菜品。仍需确认当天实际供应及营业时段。
A27: ven_000024 | C27: 宋都禾源·灌汤包子（汉兴路直营店） | D27: 宋都禾源灌汤包汉兴路店 | E27: 河南省开封市龙亭区黄河大街东段与汉兴路交叉口东北角 | J27: 10:00-14:30；17:00-21:30 | K27: 50-60元/人 | L27: unknown | M27: unknown | N27: unknown | O27: src_000096 | P27: pending_review | S27: 5 | T27: 携程附近列表显示店名及人均参考价；只显示约10:00开门提示，完整营业时间和精确地址待核实。 携程附近美食页显示10:00营业，仅显示开门时间。 平台页面显示人均约54元/人，仅供消费预算参考，不是单道菜价格。 地址核查（2026-10-22）：携程详情页提供路口方位及营业时段；未提供精确门牌/坐标，正式推荐前复核。 第三轮核查（2026-10-22）：携程页面支持黄河大街东段与汉兴路交叉口东北角及10:00-14:30、17:00-21:30；本轮业务搜索还出现汉兴路16号院付2的“禾源/禾源汤包”地点线索，但无法确认是同一分店，因此不合并地址、不填坐标。
A28: ven_000025 | C28: 贪烤 | E28: 河南省开封市夷山大街佳和世家1号楼14号铺1层 | J28: 11:30-14:30；17:30-21:00 | K28: 80-90元/人 | L28: unknown | M28: unknown | N28: unknown | O28: src_000097 | P28: pending_review | S28: 5 | T28: 携程附近列表显示店名、人均参考价及约11:30开门提示；精确地址和完整营业时间待核实。 携程附近美食页显示11:30营业，仅显示开门时间。 平台页面显示人均约82元/人，仅供消费预算参考，不是单道菜价格。 地址核查（2026-10-22）：Trip.com页面列出佳和世家1号楼14号铺1层及营业时段；平台资料仍需正式推荐前复核。 第三轮核查（2026-10-22）：Trip.com页面支持夷山大街佳和世家1号楼14号铺1层、11:30-14:30及17:30-21:00，页面可见2026-08-17用户点评；本轮未找到能可靠对应该分店的高德坐标。
A29: ven_000026 | C29: 梁山烤肉（东京总店） | D29: 梁山烤肉东京总店 | E29: 河南省开封市龙亭区万胜路（Trip.com当前餐厅详情写8号；另有用户游记及工商注册地址写1号，门牌未确认） | J29: 10:00-24:00 | K29: 60-70元/人 | L29: unknown | M29: unknown | N29: unknown | O29: src_000116 | P29: conflict | S29: 6 | T29: 携程附近列表显示店名、人均参考价及约10:00开门提示；精确地址、完整营业时间和菜单待核实。 携程附近美食页显示10:00营业，仅显示开门时间。 平台页面显示人均约65元/人，仅供消费预算参考，不是单道菜价格。 地址冲突（2026-10-22）：携程详情区写万胜路8号，但同页用户点评和BOSS企业信息列万胜路1号（辅助来源src_000099）。已标记conflict；须用高德地图或电话确认后才能作为正式导航地址。 二次核查（2026-10-22）：携程页面餐厅信息区写“万胜路8号”，同页用户点评写“万胜路1号”，BOSS企业信息也列“万胜路1号”。已将address改为地标级位置并明确门牌冲突；未联系商家确认前不得当作精确导航地址。 第三轮核查（2026-10-22）：Trip.com当前餐厅详情区仍列万胜路8号、10:00-24:00、电话18568673633，并有2026-04-25近期评价；但用户游记文字与BOSS工商注册地址写万胜路1号。餐厅详情区更适合作为候选导航线索，但未直接联系商家前仍保留conflict状态，不将1号或8号宣称为最终核实地址。
A30: ven_000027 | C30: 开封市福兴斋清真食品厂（福兴斋品牌） | D30: 福兴斋 | E30: 河南省开封市祥符区朱仙镇北关（食品加工厂址，非已确认的游客消费门店） | L30: unknown | M30: unknown | N30: unknown | O30: src_000101 | P30: pending_review | S30: 3 | T30: 商务部老字号数字博物馆支持品牌及桶子鸡产品信息，但该记录可能是生产主体而非游客可直接到店消费的门店；零售门店地址与营业信息待核实。 地址核查（2026-10-22）：祥符区政府食品生产监督公示列出该厂地址为朱仙镇北关。该记录是食品生产主体，不是已确认的游客可到店消费门店；正式推荐池应先核实其零售门店或替换为具体门店。 第三轮核查（2026-10-22）：该记录的政府公示来源支持食品生产主体厂址，但不能证明游客可直接在厂址消费或购买。建议从“游客餐饮推荐商家”候选池中排除，除非另行找到具体零售门店及其地址。
A31: ven_000028 | C31: 宜生斋 | D31: 宜生斋老庞家 | E31: 河南省开封市顺河回族区南羊小区1号楼1层西头 | L31: unknown | M31: unknown | N31: unknown | O31: src_000063 | P31: pending_review | S31: 2 | T31: 地址和桶子鸡/烧鸡主营产品来自商务部老字号数字博物馆；营业时间及当前门店状态待核实。 第三轮核查（2026-10-22）：商务部老字号数字博物馆页面明确写明宜生斋总店地址为顺河回族区南羊小区1号楼1层西头，并说明主营桶子鸡、烧鸡；地址有较强的品牌来源支持，但页面未提供高德坐标或当前营业状态，仍需地图/商家确认。
A32: ven_000029 | C32: 庞记桶子鸡（旗舰店） | D32: 庞记桶子鸡 | E32: 河南省开封市龙亭区黄河大街8号一层2号 | F32: 114.32264 | G32: 34.804717 | H32: GCJ-02 | I32: B0FFGZKNA5 | L32: unknown | M32: unknown | N32: unknown | O32: src_000087 | P32: pending_review | S32: 3 | T32: 高德开封美食榜将其列为桶子鸡候选商家，但本轮页面未提供可核实的精确地址、营业时间和门店详情。 地址/坐标核查（2026-10-22）：高德地点页提供黄河大街8号一层2号及坐标（GCJ-02）；页面存在较早用户评价，当前营业状态仍需确认。 第三轮核查（2026-10-22）：重新打开高德地点页确认黄河大街8号一层2号、坐标34.804717/114.322644及POI B0FFGZKNA5；页面电话18903785556，可见评价较早，当前营业状态需复核。
A33: ven_000030 | C33: 三胜街田庆辉田记米线 | D33: 田庆辉田记米线；田记米线 | E33: 河南省开封市龙亭区三胜前街7号 | F33: 114.35603 | G33: 34.800376 | H33: GCJ-02 | I33: B0FFG02SUH | L33: unknown | M33: unknown | N33: unknown | O33: src_000103 | P33: pending_review | S33: 4 | T33: 高德开封美食榜提供店名及米线介绍；精确地址、营业时间和实时菜单待核实。 地址核查未完成（2026-10-22）：高德2025美食榜只列店名/菜品；大众点评相册页（来源src_000102）可确认店名与菜品图片，但详情页触发美团验证，未能取得精确地址。抖音/美团/小红书公开可检索结果未找到可交叉确认的门牌，因此地址继续留空，不猜填。 二次核查（2026-10-22）：高德地点页补充精确地址“三胜前街7号”、坐标34.800376,114.356027（GCJ-02）和POI B0FFG02SUH；可见评价日期为2019-11-24，当前营业状态仍需复核。来源见src_000103。 第三轮核查（2026-10-22）：重新打开高德地点页确认三胜前街7号、坐标34.800376/114.356027、电话13569506620及POI B0FFG02SUH；可见用户评价仍为2019年，不能证明当前仍营业，保留待核实。
A34: ven_000031 | C34: 益品虾皇（鼎立总店） | D34: 益品虾皇鼎立总店 | I34: B0FFHXMMZP | L34: unknown | M34: unknown | N34: unknown | O34: src_000081 | P34: pending_review | S34: 4 | T34: 高德开封美食榜将其列为候选商家；精确地址、营业时间、价格及当前菜单待核实。 地址核查未完成（2026-10-22）：高德2025美食榜仅收录名称，未给出具体门牌；本轮公开检索未找到可交叉确认的高德POI或可靠的抖音/美团/小红书门店地址，地址继续留空，不按“鼎立总店”字样推测具体门牌。 二次核查（2026-10-22）：高德2025榜单中的“益品虾皇（鼎立总店）”链接对应POI标识B0FFHXMMZP，但详情页本轮无法成功打开，未获得地址/坐标。吉屋网另列同名商户“黄河路北段安泰警苑小区斜对面”（来源src_000104），尚不能确认与“鼎立总店”为同一分店，因此address仍留空，不猜填。 第三轮核查（2026-10-22）：高德2025美食榜仍出现“益品虾皇（鼎立总店）”，但其POI链接B0FFHXMMZP本轮返回404；公开检索未找到可确认该分店地址的美团/抖音/小红书页面。另一个网页提到黄河路北段安泰警苑附近的同名商户，但不能证明同一分店。地址继续留空，不猜填。
A35: ven_000032 | C35: 楼上楼灌汤包子馆（大梁路店） | D35: 楼上楼灌汤包子馆 | E35: 河南省开封市龙亭区大梁路与武夷路交叉口东南角（航天大酒店对面） | F35: 114.31881 | G35: 34.801561 | H35: GCJ-02 | I35: B0GRGOROMS | L35: unknown | M35: unknown | N35: unknown | O35: src_000082 | P35: candidate | S35: 2 | T35: 高德页面提供地址和坐标；推荐菜、营业时间及当前供应仍需核实。 第三轮核查（2026-10-22）：高德地点页支持大梁路与武夷路交叉口东南角、航天大酒店对面，坐标34.801561/114.318807及POI B0GRGOROMS；可见评价为2020年，当前营业状态需复核。

Sheet 17_vendor_foods
A1: 菜品供应关系 vendor_foods
A2: 仅收集候选与核实数据；不得把格式正确误判为事实真实。导入前请运行校验脚本。
A3: relation_id | B3: vendor_id | C3: food_id | D3: evidence_source_id | E3: evidence_note | F3: verified_at | G3: validation_status | H3: seasonal_flag | I3: available_from | J3: available_to | K3: reviewer | L3: version | M3: notes
A4: vf_000001 | B4: ven_000001 | C4: food_000001 | D4: src_000064 | E4: 公开平台页面/推荐菜列表列有“灌汤包”；该证据仅支持候选关联，不等于商家当前实时供应，正式推荐前需以商家当前菜单或直接确认复核。 | G4: candidate | H4: unknown | L4: 2 | M4: 本时间为本轮页面观察时间，不是商家确认时间；需后续人工核实。
A5: vf_000002 | B5: ven_000001 | C5: food_000002 | D5: src_000064 | E5: 公开平台页面/推荐菜列表列有“鲤鱼焙面”；该证据仅支持候选关联，不等于商家当前实时供应，正式推荐前需以商家当前菜单或直接确认复核。 | G5: candidate | H5: unknown | L5: 2 | M5: 本时间为本轮页面观察时间，不是商家确认时间；需后续人工核实。
A6: vf_000003 | B6: ven_000001 | C6: food_000012 | D6: src_000064 | E6: 公开平台页面/推荐菜列表列有“汴梁炸八块”；该证据仅支持候选关联，不等于商家当前实时供应，正式推荐前需以商家当前菜单或直接确认复核。 | G6: candidate | H6: unknown | L6: 2 | M6: 本时间为本轮页面观察时间，不是商家确认时间；需后续人工核实。
A7: vf_000004 | B7: ven_000001 | C7: food_000009 | D7: src_000064 | E7: 公开平台页面/推荐菜列表列有“三狠汤”；该证据仅支持候选关联，不等于商家当前实时供应，正式推荐前需以商家当前菜单或直接确认复核。 | G7: candidate | H7: unknown | L7: 2 | M7: 本时间为本轮页面观察时间，不是商家确认时间；需后续人工核实。
A8: vf_000005 | B8: ven_000001 | C8: food_000005 | D8: src_000064 | E8: 公开平台页面/推荐菜列表列有“杏仁茶”；该证据仅支持候选关联，不等于商家当前实时供应，正式推荐前需以商家当前菜单或直接确认复核。 | G8: candidate | H8: unknown | L8: 2 | M8: 本时间为本轮页面观察时间，不是商家确认时间；需后续人工核实。
A9: vf_000006 | B9: ven_000001 | C9: food_000025 | D9: src_000064 | E9: 公开平台页面/推荐菜列表列有“宫廷豌豆糕”；该证据仅支持候选关联，不等于商家当前实时供应，正式推荐前需以商家当前菜单或直接确认复核。 | G9: candidate | H9: unknown | L9: 2 | M9: 本时间为本轮页面观察时间，不是商家确认时间；需后续人工核实。
A10: vf_000007 | B10: ven_000001 | C10: food_000003 | D10: src_000064 | E10: 公开平台页面/推荐菜列表列有“桶子鸡”；该证据仅支持候选关联，不等于商家当前实时供应，正式推荐前需以商家当前菜单或直接确认复核。 | G10: candidate | H10: unknown | L10: 2 | M10: 本时间为本轮页面观察时间，不是商家确认时间；需后续人工核实。
A11: vf_000008 | B11: ven_000002 | C11: food_000004 | D11: src_000065 | E11: 公开平台页面/推荐菜列表列有“汴京炒凉粉”；该证据仅支持候选关联，不等于商家当前实时供应，正式推荐前需以商家当前菜单或直接确认复核。 | G11: candidate | H11: unknown | L11: 2 | M11: 本时间为本轮页面观察时间，不是商家确认时间；需后续人工核实。
A12: vf_000009 | B12: ven_000002 | C12: food_000011 | D12: src_000065 | E12: 公开平台页面/推荐菜列表列有“朱仙镇豆干丝”；该证据仅支持候选关联，不等于商家当前实时供应，正式推荐前需以商家当前菜单或直接确认复核。 | G12: candidate | H12: unknown | L12: 2 | M12: 本时间为本轮页面观察时间，不是商家确认时间；需后续人工核实。
A13: vf_000010 | B13: ven_000002 | C13: food_000010 | D13: src_000065 | E13: 公开平台页面/推荐菜列表列有“汴梁黄焖鱼”；该证据仅支持候选关联，不等于商家当前实时供应，正式推荐前需以商家当前菜单或直接确认复核。 | G13: candidate | H13: unknown | L13: 2 | M13: 本时间为本轮页面观察时间，不是商家确认时间；需后续人工核实。
A14: vf_000011 | B14: ven_000002 | C14: food_000003 | D14: src_000065 | E14: 公开平台页面/推荐菜列表列有“桶子鸡”；该证据仅支持候选关联，不等于商家当前实时供应，正式推荐前需以商家当前菜单或直接确认复核。 | G14: candidate | H14: unknown | L14: 2 | M14: 本时间为本轮页面观察时间，不是商家确认时间；需后续人工核实。
A15: vf_000012 | B15: ven_000003 | C15: food_000004 | D15: src_000066 | E15: 公开平台页面/推荐菜列表列有“汴梁炒凉粉”；该证据仅支持候选关联，不等于商家当前实时供应，正式推荐前需以商家当前菜单或直接确认复核。 | G15: candidate | H15: unknown | L15: 2 | M15: 本时间为本轮页面观察时间，不是商家确认时间；需后续人工核实。
... A51: vf_000048 | B51: ven_000023 | C51: food_000021 | D51: src_000085 | E51: 携程餐厅详情页将该店特色菜列为“四味烩菜”；本表标准菜名为“四味菜”，先建立待复核候选关联，需确认是否按同一菜品标准化。 | G51: pending_review | H51: unknown | L51: 2 | M51: 记录时间为本轮查看来源时间，不代表商家已直接确认；名称映射待人工复核。

Sheet 18_source_records
A1: 来源与证据 source_records
A2: 仅收集候选与核实数据；不得把格式正确误判为事实真实。导入前请运行校验脚本。
A3: source_id | B3: source_type | C3: title | D3: source_url | E3: publisher | F3: published_at | G3: accessed_at | H3: captured_at | I3: evidence_path | J3: rights_status | K3: usage_notes | L3: content_sha256 | M3: validation_status | N3: reviewer | O3: version | P3: notes
A4: src_000001 | B4: official | C4: 清明上河园官网首页 | D4: https://www.qingmings.com/ | E4: 清明上河园（中国开封清明上河园股份有限公司） | G4: 2026-10-21T22:36:46+08:00 | H4: 2026-10-21T22:36:46+08:00 | I4: evidence/01_原始来源/清明上河园/清明上河园_官网首页_20261021.html | J4: public_view_only | K4: 仅内部核对与引用，不对外转载；版权归清明上河园。 | L4: cb43ddfd6d3a981aaeeb0581150274a8e04510dc5157af52e154e87c64022da6 | M4: candidate | N4: 成员1 | O4: 1 | P4: 官网首页；页脚地址和营业时间；仅保存 HTML。
A5: src_000002 | B5: official | C5: 清明上河园官网-旅游服务（常见问题/情景展示时间表） | D5: https://www.qingmings.com/service.php | E5: 清明上河园（中国开封清明上河园股份有限公司） | G5: 2026-10-21T22:36:46+08:00 | H5: 2026-10-21T22:36:46+08:00 | I5: evidence/01_原始来源/清明上河园/清明上河园_官网旅游服务_20261021.html | J5: public_view_only | K5: 仅内部核对与引用，不对外转载；版权归清明上河园。 | L5: 06f27996985119918cd2a82037af5f9615ece77d15c419cf8072fe659720c909 | M5: candidate | N5: 成员1 | O5: 1 | P5: 包含开放时间09:00-22:00、票价120/60、情景展示常规时间表；本次开放规则和节目时间的主要来源。
A6: src_000003 | B6: official | C6: 清明上河园官网-精彩演出 | D6: https://www.qingmings.com/q_show.php | E6: 清明上河园（中国开封清明上河园股份有限公司） | G6: 2026-10-21T22:36:46+08:00 | H6: 2026-10-21T22:36:46+08:00 | I6: evidence/01_原始来源/清明上河园/清明上河园_官网精彩演出_20261021.html | J6: public_view_only | K6: 仅内部核对与引用，不对外转载；版权归清明上河园。 | L6: 6ec1954d9012fefb7bb0c16fd9922a9cd99ff9c95d0cf071049e5ec4b2863b32 | M6: candidate | N6: 成员1 | O6: 1 | P6: 节目介绍与表演地点；未给具体时间。
A7: src_000004 | B7: official | C7: 清明上河园官网-景区介绍（瑰伟建筑） | D7: https://www.qingmings.com/q.php | E7: 清明上河园（中国开封清明上河园股份有限公司） | G7: 2026-10-21T22:36:46+08:00 | H7: 2026-10-21T22:36:46+08:00 | I7: evidence/01_原始来源/清明上河园/清明上河园_官网景区介绍_20261021.html | J7: public_view_only | K7: 仅内部核对与引用，不对外转载；版权归清明上河园。 | L7: f8d830af01fde307c7b60f496b62eff41e1b31d10e86028cd43df4d58c76bc4a | M7: candidate | N7: 成员1 | O7: 1 | P7: 景区简介、地址；明确迎宾门为东大门、金水门为西门。
A8: src_000005 | B8: official | C8: 清明上河园官网-预订 | D8: https://www.qingmings.com/shop.php | E8: 清明上河园（中国开封清明上河园股份有限公司） | G8: 2026-10-21T22:36:46+08:00 | H8: 2026-10-21T22:36:46+08:00 | I8: evidence/01_原始来源/清明上河园/清明上河园_官网预订_20261021.html | J8: public_view_only | K8: 仅内部核对与引用，不对外转载；版权归清明上河园。 | L8: 5b0a4344e45800b39dcee26be7aa1038897e06af5ce93a7ee26828b0b3e93519 | M8: candidate | N8: 成员1 | O8: 1 | P8: 门票预订入口；凭身份证或二维码入园。
A9: src_000006 | B9: official | C9: 清明上河园官网-门票列表（全价票） | D9: https://www.qingmings.com/shop_list.php?cid=1 | E9: 清明上河园（中国开封清明上河园股份有限公司） | G9: 2026-10-21T22:36:46+08:00 | H9: 2026-10-21T22:36:46+08:00 | I9: evidence/01_原始来源/清明上河园/清明上河园_官网门票列表_20261021.html | J9: public_view_only | K9: 仅内部核对与引用，不对外转载；版权归清明上河园。 | L9: d7930bba7c17206617c1872726a8ddd9561ff725298b6183c2146e6f225c11db | M9: candidate | N9: 成员1 | O9: 1 | P9: 门票列表；全价票120元。
A10: src_000007 | B10: official | C10: 清明上河园官网-清明上河园全价票商品详情 | D10: https://www.qingmings.com/shop_info.php?softid=1 | E10: 清明上河园（中国开封清明上河园股份有限公司） | G10: 2026-10-21T22:36:46+08:00 | H10: 2026-10-21T22:36:46+08:00 | I10: evidence/01_原始来源/清明上河园/清明上河园_官网全价票详情_20261021.html | J10: public_view_only | K10: 仅内部核对与引用，不对外转载；版权归清明上河园。 | L10: 3120d3c4a354ac54518a810c07654e63215aa21a62fa9b93066a60da63cd4c81 | M10: candidate | N10: 成员1 | O10: 1 | P10: 实名制分时预约；仅限购买当天使用；与2026-10-05新闻“一票游3天”存在冲突。
A11: src_000008 | B11: official | C11: 清明上河园官网-新闻&活动 | D11: https://www.qingmings.com/news.php | E11: 清明上河园（中国开封清明上河园股份有限公司） | G11: 2026-10-21T22:36:46+08:00 | H11: 2026-10-21T22:36:46+08:00 | I11: evidence/01_原始来源/清明上河园/清明上河园_官网新闻列表_20261021.html | J11: public_view_only | K11: 仅内部核对与引用，不对外转载；版权归清明上河园。 | L11: 0a4d65dbe4eaff0db7fe928f6c9e84af31a27b816e8d094820894387fa2cee06 | M11: candidate | N11: 成员1 | O11: 1 | P11: 新闻列表；2026-10-05“一票游3天”、2026-10-15重阳节免费等；用于冲突记录。
A12: src_000009 | B12: official | C12: 清明上河园官网-大宋·东京梦华 | D12: https://www.qingmings.com/m.php | E12: 清明上河园（中国开封清明上河园股份有限公司） | G12: 2026-10-21T22:36:46+08:00 | H12: 2026-10-21T22:36:46+08:00 | I12: evidence/01_原始来源/清明上河园/清明上河园_官网大宋东京梦华_20261021.html | J12: public_view_only | K12: 仅内部核对与引用，不对外转载；版权归清明上河园。 | L12: 39e5f527e6029abd5fb295f7818a39c2bfcecb1967584aa0b7ca892729e9ad79 | M12: candidate | N12: 成员1 | O12: 1 | P12: 《大宋·东京梦华》简介：70分钟、700多名演员、景龙湖。
A13: src_000010 | B13: official | C13: 开封万岁山武侠城官网首页 | D13: http://www.wansuishan.com.cn/website/pc/index.html | E13: 开封万岁山武侠城 | G13: 2026-10-21T23:04:19+08:00 | H13: 2026-10-21T23:04:19+08:00 | I13: evidence/01_原始来源/万岁山/万岁山_官网首页_20261021.html | J13: public_view_only | K13: 仅内部核对与引用，不对外转载；版权归万岁山武侠城。 | L13: 89be1c43908b327e5f45e614b6f146a8495d0ed9da349639a6d63680fdcbb44a | M13: candidate | N13: 成员1 | O13: 1 | P13: 官网首页（SPA 渲染后保存）；含地址、8:00~21:00 检票时间、客服电话；未执行脚本。
A14: src_000011 | B14: official | C14: 论！一个景区有七个入口！是什么样的体验？丝滑入园不排队，最强攻略来啦！ | D14: http://www.wansuishan.com.cn/website/pc/index.html#/newsDetail/37 | E14: 开封万岁山武侠城 | F14: 2025-12-19T17:30:00+08:00 | G14: 2026-10-21T23:04:19+08:00 | H14: 2026-10-21T23:04:19+08:00 | I14: evidence/01_原始来源/万岁山/万岁山_官网七个入口_20261021.html | J14: public_view_only | K14: 仅内部核对与引用，不对外转载；版权归万岁山武侠城。 | L14: 0b463d2626e73d295741dcf80a6c70d4986d08a99d3ff2af7e41685e7089f24a | M14: candidate | N14: 成员1 | O14: 1 | P14: 官方文章；正文为图片，关键图片存于 evidence/01_原始来源/万岁山/七个入口/；入口名单见 万岁山_七个入口名单与地图_20261021.png；公告见 万岁山_七个入口公告_20261021.png。
A15: src_000012 | B15: official | C15: 万岁山官网-必看推荐 | D15: http://www.wansuishan.com.cn/website/pc/index.html#/recommend | E15: 开封万岁山武侠城 | G15: 2026-10-21T23:07:50+08:00 | H15: 2026-10-21T23:07:50+08:00 | I15: evidence/01_原始来源/万岁山/万岁山_官网必看推荐_20261021.html | J15: public_view_only | K15: 仅内部核对与引用，不对外转载；版权归万岁山武侠城。 | L15: 93ad7d314b8e823b9f2f53e94c2fa1a7c95faf34081d545f9116c518ae0af2b6 | M15: candidate | N15: 成员1 | O15: 1 | P15: 官网必看推荐页；含打铁花、三打祝家庄、王婆说媒、城北枪声、江湖音乐节、室内三大剧场、仙侠巡游介绍。
A16: src_000013 | B16: provider | C16: 美团（官方公众号购票入口）-万岁山武侠城门票页 | E16: 美团 | G16: 2026-10-21T23:11:20+08:00 | H16: 2026-10-21T23:11:20+08:00 | I16: evidence/02_次要来源/万岁山/万岁山_美团门票页_20261021.png | J16: public_view_only | K16: 仅内部核对与引用，不对外转载；截图由成员1提供。 | L16: 3cd1dd96f44eb2d7d01f60e3f7d6b2ec9899c01b3595f54e36474bf01e833b76 | M16: candidate | N16: 成员1 | O16: 1 | P16: 用户从官方微信公众号“购票”入口跳转到该美团页面；官方抢票小程序提示“不在预约范围内”，无法打开。另附门票列表2、成人票详情、费用说明截图：08:00-23:00开放、最晚21:00入园；成人票100起、优惠票50起、大马戏118/80起、汴河游船联票128/68起、城墙观光车联票120/70起；万岁山入园时间08:00-21:00；自核销当日起3个自然日内不限次入园；未使用可随时全额退款，过期后1天自动退款，下单后不支持改期。
A17: src_000014 | B17: official | C17: 万岁山官方节目单（十里洋场区/水浒区/山水田园区/江湖艺术狂欢区/仙侠奇境区） | E17: 开封万岁山武侠城 | G17: 2026-10-21T23:32:23+08:00 | H17: 2026-10-21T23:32:23+08:00 | I17: evidence/01_原始来源/万岁山/节目单/万岁山_官方节目单_水浒区山水田园区_20261021.png | J17: public_view_only | K17: 仅内部核对与引用，不对外转载；截图由成员1提供。 | L17: 386c9bd5f5f43882725a303b01e28501041ac58947fb1e8174826df06df6cd00 | M17: candidate | N17: 成员1 | O17: 1 | P17: 官方公众号节目单截图，由成员1提供；含十里洋场区、水浒区、山水田园区、江湖艺术狂欢区、仙侠奇境区；截图日期2026-10-21。节目单为常规时刻，不是逐日场次，未据此建14表。
A18: src_000015 | B18: official | C18: 开封府官网首页 | D18: http://www.kaifengfu.cn/ | E18: 开封府（开封“开封府”旅游开发有限公司） | G18: 2026-10-21T23:34:08+08:00 | H18: 2026-10-21T23:34:08+08:00 | I18: evidence/01_原始来源/开封府/开封府_官网首页_20261021.html | J18: public_view_only | K18: 仅内部核对与引用，不对外转载；版权归开封府。 | L18: 67e98e359ff68f2bbafec78c3821ff3de180a8045678073beca8683a9258be60 | M18: candidate | N18: 成员1 | O18: 1 | P18: 官网首页；地址、电话、日间/夜游票价、开放时间、演出节目单。
A19: src_000016 | B19: official | C19: 开封府官网-预约购票/演出节目单 | D19: http://www.kaifengfu.cn/contact/goupiao.asp | E19: 开封府（开封“开封府”旅游开发有限公司） | G19: 2026-10-21T23:34:08+08:00 | H19: 2026-10-21T23:34:08+08:00 | I19: evidence/01_原始来源/开封府/开封府_官网预约购票_20261021.html | J19: public_view_only | K19: 仅内部核对与引用，不对外转载；版权归开封府。 | L19: c4fa268d84c836245a314bade6938f0504f7af504abcfd14c51ace3692deea3f | M19: candidate | N19: 成员1 | O19: 1 | P19: 官网预约购票页；完整演出节目单、日间/夜游票价、入园须知；节目单更新见2026-10-08新闻。
A20: src_000017 | B20: official | C20: 开封府官网-参观指南 | D20: http://www.kaifengfu.cn/zhinan | E20: 开封府（开封“开封府”旅游开发有限公司） | G20: 2026-10-21T23:34:08+08:00 | H20: 2026-10-21T23:34:08+08:00 | I20: evidence/01_原始来源/开封府/开封府_官网参观指南_20261021.html | J20: public_view_only | K20: 仅内部核对与引用，不对外转载；版权归开封府。 | L20: d0ebb5bbd93add343fa4301d8f8e5d262309486ed2c0ad786bcbb6aff2d55c0a | M20: candidate | N20: 成员1 | O20: 1 | P20: 官网参观指南；游客须知、开放时间（夏季7:00-19:00/冬季7:30-18:30）、票价。
A21: src_000018 | B21: official | C21: 龙亭官网-游园指南 | D21: http://www.kfltjq.com/sys-nd/16.html | E21: 开封市龙亭景区 | F21: 2022-08-04T18:16:00+08:00 | G21: 2026-10-21T23:37:02+08:00 | H21: 2026-10-21T23:37:02+08:00 | I21: evidence/01_原始来源/龙亭/龙亭_官网游园指南_20261021.html | J21: public_view_only | K21: 仅内部核对与引用，不对外转载；版权归开封市龙亭景区。 | L21: af31d6ddc0ebbdfa1ff7381733f5906970abcb1f710f7e23a029849a6c73756a | M21: candidate | N21: 成员1 | O21: 1 | P21: 门票45/22、开放08:00-21:30、南门/北门、地址电话、公交。
A22: src_000019 | B22: official | C22: 龙亭官网-龙亭概况 | D22: http://www.kfltjq.com/sys-nd/14.html | E22: 开封市龙亭景区 | F22: 2022-08-04T18:10:00+08:00 | G22: 2026-10-21T23:37:02+08:00 | H22: 2026-10-21T23:37:02+08:00 | I22: evidence/01_原始来源/龙亭/龙亭_官网龙亭概况_20261021.html | J22: public_view_only | K22: 仅内部核对与引用，不对外转载；版权归开封市龙亭景区。 | L22: b95fd95c2bccf24fd9cba9ebfbc356c80e23c1427b7a934d6e06063e518186b6 | M22: candidate | N22: 成员1 | O22: 1 | P22: AAAA景区介绍；列出《太祖大典》《皇城司》《江山乐舞》《大宋科举》《宫廷迎宾》等节目名，未给时间。
A23: src_000020 | B23: official | C23: 龙亭官网-节目表 | D23: http://www.kfltjq.com/h-col-108.html | E23: 开封市龙亭景区 | G23: 2026-10-21T23:37:02+08:00 | H23: 2026-10-21T23:37:02+08:00 | I23: evidence/01_原始来源/龙亭/龙亭_官网节目表_20261021.html | J23: public_view_only | K23: 仅内部核对与引用，不对外转载；版权归开封市龙亭景区。 | L23: ad777a6dcf91b05be9139c282d6a100b4987f240e49bc2668b3432cb4a90b52b | M23: candidate | N23: 成员1 | O23: 1 | P23: 官网节目表页仅提示扫码关注龙亭景区公众号查看节目单，未列具体时间；13表时间待补。
A24: src_000021 | B24: official | C24: 开封市A级旅游景区名录 | D24: http://www.kfsfq.gov.cn/cxythsfq/ly/pc/content/content_1874704907328372736.html | E24: 开封市城乡一体化示范区人民政府 | G24: 2026-10-21T23:41:48+08:00 | H24: 2026-10-21T23:41:48+08:00 | I24: evidence/01_原始来源/大相国寺/开封市A级旅游景区名录_20261021.html | J24: public_view_only | K24: 仅内部核对与引用，不对外转载；政府公开信息。 | L24: b6b88792a814706fcad967b57cb7535ed30e2fe7c9b878a969d7cb0647eece07 | M24: candidate | N24: 成员1 | O24: 1 | P24: 政府名录：大相国寺为4A。
A25: src_000022 | B25: official | C25: 大相国寺-河南省退役军人事务厅 | D25: https://tyjrswt.henan.gov.cn/2025/02-28/3129957.html | E25: 河南省退役军人事务厅 | F25: 2025-02-28T00:00:00+08:00 | G25: 2026-10-21T23:41:48+08:00 | H25: 2026-10-21T23:41:48+08:00 | I25: evidence/01_原始来源/大相国寺/河南省退役军人事务厅_大相国寺_20261021.html | J25: public_view_only | K25: 仅内部核对与引用，不对外转载；政府公开信息。 | L25: bef8bb63e57bc17131adeb2dd958b2d74a2ca3b9b71a625b1387dbd8f2ff4ab0 | M25: candidate | N25: 成员1 | O25: 1 | P25: 所在地鼓楼区；类别旅游景区；面向全省优待证持证人免门票。
A26: src_000023 | B26: provider | C26: 去哪儿网-大相国寺门票页 | D26: https://piao.qunar.com/ticket/detail_6468.html | E26: 去哪儿网 | G26: 2026-10-21T23:41:48+08:00 | H26: 2026-10-21T23:41:48+08:00 | I26: evidence/02_次要来源/大相国寺/大相国寺_去哪儿门票页_20261021.html | J26: public_view_only | K26: 仅内部核对与引用，不对外转载；截图/页面由成员1采集。 | L26: 64510f5988234f8e6e4026a994894c011f94092f62690a3b42e2490bfe8ecdcf | M26: candidate | N26: 成员1 | O26: 1 | P26: 地址、冬/春秋/夏开放时间、停止入园时间、免票/半价政策；OTA次要来源。
A27: src_000024 | B27: provider | C27: 大河票务网-2025开封大相国寺门票及预约入口 | D27: https://m.dahepiao.com/news/20251217539870.html | E27: 大河票务网 | F27: 2025-12-17T08:53:00+08:00 | G27: 2026-10-21T23:41:48+08:00 | H27: 2026-10-21T23:41:48+08:00 | I27: evidence/02_次要来源/大相国寺/大相国寺_大河票务门票文章_20261021.html | J27: public_view_only | K27: 仅内部核对与引用，不对外转载；页面由成员1采集。 | L27: 5764e017e197523da7da67737dd993e9a1afe5591f23135d95f7addb78263c32 | M27: candidate | N27: 成员1 | O27: 1 | P27: 开放时间、地址、门票价格（成人37.5/优待19）、简介；OTA次要来源。
A28: src_000025 | B28: official | C28: 龙亭景区官方节目单（白天/夜游） | E28: 开封市龙亭景区 | G28: 2026-10-21T23:45:12+08:00 | H28: 2026-10-21T23:45:12+08:00 | I28: evidence/01_原始来源/龙亭/节目单/龙亭_官方节目单_白天夜游_20261021.jpg | J28: public_view_only | K28: 仅内部核对与引用，不对外转载；截图由成员1提供。 | L28: 036b68ee8423db5b681c17259f95ee121b1b54b47c4be101ff8dcec2af5f87af | M28: candidate | N28: 成员1 | O28: 1 | P28: 官方节目单截图，由成员1提供；含白天+夜游；常规时刻，不是逐日场次；未据此建14表。
A29: src_000026 | B29: research | C29: 门票价格调整！开封一景区发布最新公告！ | D29: https://www.hntv.tv/news/0/1915212805625851906 | E29: 河南交通广播/大象新闻 | F29: 2025-04-24T09:14:50+08:00 | G29: 2026-10-21T23:49:01+08:00 | H29: 2026-10-21T23:49:01+08:00 | I29: evidence/02_次要来源/铁塔/铁塔_河南交通广播营业时间票价公告_20261021.html | J29: public_view_only | K29: 仅内部核对与引用，不对外转载；页面由成员1采集。 | L29: daa84e099b2a19cc343ca877431a1b3da2b28ee60df3a6ccab6ae7eb34899278 | M29: candidate | N29: 成员1 | O29: 1 | P29: 2025-04-24河南交通广播转述开封铁塔景区公告：08:30-18:00，17:30停止售票，成人30/儿童学生15，光影秀暂停。
A30: src_000027 | B30: research | C30: 2026开封铁塔景区国庆有什么好玩的？ | D30: https://m.kf.bendibao.com/xiuxian/24874.shtm | E30: 开封本地宝 | F30: 2026-09-27T19:55:00+08:00 | G30: 2026-10-21T23:49:01+08:00 | H30: 2026-10-21T23:49:01+08:00 | I30: evidence/02_次要来源/铁塔/铁塔_本地宝2026国庆活动_20261021.html | J30: public_view_only | K30: 仅内部核对与引用，不对外转载；页面由成员1采集。 | L30: 1b7a4f45d40cded3b0df40b4a75f3b88cafa7c4dced8f1da7cc106e5c03063fb | M30: candidate | N30: 成员1 | O30: 1 | P30: 2026国庆活动：纳土归宋/铁塔匠心 9/10-11/30；五灵寻境 9/19-11/30；把菊吟诗 9/25-10/17 10:00-17:00；地址北门大街210号。
A31: src_000028 | B31: official | C31: 翰园碑林官网-翰园介绍 | D31: https://www.zghybl.cn/about.html | E31: 中国翰园碑林 | G31: 2026-10-21T23:52:09+08:00 | H31: 2026-10-21T23:52:09+08:00 | I31: evidence/01_原始来源/翰园碑林/翰园碑林_官网翰园介绍_20261021.html | J31: public_view_only | K31: 仅内部核对与引用，不对外转载；版权归中国翰园碑林。 | L31: 0831387a16a5d253c923bae8d9ad4083d7cc76f5d12f29908e564b0b3b1f15b5 | M31: candidate | N31: 成员1 | O31: 1 | P31: AAAA、占地120亩、刻碑4000多块、中国书法名园。
A32: src_000029 | B32: official | C32: 翰园碑林官网-游园攻略 | D32: https://www.zghybl.cn/raiders.html | E32: 中国翰园碑林 | G32: 2026-10-21T23:52:09+08:00 | H32: 2026-10-21T23:52:09+08:00 | I32: evidence/01_原始来源/翰园碑林/翰园碑林_官网游园攻略_20261021.html | J32: public_view_only | K32: 仅内部核对与引用，不对外转载；版权归中国翰园碑林。 | L32: bb9736da169978c9c4bb85a11213cf30c56720fd65c3ed34e3ec14f42e573b4b | M32: candidate | N32: 成员1 | O32: 1 | P32: 推荐线路以南大门/北大门为起终点；南门、北门均可进出。
A33: src_000030 | B33: official | C33: 翰园碑林官网-联系我们 | D33: https://www.zghybl.cn/contact.html | E33: 中国翰园碑林 | G33: 2026-10-21T23:52:09+08:00 | H33: 2026-10-21T23:52:09+08:00 | I33: evidence/01_原始来源/翰园碑林/翰园碑林_官网联系我们_20261021.html | J33: public_view_only | K33: 仅内部核对与引用，不对外转载；版权归中国翰园碑林。 | L33: d81c9159d00930a70e2f8bc82cf2de2ac422aed1cb16fe1474f01506fe03ac39 | M33: candidate | N33: 成员1 | O33: 1 | P33: 地址龙亭北路15号、电话0371-22891558、页脚开放时间8:00-22:00。
A34: src_000031 | B34: provider | C34: 大河票务网-2025中国翰园碑林简介/门票价格 | D34: https://m.dahepiao.com/news/20250827527701.html | E34: 大河票务网 | F34: 2025-08-27T10:20:00+08:00 | G34: 2026-10-21T23:52:09+08:00 | H34: 2026-10-21T23:52:09+08:00 | I34: evidence/02_次要来源/翰园碑林/翰园碑林_大河票务门票文章_20261021.html | J34: public_view_only | K34: 仅内部核对与引用，不对外转载；页面由成员1采集。 | L34: eeb9de2f4a5a1c5f99882cc93682ad46d39fad967cdce877e7023a8520fb3d9f | M34: candidate | N34: 成员1 | O34: 1 | P34: 门票成人40/优待20；开放08:00-22:00；地址；联票价格；OTA次要来源。
A35: src_000032 | B35: official | C35: 包公祠-豫台视窗 | D35: https://ytsc.rootinhenan.gov.cn/sitesources/ytsc/page_pc/hnly/fjms/article52dbbd16f4d543278692665bc2d2533d.html | E35: 河南省人民政府台湾事务办公室 | F35: 2008-05-28T14:41:54+08:00 | G35: 2026-10-21T23:55:42+08:00 | H35: 2026-10-21T23:55:42+08:00 | I35: evidence/01_原始来源/包公祠/包公祠_豫台视窗_20261021.html | J35: public_view_only | K35: 仅内部核对与引用，不对外转载；政府公开信息。 | L35: ed04d5c9952cc91d4b36daded1ec15507eb2e1e86910a4f781fb17273717804c | M35: candidate | N35: 成员1 | O35: 1 | P35: 4A、地址向阳路1号、营业7:00-19:00、门票20元（2008年信息）、描述。
A36: src_000033 | B36: provider | C36: 2025开封包公祠景点简介+门票价格+免费政策+游玩路线 | D36: https://m.dahepiao.com/news/20250605515582.html | E36: 大河票务网 | F36: 2025-06-05T10:46:00+08:00 | G36: 2026-10-21T23:55:42+08:00 | H36: 2026-10-21T23:55:42+08:00 | I36: evidence/02_次要来源/包公祠/包公祠_大河票务门票文章_20261021.html | J36: public_view_only | K36: 仅内部核对与引用，不对外转载；页面由成员1采集。 | L36: 363a54288e68b152005a8978fb86ebe5f04be6ceb6f5eaa529df6d2215032a91 | M36: candidate | N36: 成员1 | O36: 1 | P36: 04/01-10/31 07:00-19:00；11/01-03/31 07:30-17:30；线上成人27；游玩路线东门→...
A37: src_000034 | B37: research | C37: 包公祠-河南旅游网 | D37: http://www.uhenan.com/ScenicArea/Content/S1194968738378620928 | E37: 河南旅游网 | G37: 2026-10-21T23:55:42+08:00 | H37: 2026-10-21T23:55:42+08:00 | I37: evidence/02_次要来源/包公祠/包公祠_河南旅游网_20261021.html | J37: public_view_only | K37: 仅内部核对与引用，不对外转载；页面由成员1采集。 | L37: 00cbc389594c641b187ab380af749726bfe4635d7f1ef75f9d4127a6ff0edc2b | M37: candidate | N37: 成员1 | O37: 1 | P37: 4A、电话0371-23931595、门票20/开放7:00-19:00（旧）、描述。
A38: src_000035 | B38: provider | C38: 去哪儿网-天波杨府门票页 | D38: http://piao.qunar.com/ticket/detail_10501.html | E38: 去哪儿网 | G38: 2026-10-22T00:01:06+08:00 | H38: 2026-10-22T00:01:06+08:00 | I38: evidence/02_次要来源/天波杨府/天波杨府_去哪儿门票页_20261022.html | J38: public_view_only | K38: 仅内部核对与引用，不对外转载；页面由成员1采集。 | L38: 1dbd33821b1f4a6783e28d1716eddb26c14e8b8eb23cdab1fff60d2df1c335ea | M38: candidate | N38: 成员1 | O38: 1 | P38: 地址龙亭北路14号；08:00-22:00、21:30停止入园；描述；免票/半价政策。
A39: src_000036 | B39: official | C39: 天波杨府-河南省退役军人事务厅 | D39: https://tyjrswt.henan.gov.cn/2025/02-28/3129954.html | E39: 河南省退役军人事务厅 | F39: 2025-02-28T00:00:00+08:00 | G39: 2026-10-22T00:01:06+08:00 | H39: 2026-10-22T00:01:06+08:00 | I39: evidence/01_原始来源/天波杨府/天波杨府_河南省退役军人事务厅_20261022.html | J39: public_view_only | K39: 仅内部核对与引用，不对外转载；政府公开信息。 | L39: 82edcb23a62a6989de8bc327f08834770b7b70f97bccc16f36f32cee7eb5c95c | M39: candidate | N39: 成员1 | O39: 1 | P39: 所在地龙亭区；类别旅游景区；优待证持证人免门票。
A40: src_000037 | B40: research | C40: 天波杨府-河南景区详情 | D40: https://huilongwenlv.com/resources/44666/%E5%A4%A9%E6%B3%A2%E6%9D%A8%E5%BA%9C/ | E40: 辉龙科技文化旅游资源推荐系统 | G40: 2026-10-22T00:01:06+08:00 | H40: 2026-10-22T00:01:06+08:00 | I40: evidence/02_次要来源/天波杨府/天波杨府_河南景区详情_20261022.html | J40: public_view_only | K40: 仅内部核对与引用，不对外转载；页面由成员1采集。 | L40: ef1e4d390332f68cb658fa79a71986e5c5f948f6dcf5dadb17ba031e51b21911 | M40: candidate | N40: 成员1 | O40: 1 | P40: 4A、地址、电话0371-22890559/22890553、旧开放8:00-18:00、门票30、官网tianbo.kf.cn（已失效）。
A41: src_000038 | B41: official | C41: 开封城墙官网-游玩指南 | D41: http://kfcqjq.com/www/wan/detail/id/14.html | E41: 开封市宋都城墙景区 | G41: 2026-10-22T00:05:18+08:00 | H41: 2026-10-22T00:05:18+08:00 | I41: evidence/01_原始来源/开封城墙/开封城墙_官网游玩指南_20261022.html | J41: public_view_only | K41: 仅内部核对与引用，不对外转载；版权归开封市宋都城墙景区。 | L41: d72857810b5235546618519baa2021b8d87d7d5a4d4d770f6abbc826be532da5 | M41: candidate | N41: 成员1 | O41: 1 | P41: 营业时间夏8:30-22:00/冬8:30-21:30；全价40/半价20；四个登城口；地址电话。
A42: src_000039 | B42: official | C42: 开封城墙官网-微梦大梁门 | D42: http://www.kfcqjq.com/www/weimeng/index.html | E42: 开封市宋都城墙景区 | G42: 2026-10-22T00:05:18+08:00 | H42: 2026-10-22T00:05:18+08:00 | I42: evidence/01_原始来源/开封城墙/开封城墙_官网微梦大梁门_20261022.html | J42: public_view_only | K42: 仅内部核对与引用，不对外转载；版权归开封市宋都城墙景区。 | L42: e608c6d721066fd76f9b4dc0ce5487f9a3dbba3cf98233a647ecde80c6da00ff | M42: candidate | N42: 成员1 | O42: 1 | P42: 《古马道》9:00-21:00 古马道遗址展馆；《微梦大梁门》9:15-21:15 大梁门城门一楼。
A43: src_000040 | B43: official | C43: 开封山陕甘会馆简介-龙亭区人民政府 | D43: http://www.longting.gov.cn/ltq/c00613/pc/content/content_2002670421052616704.html | E43: 开封市龙亭区人民政府 | G43: 2026-10-22T00:07:15+08:00 | H43: 2026-10-22T00:07:15+08:00 | I43: evidence/01_原始来源/山陕甘会馆/山陕甘会馆_龙亭区政府_20261022.html | J43: public_view_only | K43: 仅内部核对与引用，不对外转载；政府公开信息。 | L43: e1ce614b026ab9d799d24a4241c29681dcdc5577af96e4737d455e2dc6ff3fe6 | M43: candidate | N43: 成员1 | O43: 1 | P43: 地址徐府街85号、清乾隆四十一年建、全国重点文物保护单位、砖石木雕三绝、描述。
A44: src_000041 | B44: official | C44: 开封山陕甘会馆-河南省退役军人事务厅 | D44: https://tyjrswt.henan.gov.cn/2025/02-28/3129953.html | E44: 河南省退役军人事务厅 | F44: 2025-02-28T00:00:00+08:00 | G44: 2026-10-22T00:07:15+08:00 | H44: 2026-10-22T00:07:15+08:00 | I44: evidence/01_原始来源/山陕甘会馆/山陕甘会馆_河南省退役军人事务厅_20261022.html | J44: public_view_only | K44: 仅内部核对与引用，不对外转载；政府公开信息。 | L44: 7e00b399597f4456b28b43b2bcb854bac33d40161624beff8286878ede5e5639 | M44: candidate | N44: 成员1 | O44: 1 | P44: 所在地龙亭区；类别旅游景区；优待证持证人免门票。
A45: src_000042 | B45: provider | C45: 2025山陕甘会馆参观简介+门票价格+购票入口 | D45: https://m.dahepiao.com/news/20250924531554.html | E45: 大河票务网 | F45: 2025-09-24T10:36:00+08:00 | G45: 2026-10-22T00:07:15+08:00 | H45: 2026-10-22T00:07:15+08:00 | I45: evidence/02_次要来源/山陕甘会馆/山陕甘会馆_大河票务_20261022.html | J45: public_view_only | K45: 仅内部核对与引用，不对外转载；页面由成员1采集。 | L45: 08fbf36abb5a8152e0f68170f30b279ec75c56c901281e6b85a8d59bea6c3146 | M45: candidate | N45: 成员1 | O45: 1 | P45: 开放08:00-18:00/08:00-17:30；线上成人22.31；地址；建筑介绍。
A46: src_000043 | B46: research | C46: 延庆观旅游指南-忆起追迹（全国重点文物保护单位） | D46: https://www.iwenbo.fun/heritage/513.html | E46: 忆起追迹 | G46: 2026-10-22T00:09:25+08:00 | H46: 2026-10-22T00:09:25+08:00 | I46: evidence/02_次要来源/延庆观/延庆观_忆起追迹_20261022.html | J46: public_view_only | K46: 仅内部核对与引用，不对外转载；页面由成员1采集。 | L46: 04abc35ae5679138b98bd27b1643a19c97e0019f98667e52423518327c6b71a8 | M46: candidate | N46: 成员1 | O46: 1 | P46: 国保信息：地址观前街53号、鼓楼区；开放8:00-18:30、门票30；2012年AAA说法。
A47: src_000044 | B47: research | C47: 延庆观-中国华夏文化遗产基金会 | D47: https://www.cchfound.com/product/3560.html | E47: 中国华夏文化遗产基金会 | G47: 2026-10-22T00:09:25+08:00 | H47: 2026-10-22T00:09:25+08:00 | I47: evidence/02_次要来源/延庆观/延庆观_中国华夏文化遗产基金会_20261022.html | J47: public_view_only | K47: 仅内部核对与引用，不对外转载；页面由成员1采集。 | L47: 47f14fc14c38476f72c69c5108a1912ee3fb5f0bdd52d8eaf5ab582241c105c7 | M47: candidate | N47: 成员1 | O47: 1 | P47: 延庆观历史、玉皇阁18.25米、三路布局、地址观前街53号、三大名观。
A48: src_000045 | B48: provider | C48: 开封延庆观旅游攻略-要出发周边游 | D48: https://you.yaochufa.com/p_kaifengyanqingguan | E48: 要出发周边游 | G48: 2026-10-22T00:09:25+08:00 | H48: 2026-10-22T00:09:25+08:00 | I48: evidence/02_次要来源/延庆观/延庆观_要出发周边游_20261022.html | J48: public_view_only | K48: 仅内部核对与引用，不对外转载；页面由成员1采集。 | L48: 73e73138f4f8393dbf5531618e0f7e75364bb53b2bab22840bcd4ba39ed43d4d | M48: candidate | N48: 成员1 | O48: 1 | P48: 门票门市价15元、开放8:00-18:30、地址观前街53号。
A49: src_000046 | B49: research | C49: 2026开封延庆观旅游攻略-相约久久 | D49: https://m.meet99.com/jingdian-yanqingguan-132242 | E49: 相约久久 | G49: 2026-10-22T00:09:25+08:00 | H49: 2026-10-22T00:09:25+08:00 | I49: evidence/02_次要来源/延庆观/延庆观_相约久久_20261022.html | J49: public_view_only | K49: 仅内部核对与引用，不对外转载；页面由成员1采集。 | L49: 3896d6c633e596f28f9373e61fd871c722fe86d81c491600beaeb2e1ba29fe5a | M49: candidate | N49: 成员1 | O49: 1 | P49: 门票35元、开放09:00-17:30；与忆起追迹/要出发口径冲突。
A50: src_000047 | B50: official | C50: 餐饮及夜市提质行动助力开封市文旅提质-河南省人民政府 | D50: https://www.henan.gov.cn/2024/10-24/3077707.html | E50: 河南省人民政府（来源：开封市人民政府） | F50: 2024-10-25T14:50:00+08:00 | G50: 2026-10-22T00:14:08+08:00 | H50: 2026-10-22T00:14:08+08:00 | I50: evidence/01_原始来源/夜市/河南省政府_夜市提质_20261022.html | J50: public_view_only | K50: 仅内部核对与引用，不对外转载；政府公开信息。 | L50: 04d515e1148c62c4353b23614fa69ae04fd06e3696a63abba9abb2f303701c37 | M50: candidate | N50: 成员1 | O50: 1 | P50: 三大夜市：老河大夜市（青春记忆）、鼓楼夜市（古都文化）、西司夜市（市井烟火）。
A51: src_000048 | B51: official | C51: 开封夜市，崭新面貌待宾朋-开封市人民政府 | D51: https://www.kaifeng.gov.cn/kfsrmzfwz/zwyw/pc/content/content_1848889112874242048.html | E51: 开封市人民政府 | G51: 2026-10-22T00:14:08+08:00 | H51: 2026-10-22T00:14:08+08:00 | I51: evidence/01_原始来源/夜市/开封市政府_夜市评论员文章_20261022.html | J51: public_view_only | K51: 仅内部核对与引用，不对外转载；政府公开信息。 | L51: 5dcfdb93135a37e07adea04685d234fc09f45df232c493390047699ed97abb62 | M51: candidate | N51: 成员1 | O51: 1 | P51: 鼓楼夜市（古都文化）、西司夜市（市井烟火）、老河大夜市（青春记忆）；夜市提质六大一。
A52: src_000049 | B52: provider | C52: 携程-开封鼓楼夜市 | D52: https://you.ctrip.com/sight/kaifeng165/4926441.html | E52: 携程 | G52: 2026-10-22T00:14:08+08:00 | H52: 2026-10-22T00:14:08+08:00 | I52: evidence/02_次要来源/夜市/鼓楼夜市_携程_20261022.html | J52: public_view_only | K52: 仅内部核对与引用，不对外转载；页面由成员1采集。 | L52: d55e59320a4cff99987414956d00f38713521a3a40b19dc348533a5b7e6c56e4 | M52: candidate | N52: 成员1 | O52: 1 | P52: 地址鼓楼区鼓楼街鼓楼南广场；平台标10:00-22:00；电话0371-22627890；介绍。
A53: src_000050 | B53: research | C53: 老河大夜市，追寻青春记忆-百家号 | D53: https://baijiahao.baidu.com/s?id=1778714820220805934 | E53: 百家号（陈起2023） | F53: 2023-10-03T14:30:00+08:00 | G53: 2026-10-22T00:14:08+08:00 | H53: 2026-10-22T00:14:08+08:00 | I53: evidence/02_次要来源/夜市/老河大夜市_百家号_20261022.html | J53: public_view_only | K53: 仅内部核对与引用，不对外转载；页面由成员1采集。 | L53: 0520cb0c8fc24a536a63a52502c7a361f73eb057061ef0107e084aa41dade717 | M53: candidate | N53: 成员1 | O53: 1 | P53: 地址河大西门外内环东路北段与龙亭北路交叉口；约200米；天黑而聚、凌晨而散；小吃描述。
A54: src_000051 | B54: official | C54: 开封大相国寺官方小程序-自助购票/购票须知 | E54: 开封大相国寺 | G54: 2026-10-22T00:16:55+08:00 | H54: 2026-10-22T00:16:55+08:00 | I54: evidence/01_原始来源/大相国寺/大相国寺_官方小程序购票须知_20261022_1.png | J54: public_view_only | K54: 仅内部核对与引用，不对外转载；截图由成员1提供。 | L54: df9ffb1289002fcb914c7960e742686d4566504ec07f28b1aa1db040d2a48bb5 | M54: candidate | N54: 成员1 | O54: 1 | P54: 官方小程序：4A；全价40/半价20；开放8:00-18:00；无需取票，二维码/身份证入园；仅限当日有效；未使用可随时退，刷码后不退；半价票适用6-18岁、学生、教师等。
A55: src_000052 | B55: official | C55: 清明上河园官方小程序-今日节目单 | E55: 清明上河园 | G55: 2026-10-22T00:16:55+08:00 | H55: 2026-10-22T00:16:55+08:00 | I55: evidence/01_原始来源/清明上河园/清明上河园_官方小程序今日节目单_20261022_1.png | J55: public_view_only | K55: 仅内部核对与引用，不对外转载；截图由成员1提供。 | L55: fa40b6a73d89f85fb9be8e7bb0eb1d1c9ce6ed3f401c661b7564e7933cc8ee84 | M55: candidate | N55: 成员1 | O55: 1 | P55: 官方小程序手绘地图-今日节目单；截图2026-10-22；今日页面未标日期；常规时刻，未建14表。
A56: src_000053 | B56: official | C56: 铁塔景区官方节目单 | E56: 开封铁塔景区 | G56: 2026-10-22T00:16:55+08:00 | H56: 2026-10-22T00:16:55+08:00 | I56: evidence/01_原始来源/铁塔/铁塔_官方节目单_20261022.png | J56: public_view_only | K56: 仅内部核对与引用，不对外转载；截图由成员1提供。 | L56: 4f0e908a9a6421c28f35b74453595dfe57246a17f28396a8b9d96226a8fafe86 | M56: candidate | N56: 成员1 | O56: 1 | P56: 官方节目单：时间/地点/内容/类型；所有节目因天气或特殊原因以当天广播为准。
A57: src_000054 | B57: official | C57: 铁塔景区门票价格公示牌 | E57: 开封铁塔景区 | G57: 2026-10-22T00:16:55+08:00 | H57: 2026-10-22T00:16:55+08:00 | I57: evidence/01_原始来源/铁塔/铁塔_官方门票价格公示牌_20261022.jpg | J57: public_view_only | K57: 仅内部核对与引用，不对外转载；截图由成员1提供。 | L57: 2b3221c73baea314e4231595582da0b93e6fc7fbc939357d2b3b24bd71780151 | M57: candidate | N57: 成员1 | O57: 1 | P57: 全价30元/半价15元；免费票适用人群；执行对象。
A58: src_000055 | B58: field_check | C58: 铁塔景区客服回复（用户转述） | E58: 开封铁塔景区客服 | G58: 2026-10-22T00:16:55+08:00 | H58: 2026-10-22T00:16:55+08:00 | I58: evidence/01_原始来源/铁塔/铁塔_客服回复_20261022.txt | J58: public_view_only | K58: 仅内部核对与引用；用户转述，建议补截图/录音。 | L58: 780a42d3e0ffd5f94c7df9a46af7a1ff6bbd9844fdc3544beef3e37c32569a80 | M58: candidate | N58: 成员1 | O58: 1 | P58: 景区客服：营业8:30-21:00；《五灵寻禅》10:00-17:00，周一NPC休息；具体以节目单为准。
A59: src_000056 | B59: research | C59: 2025端午假期开封夜市推荐-开封本地宝 | D59: http://kf.bendibao.com/jieri/2025430/21329.shtm | E59: 开封本地宝 | F59: 2025-05-29T11:45:00+08:00 | G59: 2026-10-22T00:21:49+08:00 | H59: 2026-10-22T00:21:49+08:00 | I59: evidence/02_次要来源/夜市/西司夜市_本地宝_20261022.html | J59: public_view_only | K59: 仅内部核对与引用，不对外转载；页面由成员1采集。 | L59: caad5783a075daa98007e30bad177bd1d75789db83665b36872c862e4dee88c5 | M59: candidate | N59: 成员1 | O59: 1 | P59: 西司夜市位于鼓楼区包公祠附近丁角街，规模较大，上百个摊位；推荐小吃；未写营业时间。
A60: src_000057 | B60: research | C60: 开封五万平米“宋城”迎客 大宋市井繁华再现-央广网 | D60: http://travel.cnr.cn/lyjd/610/201311/t20131120_514181619.shtml | E60: 央广网（来源：中国新闻网） | F60: 2013-11-20T07:24:00+08:00 | G60: 2026-10-22T00:24:57+08:00 | H60: 2026-10-22T00:24:57+08:00 | I60: evidence/02_次要来源/汴梁小宋城/汴梁小宋城_央广网开城报道_20261022.html | J60: public_view_only | K60: 仅内部核对与引用，不对外转载；页面由成员1采集。 | L60: a3e4e8946764262bbe75f66fb59d1e6a7f60f649b458aa8305faa2d762bd1646 | M60: candidate | N60: 成员1 | O60: 1 | P60: 2013开城报道：原东京艺术中心改造，约5万㎡，餐饮街区2万㎡，《千回大宋》在东京艺术中心上演。
A61: src_000058 | B61: provider | C61: 小宋城千回大宋演出门票-大河票务网 | D61: https://m.dahepiao.com/yanchupiaowu1/2016061817461.html | E61: 大河票务网 | G61: 2026-10-22T00:24:57+08:00 | H61: 2026-10-22T00:24:57+08:00 | I61: evidence/02_次要来源/汴梁小宋城/汴梁小宋城_大河票务千回大宋_20261022.html | J61: public_view_only | K61: 仅内部核对与引用，不对外转载；页面由成员1采集。 | L61: f782612f3a8d53aaee6dabe3b39158a5cef5a84567298cac13fe22c6f3ac5736 | M61: candidate | N61: 成员1 | O61: 1 | P61: 《千回大宋》每晚20:00-21:20，80分钟；票面188/288；地址大梁路西段。
A62: src_000059 | B62: provider | C62: 汴梁小宋城参观攻略2026-永安旅游 | D62: https://www.wingontravel.com/discovery/scenic-xiao-song-city-56808777 | E62: 永安旅游 | G62: 2026-10-22T00:24:57+08:00 | H62: 2026-10-22T00:24:57+08:00 | I62: evidence/02_次要来源/汴梁小宋城/汴梁小宋城_永安旅游_20261022.html | J62: public_view_only | K62: 仅内部核对与引用，不对外转载；页面由成员1采集。 | L62: b8a9b0bd1064f22741fd407cc8c4e567db998ea69df9a00dbbec75fd1199a2c0 | M62: candidate | N62: 成员1 | O62: 1 | P62: 地址金明区大梁路西段；电话0371-23268888/23388562；约5万㎡、餐饮2万㎡。
A63: src_000060 | B63: official | C63: 老饕的“五一”汴梁行：从早鲜到夜香，鼓楼美食全打卡 | D63: https://www.gulou.gov.cn/kfsglqwz/c00202/pc/content/content_1935255435885350912.html | E63: 开封市鼓楼区人民政府网站 | G63: 2026-10-22T00:36:00+08:00 | J63: public_view_only | K63: 用于内部候选菜品识别和简介参考；不批量转载或公开复制原文，最终推荐前需复核具体商家菜单。 | M63: candidate | O63: 1 | P63: 页面介绍鲤鱼焙面、桶子鸡、炒凉粉等开封美食。网页发布时间本轮未确认，未保存本地快照；只支持候选菜品及文化介绍，不证明具体门店当前供应。
A64: src_000061 | B64: official | C64: 第三十四期开封非遗市集预告 | D64: https://www.kaifeng.gov.cn/kfsrmzfwz/cggtyx/pc/content/content_1873547186096914432.html | E64: 开封市人民政府网站 | G64: 2026-10-22T00:36:00+08:00 | J64: public_view_only | K64: 仅用于识别开封传统食品/制作技艺候选；活动为历史预告，不作为当前商家营业或供应证明。 | M64: candidate | O64: 1 | P64: 页面列有汴梁张二炒凉粉、桶子鸡、朱仙镇五香豆腐干、五香风干兔肉、五香牛肉、豌豆糕、枣花馍、梨膏糖、洧川豆腐等传统美食项目。未保存本地快照。
A65: src_000062 | B65: official | C65: 福兴斋—老字号数字博物馆 | D65: https://lzhbwg.mofcom.gov.cn/edi_ecms_web_front/thb/detail/8a43fd72f22a4a789c1e5de85295f694 | E65: 商务部老字号数字博物馆 | G65: 2026-10-22T00:36:00+08:00 | J65: public_view_only | K65: 用于核对福兴斋品牌及桶子鸡产品信息；页面内容仅供内部核对与引用，未确认可批量存储或再发布。 | M65: candidate | O65: 1 | P65: 页面显示福兴斋品牌、开封市福兴斋清真食品厂、河南老字号及桶子鸡产品介绍。不能据此确认某一零售门店当前营业时间或具体地址。
A66: src_000063 | B66: official | C66: 宜生斋—老字号数字博物馆 | D66: https://lzhbwg.mofcom.gov.cn/edi_ecms_web_front/thb/detail/475d775db53642e89cc65e9772b5a015 | E66: 商务部老字号数字博物馆 | G66: 2026-10-22T00:36:00+08:00 | J66: public_view_only | K66: 用于核对宜生斋品牌、主营产品及页面公布的地址；营业时间需另行确认。 | M66: candidate | O66: 2 | P66: 页面介绍宜生斋主营桶子鸡、烧鸡，并列出总店地址为开封市顺河回族区南羊小区1号楼1层西头。未保存本地快照。 第三轮复核（2026-10-22）：重新查看商务部老字号数字博物馆页面，明确支持宜生斋总店地址“开封市顺河回族区南羊小区1号楼1层西头”；未提供经纬度或当前营业状态。
A67: src_000064 | B67: provider | C67: 第一楼·中华老字号（寺后街总店）—携程美食 | D67: https://gs.ctrip.com/html5/you/foods/kaifeng165/4926446.html | E67: 携程美食 | G67: 2026-10-22T00:36:00+08:00 | J67: public_view_only | K67: 用于内部候选核对；平台推荐菜、价格和营业时间可能变化，勿直接当作商家实时官方菜单。 | M67: candidate | O67: 1 | P67: 页面显示地址开封鼓楼区寺后街8号、营业时段10:30-14:00及17:30-21:00、人均约64元；推荐菜包含灌汤包、鲤鱼焙面、汴梁炸八块、三狠汤、杏仁茶、宫廷豌豆糕、桶子鸡等。未保存页面快照。
A68: src_000065 | B68: provider | C68: 黄家老店（宋城路店）—携程美食 | D68: https://gs.ctrip.com/html5/you/foods/kaifeng165/107473.html | E68: 携程美食 | G68: 2026-10-22T00:36:00+08:00 | J68: public_view_only | K68: 平台信息仅作候选线索；营业时间、价格和推荐菜需正式推荐前再次核实。 | M68: candidate | O68: 1 | P68: 页面显示地址宋城路凤凰城1号楼、营业时间10:00-21:30（页面显示）、人均约53元；推荐菜包括汴京炒凉粉、朱仙镇豆干丝、汴梁黄焖鱼、桶子鸡等。未保存页面快照。
A69: src_000066 | B69: provider | C69: 黄家老店（晋安路店）—携程美食 | D69: https://gs.ctrip.com/html5/you/foods/kaifeng165/11169507.html | E69: 携程美食 | G69: 2026-10-22T00:36:00+08:00 | J69: public_view_only | K69: 平台信息仅作候选线索；营业时间、价格和推荐菜需正式推荐前再次核实。 | M69: candidate | O69: 1 | P69: 页面显示地址晋安路中段宏泰怡园1号楼底商（武夷夜市南头）、营业时间10:30-21:00、人均约59元；推荐菜包括汴梁炒凉粉、黄河大鲤鱼、蟹黄汤包、汴京杏仁茶、桶子鸡、灌汤包子等。未保存页面快照。
A70: src_000067 | B70: provider | C70: 楼中楼酒店（汴梁小宋城店）—携程美食 | D70: https://gs.ctrip.com/html5/you/foods/fooddetail/2033356/7578897.html | E70: 携程美食 | G70: 2026-10-22T00:36:00+08:00 | J70: public_view_only | K70: 平台推荐菜不等于商家实时菜单；内部候选使用，最终供应关系需再次核实。 | M70: candidate | O70: 1 | P70: 页面显示地址大梁路汴梁小宋城小吃城一楼擂台东侧6号/7号附近，营业时间10:00-14:00及17:00-21:00，人均约61元；推荐菜包括鲤鱼焙面、羊肉炕馍、开封杏仁茶、黄焖鱼、红薯泥等。未保存页面快照。
A71: src_000068 | B71: provider | C71: 中兴楼（汴京路店）—携程美食 | D71: https://gs.ctrip.com/html5/you/foods/kaifeng165/4926492.html | E71: 携程美食 | G71: 2026-10-22T00:36:00+08:00 | J71: public_view_only | K71: 平台信息仅作候选线索；价格、营业时间和推荐菜需正式推荐前再次核实。 | M71: candidate | O71: 1 | P71: 页面显示地址汴京路43号（汴京公园旁西约30米）、营业时间10:30-14:00及17:00-21:00、人均约77元；推荐菜包括鲤鱼焙面、炸八件、三狠汤、塌锅牛肉等。未保存页面快照。
A72: src_000069 | B72: provider | C72: 梅利汴京烤鸭·开封豫菜地标店（东司门店）—携程美食 | D72: https://gs.ctrip.com/html5/you/foods/fooddetail/165/107493.html | E72: 携程美食 | G72: 2026-10-22T00:36:00+08:00 | J72: public_view_only | K72: 平台信息仅作候选线索；正式推荐前复核商家当前营业及菜单。 | M72: candidate | O72: 1 | P72: 页面显示地址解放路与曹门大街交叉口东约60米路南、营业时间10:00-21:00、人均约56元；推荐菜包括汴京果木烤鸭、开封灌汤小笼包、鲤鱼焙面、炸八块、特色炒凉粉、三狠汤、八宝杏仁茶等。未保存页面快照。
A73: src_000070 | B73: provider | C73: 稻香居锅贴（宋都御街店）—携程美食 | D73: https://gs.ctrip.com/html5/you/foods/kaifeng165/4926448.html | E73: 携程美食 | G73: 2026-10-22T00:36:00+08:00 | J73: public_view_only | K73: 平台信息仅作候选线索；正式推荐前复核营业时间及菜单。 | M73: candidate | O73: 1 | P73: 页面显示地址宋都御街73号、营业时间10:00-20:00、人均约44元；推荐菜包括锅贴、炒红薯泥、开封桶子鸡、糖醋鲤鱼焙面、开封黄焖鱼等。未保存页面快照。
A74: src_000071 | B74: provider | C74: 兴盛德花生老店（中山路店）—携程美食 | D74: https://gs.ctrip.com/html5/you/foods/Kaifeng165/7577515.html | E74: 携程美食 | G74: 2026-10-22T00:36:00+08:00 | J74: public_view_only | K74: 平台信息仅作候选线索；具体商品、库存及营业时间需再次核实。 | M74: candidate | O74: 1 | P74: 页面显示地址相国寺街道中山路北段84号、营业时间08:00-21:00、人均约29元；推荐菜/商品包括麻辣花生、蜂蜜花生、桶子鸡、兴盛德传统花生糕、花生糖等。未保存页面快照。
... A102: src_000099 | B102: provider | C102: 示范区梁山烤肉店企业信息—BOSS直聘 | D102: https://m.zhipin.com/companys/1266dbddc02135061XZ50t6-ElA~.html | E102: BOSS直聘企业信息页 | G102: 2026-10-22T01:37:41+08:00 | J102: public_view_only | K102: 仅作地址冲突的辅助线索；企业注册地址不一定等于顾客入口门牌。 | M102: candidate | O102: 2 | P102: 页面工商信息列示注册地址为“示范区万胜路1号”，与携程餐厅信息区的万胜路8号不同。注册地址不能直接替代门店导航地址；本轮未保存本地网页快照。 第三轮复核（2026-10-22）：页面显示2026-06-25更新，工商注册地址为示范区万胜路1号。该地址是注册地址，不必然等于游客导航入口，仍需商家直接确认。
A103: src_000100 | B103: provider | C103: 开封宋园灌汤小笼包相关公开视频/评论—抖音 | D103: https://www.douyin.com/video/7688817752341140047 | E103: 抖音公开页面 | F103: 2026-09-24 | G103: 2026-10-22T01:37:41+08:00 | J103: public_view_only | K103: 用户生成内容，仅作宽泛区域线索，不作为精确门牌或营业状态证据。 | M103: candidate | O103: 1 | P103: 公开评论提到黄河大街北段的宋园包子店，但未提供门牌号；精确地址以Trip.com餐厅详情页为主，本条不单独证明门店地址。本轮未保存本地网页快照。
A104: src_000101 | B104: official | C104: 祥符区市场监督管理局食品生产日常监督检查结果公示表 | D104: https://www.xiangfuqu.gov.cn/kfsxfqwz/c00889/pc/content/content_2001117008548458496.html | E104: 开封市祥符区人民政府网站 | G104: 2026-10-22T01:37:41+08:00 | J104: public_view_only | K104: 用于核对食品加工主体厂址，不代表该处是游客可直接到店消费的零售门店。 | M104: candidate | O104: 1 | P104: 政府公示表列出开封市福兴斋清真食品厂，地址为开封市祥符区朱仙镇北关。该记录是食品生产主体地址，不能直接作为游客到店用餐/购买的零售门店地址。本轮未保存本地网页快照。
A105: src_000102 | B105: provider | C105: 三胜街田庆辉田记米线—大众点评店铺相册页 | D105: https://www.dianping.com/shop/4022422/photos | E105: 大众点评（美团旗下） | G105: 2026-10-22T01:37:41+08:00 | J105: public_view_only | K105: 用于确认店铺名称和菜品线索；店铺详情页触发平台验证，未获得可核验的精确地址。 | M105: candidate | O105: 2 | P105: 相册页可见店铺名称和米线等菜品图片，但详情页跳转美团验证页面，当前可访问内容没有提供精确地址；不作为地址证据。本轮未保存本地网页快照。 二次核查（2026-10-22）：本来源仅作店名/菜品图片的辅助线索；精确地址和坐标现由高德地点页src_000103支持。
A106: src_000103 | B106: provider | C106: 三胜街田庆辉田记米线—高德地图地点页（二次核查） | D106: https://www.amap.com/place/B0FFG02SUH | E106: 高德地图 | G106: 2026-10-22T01:51:51+08:00 | J106: public_view_only | K106: 用于内部核对商家地址和地图坐标；当前营业状态仍需复核，不批量转载页面内容。 | M106: candidate | O106: 1 | P106: 高德地点页显示地址为开封市龙亭区三胜前街7号，电话13569506620，坐标34.800376,114.356027。页面可访问，但可见用户评价日期为2019-11-24，不能单独证明当前仍营业；本轮未保存本地网页快照。
A107: src_000104 | B107: provider | C107: 益品虾皇同名商户位置线索—开封吉屋网周边配套列表 | D107: https://kaifeng.jiwu.com/loupan/182299.html | E107: 开封吉屋网 | G107: 2026-10-22T01:51:51+08:00 | J107: public_view_only | K107: 只作为地址线索，不可单独用于精确导航或证明分店身份。 | M107: candidate | O107: 1 | P107: 页面周边配套列出“益品虾皇（黄河路北段安泰警苑小区斜对面）”，但没有明确证明它就是高德2025榜单中的“益品虾皇（鼎立总店）”；因此只记为线索，不填入正式地址字段。本轮未保存本地网页快照。
A108: src_000105 | B108: provider | C108: 西司广场夜市—高德地图地点页（李记五香豆沫坐标比对参考） | D108: https://ditu.amap.com/place/B017A0N0RK | E108: 高德地图 | G108: 2026-10-22T01:51:51+08:00 | J108: public_view_only | K108: 仅用于判断地图坐标附近地标，不作为李记五香豆沫自身地址证据。 | M108: candidate | O108: 1 | P108: 高德页面显示西司广场夜市地址为开封市鼓楼区丁角街83号，坐标34.794594,114.338268。与李记五香豆沫来源坐标34.794724,114.338246约相距14-15米，提示“丁角街2号”门牌与该坐标的对应关系需再次核验；本轮未保存本地网页快照。
A109: src_000106 | B109: provider | C109: 第一楼（寺后街店）—高德地图地点页（三轮核查） | D109: https://www.amap.com/place/B017A00HWY | E109: 高德地图 | G109: 2026-10-22T01:43:00+08:00 | J109: public_view_only | K109: 用于内部核对门店地址、坐标及POI编号；营业时段参考独立餐厅详情页。 | M109: candidate | O109: 1 | P109: 高德地点页显示地址为开封市鼓楼区寺后街8号，坐标34.794059,114.351924，电话0371-25998655/13083882366，POI B017A00HWY。携程餐厅详情另列10:30-14:00、17:30-21:00并有近期可访问的餐厅页面。高德可见用户评价较早，当前营业状态仍未由商家直接确认。本轮未保存本地网页快照。
A110: src_000107 | B110: provider | C110: 黄家老店（宋城路店）—高德地图地点页（三轮核查） | D110: https://www.amap.com/place/B017A00L40 | E110: 高德地图 | G110: 2026-10-22T01:43:00+08:00 | J110: public_view_only | K110: 用于内部核对该分店地址、坐标及POI编号；不证明当前营业状态。 | M110: candidate | O110: 1 | P110: 高德地点页显示地址为开封市龙亭区宋城路凤凰城1号楼（近西环城路），坐标34.785167,114.324778，电话0371-23991818，POI B017A00L40。页面可访问，但可见用户评价为2016年，当前营业状态仍需复核。本轮未保存本地网页快照。
A111: src_000108 | B111: provider | C111: 中兴楼（汴京路店）—高德地图地点页（三轮核查） | D111: https://www.amap.com/place/B017A000DA | E111: 高德地图 | G111: 2026-10-22T01:43:00+08:00 | J111: public_view_only | K111: 用于内部核对地址、坐标及POI编号；营业时间参考携程餐厅页。 | M111: candidate | O111: 1 | P111: 高德地点页显示地址为开封市顺河回族区汴京路43号，坐标34.793215,114.370321，电话0371-22661000/0371-22662000/16627615229，POI B017A000DA。携程页面显示营业时段10:30-14:00、17:00-21:00。高德可见评价较早，当前营业状态仍需商家确认。本轮未保存本地网页快照。
A112: src_000109 | B112: provider | C112: 稻香居（宋都御街店）—高德地图地点页（三轮核查） | D112: https://ditu.amap.com/place/B017A00K1Y | E112: 高德地图 | G112: 2026-10-22T01:43:00+08:00 | J112: public_view_only | K112: 用于内部核对地址、坐标及POI编号；营业时段参考携程餐厅页。 | M112: candidate | O112: 1 | P112: 高德地点页显示地址为开封市龙亭区宋都御街73号，坐标34.800888,114.352005，电话0371-22884603，POI B017A00K1Y。携程页面列出营业时段10:00-20:00；高德可见用户评价较早，当前营业状态仍需复核。本轮未保存本地网页快照。
A113: src_000110 | B113: provider | C113: 李小记羊肉胡辣汤（清真店）—高德地图地点页（三轮核查） | D113: https://www.amap.com/place/B017A0NJMD | E113: 高德地图 | G113: 2026-10-22T01:43:00+08:00 | J113: public_view_only | K113: 用于内部核对地图位置、坐标、电话；地址详细表述与携程页面存在粒度差异，需复核。 | M113: candidate | O113: 1 | P113: 高德地点页显示地址为开封市顺河回族区劳动路苹东社区，坐标34.807061,114.380358，电话13938618226，POI B017A0NJMD。携程同名页面给出“苹果园东路与苹果园中路交叉口往南约20米路东”，电话同为13938618226。电话一致支持同一门店的可能性，但两种地址描述不完全一致，精确入口需人工复核。本轮未保存本地网页快照。
A114: src_000111 | B114: provider | C114: 西门郑羊双肠（大梁路店）—携程餐厅详情（三轮核查） | D114: https://you.ctrip.com/yougourmet/restdetail/kaifeng165/33211195.html | E114: 携程 | G114: 2026-10-22T01:43:00+08:00 | J114: public_view_only | K114: 用于内部核对门店地址、电话、营业时段和近期评价；导航坐标仍需地图端复核。 | M114: candidate | O114: 1 | P114: 页面显示门店名“西门郑羊双肠（大梁路店）”，地址为大梁路1号（梁园市场西门附近），电话13353811330，营业时段06:30-14:00；页面可见2025-09至2025-11用户评价。页面所用行政区称“金明区”，工作簿保留当前龙亭区描述；未找到可确认该分店的高德精确坐标。本轮未保存本地网页快照。
A115: src_000112 | B115: provider | C115: 黄家老店（晋安路店）—Trip.com餐厅详情（三轮核查） | D115: https://hk.trip.com/restaurant/china/kaifeng/detail/huangjia-old-restaurant-20554653/ | E115: Trip.com | G115: 2026-10-22T01:43:00+08:00 | J115: public_view_only | K115: 用于内部核对该分店地址、营业时段和电话；不将搜索摘要推算为坐标。 | M115: candidate | O115: 1 | P115: 页面显示地址为晋安路中段宏泰怡园1号楼底商（武夷夜市南头），营业时段10:30-21:00，电话0371-23858988。公开页面支持地址和营业时段，但本轮没有取得可靠的经纬度或可确认的高德POI编号。本轮未保存本地网页快照。
... A119: src_000116 | B119: provider | C119: 梁山烤肉（东京总店）—Trip.com餐厅详情（当前地址字段及近期评价） | D119: https://tw.trip.com/restaurant/china/kaifeng/detail/liangshankaorou-42269656/ | E119: Trip.com | G119: 2026-10-22T01:43:00+08:00 | J119: public_view_only | K119: 用于核对餐厅详情页当前展示地址、电话、营业时段和近期评价；仍需解决1号/8号冲突。 | M119: conflict | O119: 1 | P119: 餐厅详情区显示万胜路8号（大梁路与黄河大街交叉口西北角，西郊乡政府西隔壁），电话18568673633，营业时段10:00-24:00；页面有2026-04-25近期评价。但另一篇用户游记文字写万胜路1号，BOSS工商注册地址也为万胜路1号。详情区8号较适合当作当前平台导航线索，但门牌冲突未被商家直接确认，不标记为已核实。本轮未保存本地网页快照。
A120: src_000117 | B120: official | C120: 清明上河园官网-百度百科专题页（含官方导览图） | D120: http://www.qingmings.com/2019baidubaoke.php | E120: 清明上河园（中国开封清明上河园股份有限公司） | G120: 2026-10-22T21:32:06+08:00 | H120: 2026-10-22T21:32:06+08:00 | I120: evidence/01_原始来源/清明上河园/清明上河园_官网导览图页_20261022.html | J120: public_view_only | K120: 仅内部核对与引用，不对外转载；版权归清明上河园。 | L120: d2bbc86662edd3e4b93694e5ff8b9c8b5d15dea35705c1d63f6b7ba539d8474b | M120: candidate | N120: 成员1 | O120: 1 | P120: 官网专题页；页面内“清园寻胜图”为景区导览图，标注园区建筑、水系、道路与出入口；页面原图700×444。
A121: src_000118 | B121: official | C121: 万岁山官网-影像中心（视频中心） | D121: http://www.wansuishan.com.cn/website/pc/index.html#/imgCenter | E121: 开封万岁山武侠城 | G121: 2026-10-22T21:43:43+08:00 | H121: 2026-10-22T21:43:43+08:00 | I121: evidence/01_原始来源/万岁山/万岁山_官网视频中心_20261022.png | J121: public_view_only | K121: 仅内部核对与引用，不对外转载；版权归万岁山武侠城。 | L121: bb07ab94ce932a1a973915113f74e4a4e641b272302afac90abdf52c3a24dd35 | M121: candidate | N121: 成员1 | O121: 1 | P121: 官网影像中心→视频中心；页面列出2个官方宣传视频；接口原始返回见同目录 JSON；视频文件较大，未下载，仅存链接。
A122: src_000119 | B122: official | C122: 万岁山官网-侠客服务（智慧地图/景区导览图） | D122: http://www.wansuishan.com.cn/website/pc/index.html#/service | E122: 开封万岁山武侠城 | G122: 2026-10-22T21:43:43+08:00 | H122: 2026-10-22T21:43:43+08:00 | I122: evidence/01_原始来源/万岁山/万岁山_官网景区地图_20261022.png | J122: public_view_only | K122: 仅内部核对与引用，不对外转载；版权归万岁山武侠城。 | L122: c12ae286ce33fa7df3d56fa0f06d5a46f83c7ee68fc87ebcd69385a3c4e2c7f6 | M122: candidate | N122: 成员1 | O122: 1 | P122: 官网侠客服务→智慧地图；导览图标注出入口、演出场地和游览设施；原图2000×737；接口原始返回见同目录 JSON。
A123: src_000120 | B123: official | C123: 开封府官网-府衙简介 | D123: http://www.kaifengfu.cn/about | E123: 开封府（开封“开封府”旅游开发有限公司） | G123: 2026-10-22T21:58:17+08:00 | H123: 2026-10-22T21:58:17+08:00 | I123: evidence/01_原始来源/开封府/开封府_官网府衙简介_20261022.html | J123: public_view_only | K123: 仅内部核对与引用，不对外转载；版权归开封府。 | L123: 985ef6560228074b9f30099b67ad2961bc7ba79fa9f609f4d9ad3d5921f30434 | M123: candidate | N123: 成员1 | O123: 1 | P123: 官网府衙简介；含沿中轴线、东线、西线的建筑分布和九个功能区；看点介绍与建筑位置的主要依据。
A124: src_000121 | B124: official | C124: 开封府官网-在线导览（景区导览图） | D124: http://www.kaifengfu.cn/daolan | E124: 开封府（开封“开封府”旅游开发有限公司） | G124: 2026-10-22T21:58:17+08:00 | H124: 2026-10-22T21:58:17+08:00 | I124: evidence/01_原始来源/开封府/开封府_官网在线导览_20261022.html | J124: public_view_only | K124: 仅内部核对与引用，不对外转载；版权归开封府。 | L124: e471213ac3b3138acd3ba61c6d22f1573379cd7802b439e3e236785a5ca5a9ac | M124: candidate | N124: 成员1 | O124: 1 | P124: 官网在线导览页；页面内为景区导览图，标注府门、仪门、大堂、梅花堂、清心楼、明礼院、天庆观、潜龙宫等建筑与出入口；原图1646×1280。
A125: src_000122 | B125: official | C125: 金秋十月，共襄盛举！开封府与游客同庆祖国华诞 | D125: http://www.kaifengfu.cn/news/view.asp?id=485 | E125: 开封府（开封“开封府”旅游开发有限公司） | F125: 2026-10-01T00:00:00+08:00 | G125: 2026-10-22T21:58:17+08:00 | H125: 2026-10-22T21:58:17+08:00 | I125: evidence/01_原始来源/开封府/开封府_官网国庆新闻_20261001.html | J125: public_view_only | K125: 仅内部核对与引用，不对外转载；版权归开封府。 | L125: b9f4c39a8772e705e6f739d3c227a0d11f7fcc496db21cba67f7786262e51952 | M125: candidate | N125: 成员1 | O125: 1 | P125: 官网新闻；发布时间仅到日期，时间未知，published_at 按当天0点记录；含府门全景、夜景光影、盘鼓迎宾等现场照片。
A126: src_000123 | B126: official | C126: 开封府官网-全景游园（建筑全景） | D126: http://www.kaifengfu.cn/kaifengfu | E126: 开封府（开封“开封府”旅游开发有限公司） | G126: 2026-10-22T21:58:17+08:00 | H126: 2026-10-22T21:58:17+08:00 | I126: evidence/01_原始来源/开封府/开封府_官网全景游园_20261022.xml | J126: public_view_only | K126: 仅内部核对与引用，不对外转载；版权归开封府。 | L126: b7ac4808a93497ec41441810164d959d07d8fa4354fcbee8a2689b6b5c3f040b | M126: candidate | N126: 成员1 | O126: 1 | P126: 官网全景游园 krpano 配置；含19个场景标题和立方图路径；本次取正厅（内）、梅花堂、清心楼、明礼院、三清殿五个场景的 pano_f 面。
A127: src_000124 | B127: official | C127: 清明上河园官方小程序导览图（用户截图） | E127: 清明上河园（中国开封清明上河园股份有限公司） | G127: 2026-10-22T22:04:57+08:00 | H127: 2026-10-22T22:04:57+08:00 | I127: evidence/01_原始来源/清明上河园/清明上河园_官方小程序导览图_20261022_1.png | J127: public_view_only | K127: 仅内部核对与引用，不对外转载；版权归原景区。 | L127: 22e9a7257f17afa73829a0fce38733ee5c95cbaa1a11f60225cfcced5676c1e4 | M127: candidate | N127: 成员1 | O127: 1 | P127: 用户提供的官方小程序导览截图；小程序无网页URL；两张截图分别覆盖园区北部和南部，含演出点位标记；截图时间2026-10-22。
A128: src_000125 | B128: official | C128: 清明上河园官方抖音宣传视频（用户提供） | D128: https://v.douyin.com/GSyFQAMOHwc/ | E128: 清明上河园（中国开封清明上河园股份有限公司） | G128: 2026-10-22T22:04:57+08:00 | H128: 2026-10-22T22:04:57+08:00 | I128: evidence/01_原始来源/清明上河园/清明上河园_官方抖音链接_20261022.txt | J128: public_view_only | K128: 仅内部核对与引用，不对外转载；版权归原景区。 | L128: 9882d62a47a64a305b949c5b4ed28eccd52846c21bd66d987c3d16f387d046a9 | M128: candidate | N128: 成员1 | O128: 1 | P128: 抖音短链解析到视频ID 7283343905708330259，账号“清明上河园”；页面触发验证码，未抓取视频文件、标题、时长；链接由用户提供。
A129: src_000126 | B129: official | C129: 万岁山武侠城官方抖音宣传视频（用户提供） | D129: https://v.douyin.com/PbkzPZFzk5Y/ | E129: 开封万岁山武侠城 | G129: 2026-10-22T22:04:57+08:00 | H129: 2026-10-22T22:04:57+08:00 | I129: evidence/01_原始来源/万岁山/万岁山_官方抖音链接_20261022.txt | J129: public_view_only | K129: 仅内部核对与引用，不对外转载；版权归万岁山武侠城。 | L129: 8adbc6bef824007412a7605ba165d81a620b54806b49fb0810e057fb2d9d6857 | M129: candidate | N129: 成员1 | O129: 1 | P129: 抖音短链解析到视频ID 7557286795680009499，账号“万岁山武侠城”；页面触发验证码，未抓取视频文件、标题、时长；链接由用户提供。
A130: src_000127 | B130: official | C130: 龙亭官网-龙亭大殿 | D130: http://www.kfltjq.com/sys-nd/7.html | E130: 开封市龙亭景区 | F130: 2022-08-04T17:08:00+08:00 | G130: 2026-10-22T22:05:38+08:00 | H130: 2026-10-22T22:05:38+08:00 | I130: evidence/01_原始来源/龙亭/龙亭_官网_龙亭大殿_20261022.html | J130: public_view_only | K130: 仅内部核对与引用，不对外转载；版权归开封市龙亭景区。 | L130: 5c679a0b05123fea105222850dc3bc96dfbe2350d2530670ea851b129bf77158 | M130: candidate | N130: 成员1 | O130: 1 | P130: 官网公园景点-龙亭大殿；含建筑尺寸、蟠龙御道、72级台阶、九五之尊格局。
...

Sheet 19_change_log
A1: 变更日志 change_log
A2: 仅收集候选与核实数据；不得把格式正确误判为事实真实。导入前请运行校验脚本。
A3: change_id | B3: table_name | C3: record_id | D3: field_name | E3: old_value | F3: new_value | G3: change_type | H3: change_reason | I3: source_id | J3: changed_at | K3: changed_by | L3: previous_version | M3: new_version | N3: approval_status | O3: notes
A4: chg_000001 | B4: 18_source_records | C4: src_000073 | D4: notes | E4: 本轮列表页可见张记逍遥胡辣汤（大坑沿街店）、化三驴肉汤馆（总店）、西门郑羊双肠（大梁路店）、宋园灌汤小笼包（黄河路店）、宋风雅宴（双龙巷店）、兴盛德花生老店、李记四味菜馆等候选；不同条目的地址/营业时段并不完整。未保存页面快照。 | F4: 本轮列表页可见楼中楼酒店（汴梁小宋城店）、黄家老店（西司店）、化三驴肉汤馆（总店）、张记逍遥胡辣汤（大坑沿街店）、西门郑羊双肠（大梁路店）、宋园灌汤小笼包（黄河路店）、兴盛德花生老店（中山路店）、李记五香豆沫等候选。页面只显示部分门店的开门时间和人均参考价，部分地址仅到区/地标层级；宋风雅宴和李记四味菜馆改由独立来源记录支持。未保存本地快照。 | G4: data_correction | H4: 修正来源备注，避免将未在该页面直接展示的商家误写为该页证据支持。 | I4: src_000073 | J4: 2026-10-22T01:16:33+08:00 | K4: 成员4（AI初步核查） | L4: 1 | M4: 2 | N4: pending_review | O4: 初步核查修正；未完成现场/商家直接确认。
A5: chg_000002 | B5: 18_source_records | C5: src_000081 | D5: validation_status | E5: candidate | F5: stale | G5: data_correction | H5: 页面标题明确为2025年榜单；只能用于发现候选，不宜作为当前营业/菜单证据。 | I5: src_000081 | J5: 2026-10-22T01:16:33+08:00 | K5: 成员4（AI初步核查） | L5: 1 | M5: 2 | N5: pending_review | O5: 初步核查修正；未完成现场/商家直接确认。
A6: chg_000003 | B6: 18_source_records | C6: src_000081 | D6: notes | E6: 页面可见马豫兴桶子鸡（万宝店）、三胜街田庆辉田记米线、邢家锅贴老店（大梁门总店）、庞记桶子鸡（旗舰店）、益品虾皇（鼎立总店）等。部分条目没有详细地址/营业时间。未保存页面快照。 | F6: 页面可见马豫兴桶子鸡（万宝店）、三胜街田庆辉田记米线、邢家锅贴老店（大梁门总店）、庞记桶子鸡（旗舰店）、益品虾皇（鼎立总店）等。部分条目没有详细地址/营业时间。未保存页面快照。 初步核查补充：该页面为2025年历史榜单，已标记stale；仅作候选发现，不证明当前营业或供应。 | G6: data_correction | H6: 明确历史榜单的时效限制。 | I6: src_000081 | J6: 2026-10-22T01:16:33+08:00 | K6: 成员4（AI初步核查） | L6: 1 | M6: 2 | N6: pending_review | O6: 初步核查修正；未完成现场/商家直接确认。
A7: chg_000004 | B7: 16_food_vendors | C7: ven_000001 | D7: business_hours | E7: 10:30-14:00；17:30-21:00（携程页面显示，需复核） | F7: 10:30-14:00；17:30-21:00 | G7: data_correction | H7: 将来源说明移至备注，营业时间字段仅保留时间值。 | I7: src_000064 | J7: 2026-10-22T01:16:33+08:00 | K7: 成员4（AI初步核查） | L7: 1 | M7: 2 | N7: pending_review | O7: 初步核查修正；未完成现场/商家直接确认。
A8: chg_000005 | B8: 16_food_vendors | C8: ven_000001 | D8: notes | E8: 地址、营业时间和人均消费来自携程页面；非商家实时官方确认，推荐前复核。 | F8: 地址、营业时间和人均消费来自携程页面；非商家实时官方确认，推荐前复核。 营业时间为平台页面展示值，正式推荐前需复核。 | G8: data_correction | H8: src_000064 | J8: 2026-10-22T01:16:33+08:00 | K8: 成员4（AI初步核查） | L8: 1 | M8: 2 | N8: pending_review | O8: 初步核查修正；未完成现场/商家直接确认。
A9: chg_000006 | B9: 16_food_vendors | C9: ven_000002 | D9: business_hours | E9: 10:00-21:30（携程页面显示，需复核） | F9: 10:00-21:30 | G9: data_correction | H9: 将来源说明移至备注，营业时间字段仅保留时间值。 | I9: src_000065 | J9: 2026-10-22T01:16:33+08:00 | K9: 成员4（AI初步核查） | L9: 1 | M9: 2 | N9: pending_review | O9: 初步核查修正；未完成现场/商家直接确认。
A10: chg_000007 | B10: 16_food_vendors | C10: ven_000002 | D10: notes | E10: 营业时间、价格和推荐菜来自携程页面；当前状态需再次确认。 | F10: 营业时间、价格和推荐菜来自携程页面；当前状态需再次确认。 营业时间为平台页面展示值，正式推荐前需复核。 | G10: data_correction | H10: src_000065 | J10: 2026-10-22T01:16:33+08:00 | K10: 成员4（AI初步核查） | L10: 1 | M10: 2 | N10: pending_review | O10: 初步核查修正；未完成现场/商家直接确认。
A11: chg_000008 | B11: 16_food_vendors | C11: ven_000003 | D11: business_hours | E11: 10:30-21:00（携程页面显示，需复核） | F11: 10:30-21:00 | G11: data_correction | H11: 将来源说明移至备注，营业时间字段仅保留时间值。 | I11: src_000066 | J11: 2026-10-22T01:16:33+08:00 | K11: 成员4（AI初步核查） | L11: 1 | M11: 2 | N11: pending_review | O11: 初步核查修正；未完成现场/商家直接确认。
A12: chg_000009 | B12: 16_food_vendors | C12: ven_000003 | D12: notes | E12: 营业时间、价格和推荐菜来自携程页面；当前状态需再次确认。 | F12: 营业时间、价格和推荐菜来自携程页面；当前状态需再次确认。 营业时间为平台页面展示值，正式推荐前需复核。 | G12: data_correction | H12: src_000066 | J12: 2026-10-22T01:16:33+08:00 | K12: 成员4（AI初步核查） | L12: 1 | M12: 2 | N12: pending_review | O12: 初步核查修正；未完成现场/商家直接确认。
A13: chg_000010 | B13: 16_food_vendors | C13: ven_000004 | D13: business_hours | E13: 10:00-14:00；17:00-21:00（携程页面显示，需复核） | F13: 10:00-14:00；17:00-21:00 | G13: data_correction | H13: 将来源说明移至备注，营业时间字段仅保留时间值。 | I13: src_000067 | J13: 2026-10-22T01:16:33+08:00 | K13: 成员4（AI初步核查） | L13: 1 | M13: 2 | N13: pending_review | O13: 初步核查修正；未完成现场/商家直接确认。
A14: chg_000011 | B14: 16_food_vendors | C14: ven_000004 | D14: notes | E14: 地址描述来自携程页面，门牌及当前营业信息仍需复核。 | F14: 地址描述来自携程页面，门牌及当前营业信息仍需复核。 营业时间为平台页面展示值，正式推荐前需复核。 | G14: data_correction | H14: src_000067 | J14: 2026-10-22T01:16:33+08:00 | K14: 成员4（AI初步核查） | L14: 1 | M14: 2 | N14: pending_review | O14: 初步核查修正；未完成现场/商家直接确认。
A15: chg_000012 | B15: 16_food_vendors | C15: ven_000005 | D15: business_hours | E15: 10:30-14:00；17:00-21:00（携程页面显示，需复核） | F15: 10:30-14:00；17:00-21:00 | G15: data_correction | H15: 将来源说明移至备注，营业时间字段仅保留时间值。 | I15: src_000068 | J15: 2026-10-22T01:16:33+08:00 | K15: 成员4（AI初步核查） | L15: 1 | M15: 2 | N15: pending_review | O15: 初步核查修正；未完成现场/商家直接确认。
A16: chg_000013 | B16: 16_food_vendors | C16: ven_000005 | D16: notes | E16: 地址、营业时间和人均消费来自携程页面；非商家实时官方确认。 | F16: 地址、营业时间和人均消费来自携程页面；非商家实时官方确认。 营业时间为平台页面展示值，正式推荐前需复核。 | G16: data_correction | H16: src_000068 | J16: 2026-10-22T01:16:33+08:00 | K16: 成员4（AI初步核查） | L16: 1 | M16: 2 | N16: pending_review | O16: 初步核查修正；未完成现场/商家直接确认。
A17: chg_000014 | B17: 16_food_vendors | C17: ven_000006 | D17: business_hours | E17: 10:00-21:00（携程页面显示，需复核） | F17: 10:00-21:00 | G17: data_correction | H17: 将来源说明移至备注，营业时间字段仅保留时间值。 | I17: src_000069 | J17: 2026-10-22T01:16:33+08:00 | K17: 成员4（AI初步核查） | L17: 1 | M17: 2 | N17: pending_review | O17: 初步核查修正；未完成现场/商家直接确认。
A18: chg_000015 | B18: 16_food_vendors | C18: ven_000006 | D18: notes | E18: 地址、营业时间和人均消费来自携程页面；当前营业与菜单需复核。 | F18: 地址、营业时间和人均消费来自携程页面；当前营业与菜单需复核。 营业时间为平台页面展示值，正式推荐前需复核。 | G18: data_correction | H18: src_000069 | J18: 2026-10-22T01:16:33+08:00 | K18: 成员4（AI初步核查） | L18: 1 | M18: 2 | N18: pending_review | O18: 初步核查修正；未完成现场/商家直接确认。
A19: chg_000016 | B19: 16_food_vendors | C19: ven_000007 | D19: business_hours | E19: 10:00-20:00（携程页面显示，需复核） | F19: 10:00-20:00 | G19: data_correction | H19: 将来源说明移至备注，营业时间字段仅保留时间值。 | I19: src_000070 | J19: 2026-10-22T01:16:33+08:00 | K19: 成员4（AI初步核查） | L19: 1 | M19: 2 | N19: pending_review | O19: 初步核查修正；未完成现场/商家直接确认。
A20: chg_000017 | B20: 16_food_vendors | C20: ven_000007 | D20: notes | E20: 地址、营业时间和人均消费来自携程页面；当前营业与菜单需复核。 | F20: 地址、营业时间和人均消费来自携程页面；当前营业与菜单需复核。 营业时间为平台页面展示值，正式推荐前需复核。 | G20: data_correction | H20: src_000070 | J20: 2026-10-22T01:16:33+08:00 | K20: 成员4（AI初步核查） | L20: 1 | M20: 2 | N20: pending_review | O20: 初步核查修正；未完成现场/商家直接确认。
A21: chg_000018 | B21: 16_food_vendors | C21: ven_000008 | D21: business_hours | E21: 08:00-21:00（携程页面显示，需复核） | F21: 08:00-21:00 | G21: data_correction | H21: 将来源说明移至备注，营业时间字段仅保留时间值。 | I21: src_000071 | J21: 2026-10-22T01:16:33+08:00 | K21: 成员4（AI初步核查） | L21: 1 | M21: 2 | N21: pending_review | O21: 初步核查修正；未完成现场/商家直接确认。
A22: chg_000019 | B22: 16_food_vendors | C22: ven_000008 | D22: notes | E22: 该页主要用于店铺/商品候选；商品零售形式、库存及当前营业需复核。 | F22: 该页主要用于店铺/商品候选；商品零售形式、库存及当前营业需复核。 营业时间为平台页面展示值，正式推荐前需复核。 | G22: data_correction | H22: src_000071 | J22: 2026-10-22T01:16:33+08:00 | K22: 成员4（AI初步核查） | L22: 1 | M22: 2 | N22: pending_review | O22: 初步核查修正；未完成现场/商家直接确认。
A23: chg_000020 | B23: 16_food_vendors | C23: ven_000009 | D23: business_hours | E23: 06:00-10:00（携程页面显示，需复核） | F23: 06:00-10:00 | G23: data_correction | H23: 将来源说明移至备注，营业时间字段仅保留时间值。 | I23: src_000072 | J23: 2026-10-22T01:16:33+08:00 | K23: 成员4（AI初步核查） | L23: 1 | M23: 2 | N23: pending_review | O23: 初步核查修正；未完成现场/商家直接确认。
A24: chg_000021 | B24: 16_food_vendors | C24: ven_000009 | D24: notes | E24: 营业时间为早餐时段，来自携程页面；清真标识与菜品配方需以商家当前信息为准。 | F24: 营业时间为早餐时段，来自携程页面；清真标识与菜品配方需以商家当前信息为准。 营业时间为平台页面展示值，正式推荐前需复核。 | G24: data_correction | H24: src_000072 | J24: 2026-10-22T01:16:33+08:00 | K24: 成员4（AI初步核查） | L24: 1 | M24: 2 | N24: pending_review | O24: 初步核查修正；未完成现场/商家直接确认。
A25: chg_000022 | B25: 16_food_vendors | C25: ven_000001 | D25: price_band | E25: 60-70元/人（平台显示人均约64元） | F25: 60-70元/人 | G25: data_correction | H25: 价格区间字段只保留人民币区间，平台人均值移至备注。 | I25: src_000064 | J25: 2026-10-22T01:16:33+08:00 | K25: 成员4（AI初步核查） | L25: 1 | M25: 2 | N25: pending_review | O25: 初步核查修正；未完成现场/商家直接确认。
A26: chg_000023 | B26: 16_food_vendors | C26: ven_000001 | D26: notes | E26: 地址、营业时间和人均消费来自携程页面；非商家实时官方确认，推荐前复核。 营业时间为平台页面展示值，正式推荐前需复核。 | F26: 地址、营业时间和人均消费来自携程页面；非商家实时官方确认，推荐前复核。 营业时间为平台页面展示值，正式推荐前需复核。 平台页面显示人均约64元，仅为参考消费，不是单道菜价格。 | G26: data_correction | H26: src_000064 | J26: 2026-10-22T01:16:33+08:00 | K26: 成员4（AI初步核查） | L26: 1 | M26: 2 | N26: pending_review | O26: 初步核查修正；未完成现场/商家直接确认。
A27: chg_000024 | B27: 16_food_vendors | C27: ven_000002 | D27: price_band | E27: 50-60元/人（平台显示人均约53元） | F27: 50-60元/人 | G27: data_correction | H27: 价格区间字段只保留人民币区间，平台人均值移至备注。 | I27: src_000065 | J27: 2026-10-22T01:16:33+08:00 | K27: 成员4（AI初步核查） | L27: 1 | M27: 2 | N27: pending_review | O27: 初步核查修正；未完成现场/商家直接确认。
A28: chg_000025 | B28: 16_food_vendors | C28: ven_000002 | D28: notes | E28: 营业时间、价格和推荐菜来自携程页面；当前状态需再次确认。 营业时间为平台页面展示值，正式推荐前需复核。 | F28: 营业时间、价格和推荐菜来自携程页面；当前状态需再次确认。 营业时间为平台页面展示值，正式推荐前需复核。 平台页面显示人均约53元，仅为参考消费，不是单道菜价格。 | G28: data_correction | H28: src_000065 | J28: 2026-10-22T01:16:33+08:00 | K28: 成员4（AI初步核查） | L28: 1 | M28: 2 | N28: pending_review | O28: 初步核查修正；未完成现场/商家直接确认。
A29: chg_000026 | B29: 16_food_vendors | C29: ven_000003 | D29: price_band | E29: 50-60元/人（平台显示人均约59元） | F29: 50-60元/人 | G29: data_correction | H29: 价格区间字段只保留人民币区间，平台人均值移至备注。 | I29: src_000066 | J29: 2026-10-22T01:16:33+08:00 | K29: 成员4（AI初步核查） | L29: 1 | M29: 2 | N29: pending_review | O29: 初步核查修正；未完成现场/商家直接确认。
A30: chg_000027 | B30: 16_food_vendors | C30: ven_000003 | D30: notes | E30: 营业时间、价格和推荐菜来自携程页面；当前状态需再次确认。 营业时间为平台页面展示值，正式推荐前需复核。 | F30: 营业时间、价格和推荐菜来自携程页面；当前状态需再次确认。 营业时间为平台页面展示值，正式推荐前需复核。 平台页面显示人均约59元，仅为参考消费，不是单道菜价格。 | G30: data_correction | H30: src_000066 | J30: 2026-10-22T01:16:33+08:00 | K30: 成员4（AI初步核查） | L30: 1 | M30: 2 | N30: pending_review | O30: 初步核查修正；未完成现场/商家直接确认。
A31: chg_000028 | B31: 16_food_vendors | C31: ven_000004 | D31: price_band | E31: 60-70元/人（平台显示人均约61元） | F31: 60-70元/人 | G31: data_correction | H31: 价格区间字段只保留人民币区间，平台人均值移至备注。 | I31: src_000067 | J31: 2026-10-22T01:16:33+08:00 | K31: 成员4（AI初步核查） | L31: 1 | M31: 2 | N31: pending_review | O31: 初步核查修正；未完成现场/商家直接确认。
A32: chg_000029 | B32: 16_food_vendors | C32: ven_000004 | D32: notes | E32: 地址描述来自携程页面，门牌及当前营业信息仍需复核。 营业时间为平台页面展示值，正式推荐前需复核。 | F32: 地址描述来自携程页面，门牌及当前营业信息仍需复核。 营业时间为平台页面展示值，正式推荐前需复核。 平台页面显示人均约61元，仅为参考消费，不是单道菜价格。 | G32: data_correction | H32: src_000067 | J32: 2026-10-22T01:16:33+08:00 | K32: 成员4（AI初步核查） | L32: 1 | M32: 2 | N32: pending_review | O32: 初步核查修正；未完成现场/商家直接确认。
A33: chg_000030 | B33: 16_food_vendors | C33: ven_000005 | D33: price_band | E33: 70-80元/人（平台显示人均约77元） | F33: 70-80元/人 | G33: data_correction | H33: 价格区间字段只保留人民币区间，平台人均值移至备注。 | I33: src_000068 | J33: 2026-10-22T01:16:33+08:00 | K33: 成员4（AI初步核查） | L33: 1 | M33: 2 | N33: pending_review | O33: 初步核查修正；未完成现场/商家直接确认。
A34: chg_000031 | B34: 16_food_vendors | C34: ven_000005 | D34: notes | E34: 地址、营业时间和人均消费来自携程页面；非商家实时官方确认。 营业时间为平台页面展示值，正式推荐前需复核。 | F34: 地址、营业时间和人均消费来自携程页面；非商家实时官方确认。 营业时间为平台页面展示值，正式推荐前需复核。 平台页面显示人均约77元，仅为参考消费，不是单道菜价格。 | G34: data_correction | H34: src_000068 | J34: 2026-10-22T01:16:33+08:00 | K34: 成员4（AI初步核查） | L34: 1 | M34: 2 | N34: pending_review | O34: 初步核查修正；未完成现场/商家直接确认。
A35: chg_000032 | B35: 16_food_vendors | C35: ven_000006 | D35: price_band | E35: 50-60元/人（平台显示人均约56元） | F35: 50-60元/人 | G35: data_correction | H35: 价格区间字段只保留人民币区间，平台人均值移至备注。 | I35: src_000069 | J35: 2026-10-22T01:16:33+08:00 | K35: 成员4（AI初步核查） | L35: 1 | M35: 2 | N35: pending_review | O35: 初步核查修正；未完成现场/商家直接确认。
A36: chg_000033 | B36: 16_food_vendors | C36: ven_000006 | D36: notes | E36: 地址、营业时间和人均消费来自携程页面；当前营业与菜单需复核。 营业时间为平台页面展示值，正式推荐前需复核。 | F36: 地址、营业时间和人均消费来自携程页面；当前营业与菜单需复核。 营业时间为平台页面展示值，正式推荐前需复核。 平台页面显示人均约56元，仅为参考消费，不是单道菜价格。 | G36: data_correction | H36: src_000069 | J36: 2026-10-22T01:16:33+08:00 | K36: 成员4（AI初步核查） | L36: 1 | M36: 2 | N36: pending_review | O36: 初步核查修正；未完成现场/商家直接确认。
A37: chg_000034 | B37: 16_food_vendors | C37: ven_000007 | D37: price_band | E37: 40-50元/人（平台显示人均约44元） | F37: 40-50元/人 | G37: data_correction | H37: 价格区间字段只保留人民币区间，平台人均值移至备注。 | I37: src_000070 | J37: 2026-10-22T01:16:33+08:00 | K37: 成员4（AI初步核查） | L37: 1 | M37: 2 | N37: pending_review | O37: 初步核查修正；未完成现场/商家直接确认。
A38: chg_000035 | B38: 16_food_vendors | C38: ven_000007 | D38: notes | E38: 地址、营业时间和人均消费来自携程页面；当前营业与菜单需复核。 营业时间为平台页面展示值，正式推荐前需复核。 | F38: 地址、营业时间和人均消费来自携程页面；当前营业与菜单需复核。 营业时间为平台页面展示值，正式推荐前需复核。 平台页面显示人均约44元，仅为参考消费，不是单道菜价格。 | G38: data_correction | H38: src_000070 | J38: 2026-10-22T01:16:33+08:00 | K38: 成员4（AI初步核查） | L38: 1 | M38: 2 | N38: pending_review | O38: 初步核查修正；未完成现场/商家直接确认。
A39: chg_000036 | B39: 16_food_vendors | C39: ven_000008 | D39: price_band | E39: 20-30元/人（平台显示人均约29元） | F39: 20-30元/人 | G39: data_correction | H39: 价格区间字段只保留人民币区间，平台人均值移至备注。 | I39: src_000071 | J39: 2026-10-22T01:16:33+08:00 | K39: 成员4（AI初步核查） | L39: 1 | M39: 2 | N39: pending_review | O39: 初步核查修正；未完成现场/商家直接确认。
A40: chg_000037 | B40: 16_food_vendors | C40: ven_000008 | D40: notes | E40: 该页主要用于店铺/商品候选；商品零售形式、库存及当前营业需复核。 营业时间为平台页面展示值，正式推荐前需复核。 | F40: 该页主要用于店铺/商品候选；商品零售形式、库存及当前营业需复核。 营业时间为平台页面展示值，正式推荐前需复核。 平台页面显示人均约29元，仅为参考消费，不是单道菜价格。 | G40: data_correction | H40: src_000071 | J40: 2026-10-22T01:16:33+08:00 | K40: 成员4（AI初步核查） | L40: 1 | M40: 2 | N40: pending_review | O40: 初步核查修正；未完成现场/商家直接确认。
A41: chg_000038 | B41: 16_food_vendors | C41: ven_000009 | D41: price_band | E41: 0-10元/人（平台显示人均约7元） | F41: 0-10元/人 | G41: data_correction | H41: 价格区间字段只保留人民币区间，平台人均值移至备注。 | I41: src_000072 | J41: 2026-10-22T01:16:33+08:00 | K41: 成员4（AI初步核查） | L41: 1 | M41: 2 | N41: pending_review | O41: 初步核查修正；未完成现场/商家直接确认。
A42: chg_000039 | B42: 16_food_vendors | C42: ven_000009 | D42: notes | E42: 营业时间为早餐时段，来自携程页面；清真标识与菜品配方需以商家当前信息为准。 营业时间为平台页面展示值，正式推荐前需复核。 | F42: 营业时间为早餐时段，来自携程页面；清真标识与菜品配方需以商家当前信息为准。 营业时间为平台页面展示值，正式推荐前需复核。 平台页面显示人均约7元，仅为参考消费，不是单道菜价格。 | G42: data_correction | H42: src_000072 | J42: 2026-10-22T01:16:33+08:00 | K42: 成员4（AI初步核查） | L42: 1 | M42: 2 | N42: pending_review | O42: 初步核查修正；未完成现场/商家直接确认。
A43: chg_000040 | B43: 16_food_vendors | C43: ven_000010 | D43: price_band | E43: 50-60元/人（携程附近列表显示人均约58元，需复核） | G43: data_correction | H43: 原价格区间未找到与该商家记录直接对应的来源；避免把未证实价格作为数据。 | I43: src_000075 | J43: 2026-10-22T01:16:33+08:00 | K43: 成员4（AI初步核查） | L43: 1 | M43: 2 | N43: pending_review | O43: 初步核查修正；未完成现场/商家直接确认。
A44: chg_000041 | B44: 16_food_vendors | C44: ven_000010 | D44: notes | E44: 地址/坐标来自高德地点页；平台列表价格为人均参考；营业时间待查。 | F44: 地址/坐标来自高德地点页；平台列表价格为人均参考；营业时间待查。 初步核查：当前高德来源只支持门店名称、地址和坐标；原人均约58元未找到对应来源，已清空待核实。 | G44: data_correction | H44: 原价格区间未找到与该商家记录直接对应的来源。 | I44: src_000075 | J44: 2026-10-22T01:16:33+08:00 | K44: 成员4（AI初步核查） | L44: 1 | M44: 2 | N44: pending_review | O44: 初步核查修正；未完成现场/商家直接确认。
A45: chg_000042 | B45: 16_food_vendors | C45: ven_000016 | D45: price_band | E45: 60-70元/人（携程列表显示人均约63元） | F45: 50-60元/人 | G45: data_correction | H45: 携程列表当前显示人均约55元；将错误的60-70元区间改为50-60元。 | I45: src_000073 | J45: 2026-10-22T01:16:33+08:00 | K45: 成员4（AI初步核查） | L45: 1 | M45: 2 | N45: pending_review | O45: 初步核查修正；未完成现场/商家直接确认。
A46: chg_000043 | B46: 16_food_vendors | C46: ven_000016 | D46: business_hours | F46: 10:30开门（关门时间未显示） | G46: data_correction | H46: 来源页只显示10:30营业/开门，不支持完整营业时段；避免推断关门时间。 | I46: src_000073 | J46: 2026-10-22T01:16:33+08:00 | K46: 成员4（AI初步核查） | L46: 1 | M46: 2 | N46: pending_review | O46: 初步核查修正；未完成现场/商家直接确认。
A47: chg_000044 | B47: 16_food_vendors | C47: ven_000016 | D47: notes | E47: 携程列表显示店名、鼓楼广场附近位置和人均参考价；精确门牌、营业时间和当前菜单待核实。 | F47: 携程列表显示店名、鼓楼广场附近位置和人均参考价；精确门牌、营业时间和当前菜单待核实。 初步核查：携程列表显示人均约55元、10:30营业；仅有开门时间，关门时间及精确门牌仍待核实。 | G47: data_correction | H47: 纠正人均消费并说明时间字段只有开门信息。 | I47: src_000073 | J47: 2026-10-22T01:16:33+08:00 | K47: 成员4（AI初步核查） | L47: 1 | M47: 2 | N47: pending_review | O47: 初步核查修正；未完成现场/商家直接确认。
A48: chg_000045 | B48: 16_food_vendors | C48: ven_000017 | D48: business_hours | F48: 06:30开门（关门时间未显示） | G48: data_correction | H48: 来源只显示开门时间，按原页面记录并明确关门时间未知。 | I48: src_000073 | J48: 2026-10-22T01:16:33+08:00 | K48: 成员4（AI初步核查） | L48: 1 | M48: 2 | N48: pending_review | O48: 初步核查修正；未完成现场/商家直接确认。
A49: chg_000046 | B49: 16_food_vendors | C49: ven_000017 | D49: notes | E49: 携程列表支持店名及早餐类候选；具体门牌、完整营业时段及当前菜单待核实。 | F49: 携程列表支持店名及早餐类候选；具体门牌、完整营业时段及当前菜单待核实。 携程列表显示06:30营业，仅显示开门时间。 | G49: data_correction | H49: 补充营业时间信息的来源和不完整性。 | I49: src_000073 | J49: 2026-10-22T01:16:33+08:00 | K49: 成员4（AI初步核查） | L49: 1 | M49: 2 | N49: pending_review | O49: 初步核查修正；未完成现场/商家直接确认。
A50: chg_000047 | B50: 16_food_vendors | C50: ven_000018 | D50: business_hours | F50: 06:30开门（关门时间未显示） | G50: data_correction | H50: 来源只显示开门时间，按原页面记录并明确关门时间未知。 | I50: src_000073 | J50: 2026-10-22T01:16:33+08:00 | K50: 成员4（AI初步核查） | L50: 1 | M50: 2 | N50: pending_review | O50: 初步核查修正；未完成现场/商家直接确认。
A51: chg_000048 | B51: 16_food_vendors | C51: ven_000018 | D51: notes | E51: 携程列表支持店名及驴肉汤候选；精确地址、完整营业时段和当前供应待核实。 | F51: 携程列表支持店名及驴肉汤候选；精确地址、完整营业时段和当前供应待核实。 携程列表显示06:30营业，仅显示开门时间。 | G51: data_correction | H51: 补充营业时间信息的来源和不完整性。 | I51: src_000073 | J51: 2026-10-22T01:16:33+08:00 | K51: 成员4（AI初步核查） | L51: 1 | M51: 2 | N51: pending_review | O51: 初步核查修正；未完成现场/商家直接确认。
A52: chg_000049 | B52: 16_food_vendors | C52: ven_000019 | D52: business_hours | F52: 06:30开门（关门时间未显示） | G52: data_correction | H52: 来源只显示开门时间，按原页面记录并明确关门时间未知。 | I52: src_000073 | J52: 2026-10-22T01:16:33+08:00 | K52: 成员4（AI初步核查） | L52: 1 | M52: 2 | N52: pending_review | O52: 初步核查修正；未完成现场/商家直接确认。
A53: chg_000050 | B53: 16_food_vendors | C53: ven_000019 | D53: notes | E53: 携程列表支持店名及羊双肠早餐候选；精确门牌、营业时段和菜品构成待核实。 | F53: 携程列表支持店名及羊双肠早餐候选；精确门牌、营业时段和菜品构成待核实。 携程列表显示06:30营业，仅显示开门时间。 | G53: data_correction | H53: 补充营业时间信息的来源和不完整性。 | I53: src_000073 | J53: 2026-10-22T01:16:33+08:00 | K53: 成员4（AI初步核查） | L53: 1 | M53: 2 | N53: pending_review | O53: 初步核查修正；未完成现场/商家直接确认。
A54: chg_000051 | B54: 16_food_vendors | C54: ven_000020 | D54: business_hours | F54: 05:30开门（关门时间未显示） | G54: data_correction | H54: 来源只显示开门时间，按原页面记录并明确关门时间未知。 | I54: src_000073 | J54: 2026-10-22T01:16:33+08:00 | K54: 成员4（AI初步核查） | L54: 1 | M54: 2 | N54: pending_review | O54: 初步核查修正；未完成现场/商家直接确认。
A55: chg_000052 | B55: 16_food_vendors | C55: ven_000020 | D55: notes | E55: 携程列表支持店名和豆沫候选；精确地址、完整营业时段和配方待核实。 | F55: 携程列表支持店名和豆沫候选；精确地址、完整营业时段和配方待核实。 携程列表显示05:30营业，仅显示开门时间。 | G55: data_correction | H55: 补充营业时间信息的来源和不完整性。 | I55: src_000073 | J55: 2026-10-22T01:16:33+08:00 | K55: 成员4（AI初步核查） | L55: 1 | M55: 2 | N55: pending_review | O55: 初步核查修正；未完成现场/商家直接确认。
A56: chg_000053 | B56: 16_food_vendors | C56: ven_000021 | D56: business_hours | F56: 11:30开门（关门时间未显示） | G56: data_correction | H56: 来源只显示开门时间，按原页面记录并明确关门时间未知。 | I56: src_000073 | J56: 2026-10-22T01:16:33+08:00 | K56: 成员4（AI初步核查） | L56: 1 | M56: 2 | N56: pending_review | O56: 初步核查修正；未完成现场/商家直接确认。
A57: chg_000054 | B57: 16_food_vendors | C57: ven_000021 | D57: notes | E57: 携程列表显示店名、龙亭区位置和人均参考价；精确门牌、完整营业时段和当前菜单待核实。 | F57: 携程列表显示店名、龙亭区位置和人均参考价；精确门牌、完整营业时段和当前菜单待核实。 携程列表显示11:30营业，仅显示开门时间。 | G57: data_correction | H57: 补充营业时间信息的来源和不完整性。 | I57: src_000073 | J57: 2026-10-22T01:16:33+08:00 | K57: 成员4（AI初步核查） | L57: 1 | M57: 2 | N57: pending_review | O57: 初步核查修正；未完成现场/商家直接确认。
A58: chg_000055 | B58: 16_food_vendors | C58: ven_000024 | D58: business_hours | F58: 10:00开门（关门时间未显示） | G58: data_correction | H58: 来源只显示开门时间，按原页面记录并明确关门时间未知。 | I58: src_000074 | J58: 2026-10-22T01:16:33+08:00 | K58: 成员4（AI初步核查） | L58: 1 | M58: 2 | N58: pending_review | O58: 初步核查修正；未完成现场/商家直接确认。
A59: chg_000056 | B59: 16_food_vendors | C59: ven_000024 | D59: notes | E59: 携程附近列表显示店名及人均参考价；只显示约10:00开门提示，完整营业时间和精确地址待核实。 | F59: 携程附近列表显示店名及人均参考价；只显示约10:00开门提示，完整营业时间和精确地址待核实。 携程附近美食页显示10:00营业，仅显示开门时间。 | G59: data_correction | H59: 补充营业时间信息的来源和不完整性。 | I59: src_000074 | J59: 2026-10-22T01:16:33+08:00 | K59: 成员4（AI初步核查） | L59: 1 | M59: 2 | N59: pending_review | O59: 初步核查修正；未完成现场/商家直接确认。
A60: chg_000057 | B60: 16_food_vendors | C60: ven_000025 | D60: business_hours | F60: 11:30开门（关门时间未显示） | G60: data_correction | H60: 来源只显示开门时间，按原页面记录并明确关门时间未知。 | I60: src_000074 | J60: 2026-10-22T01:16:33+08:00 | K60: 成员4（AI初步核查） | L60: 1 | M60: 2 | N60: pending_review | O60: 初步核查修正；未完成现场/商家直接确认。
A61: chg_000058 | B61: 16_food_vendors | C61: ven_000025 | D61: notes | E61: 携程附近列表显示店名、人均参考价及约11:30开门提示；精确地址和完整营业时间待核实。 | F61: 携程附近列表显示店名、人均参考价及约11:30开门提示；精确地址和完整营业时间待核实。 携程附近美食页显示11:30营业，仅显示开门时间。 | G61: data_correction | H61: 补充营业时间信息的来源和不完整性。 | I61: src_000074 | J61: 2026-10-22T01:16:33+08:00 | K61: 成员4（AI初步核查） | L61: 1 | M61: 2 | N61: pending_review | O61: 初步核查修正；未完成现场/商家直接确认。
A62: chg_000059 | B62: 16_food_vendors | C62: ven_000026 | D62: business_hours | F62: 10:00开门（关门时间未显示） | G62: data_correction | H62: 来源只显示开门时间，按原页面记录并明确关门时间未知。 | I62: src_000074 | J62: 2026-10-22T01:16:33+08:00 | K62: 成员4（AI初步核查） | L62: 1 | M62: 2 | N62: pending_review | O62: 初步核查修正；未完成现场/商家直接确认。
A63: chg_000060 | B63: 16_food_vendors | C63: ven_000026 | D63: notes | E63: 携程附近列表显示店名、人均参考价及约10:00开门提示；精确地址、完整营业时间和菜单待核实。 | F63: 携程附近列表显示店名、人均参考价及约10:00开门提示；精确地址、完整营业时间和菜单待核实。 携程附近美食页显示10:00营业，仅显示开门时间。 | G63: data_correction | H63: 补充营业时间信息的来源和不完整性。 | I63: src_000074 | J63: 2026-10-22T01:16:33+08:00 | K63: 成员4（AI初步核查） | L63: 1 | M63: 2 | N63: pending_review | O63: 初步核查修正；未完成现场/商家直接确认。
A64: chg_000061 | B64: 16_food_vendors | C64: ven_000022 | D64: name | E64: 宋风雅宴（双龙巷店） | F64: 宋风雅宴·宋文化餐厅（双龙巷店） | G64: data_correction | H64: 统一为高德地点页展示的门店名称。 | I64: src_000083 | J64: 2026-10-22T01:16:33+08:00 | K64: 成员4（AI初步核查） | L64: 1 | M64: 2 | N64: pending_review | O64: 初步核查修正；未完成现场/商家直接确认。
A65: chg_000062 | B65: 16_food_vendors | C65: ven_000022 | D65: aliases | E65: 宋风雅宴宋文化地标餐厅 | F65: 宋风雅宴（双龙巷店）；宋风雅宴·宋文化地标餐厅（双龙巷店） | G65: data_correction | H65: 补充平台名称变体，避免同一分店重复建档。 | I65: src_000083 | J65: 2026-10-22T01:16:33+08:00 | K65: 成员4（AI初步核查） | L65: 1 | M65: 2 | N65: pending_review | O65: 初步核查修正；未完成现场/商家直接确认。
A66: chg_000063 | B66: 16_food_vendors | C66: ven_000022 | D66: address | F66: 河南省开封市顺河回族区双龙巷历史文化区A7号院（宋风雅宴/杜孟模博物馆内） | G66: data_correction | H66: 补充高德地点页的具体地址。 | I66: src_000083 | J66: 2026-10-22T01:16:33+08:00 | K66: 成员4（AI初步核查） | L66: 1 | M66: 2 | N66: pending_review | O66: 初步核查修正；未完成现场/商家直接确认。
A67: chg_000064 | B67: 16_food_vendors | C67: ven_000022 | D67: lng | F67: 114.36225 | G67: data_correction | H67: 补充高德地点页坐标，坐标顺序按表格要求存经度。 | I67: src_000083 | J67: 2026-10-22T01:16:33+08:00 | K67: 成员4（AI初步核查） | L67: 1 | M67: 2 | N67: pending_review | O67: 初步核查修正；未完成现场/商家直接确认。
A68: chg_000065 | B68: 16_food_vendors | C68: ven_000022 | D68: lat | F68: 34.801763 | G68: data_correction | H68: 补充高德地点页坐标，坐标顺序按表格要求存纬度。 | I68: src_000083 | J68: 2026-10-22T01:16:33+08:00 | K68: 成员4（AI初步核查） | L68: 1 | M68: 2 | N68: pending_review | O68: 初步核查修正；未完成现场/商家直接确认。
A69: chg_000066 | B69: 16_food_vendors | C69: ven_000022 | D69: crs | F69: GCJ-02 | G69: data_correction | H69: 高德地图坐标按GCJ-02标注，避免坐标系缺失。 | I69: src_000083 | J69: 2026-10-22T01:16:33+08:00 | K69: 成员4（AI初步核查） | L69: 1 | M69: 2 | N69: pending_review | O69: 初步核查修正；未完成现场/商家直接确认。
A70: chg_000067 | B70: 16_food_vendors | C70: ven_000022 | D70: external_poi_id | F70: B0JKPHTQWF | G70: data_correction | H70: 记录高德地图POI ID，便于回溯。 | I70: src_000083 | J70: 2026-10-22T01:16:33+08:00 | K70: 成员4（AI初步核查） | L70: 1 | M70: 2 | N70: pending_review | O70: 初步核查修正；未完成现场/商家直接确认。
A71: chg_000068 | B71: 16_food_vendors | C71: ven_000022 | D71: business_hours | F71: 11:00-14:00；17:00-21:00（平台显示，需复核） | G71: data_correction | H71: 补充Trip.com页面展示的营业时段，保留待复核标记。 | I71: src_000086 | J71: 2026-10-22T01:16:33+08:00 | K71: 成员4（AI初步核查） | L71: 1 | M71: 2 | N71: pending_review | O71: 初步核查修正；未完成现场/商家直接确认。
A72: chg_000069 | B72: 16_food_vendors | C72: ven_000022 | D72: price_band | E72: 70-90元/人（携程列表显示人均约80元） | F72: 70-90元/人 | G72: data_correction | H72: 保留平台显示人均约80元对应的价格区间，价格仅供预算参考。 | I72: src_000086 | J72: 2026-10-22T01:16:33+08:00 | K72: 成员4（AI初步核查） | L72: 1 | M72: 2 | N72: pending_review | O72: 初步核查修正；未完成现场/商家直接确认。
A73: chg_000070 | B73: 16_food_vendors | C73: ven_000022 | D73: source_id | E73: src_000073 | F73: src_000083 | G73: data_correction | H73: 主来源改为直接支持门店地址和坐标的高德地点页；营业时间和价格的补充来源为src_000086。 | I73: src_000083 | J73: 2026-10-22T01:16:33+08:00 | K73: 成员4（AI初步核查） | L73: 1 | M73: 2 | N73: pending_review | O73: 初步核查修正；未完成现场/商家直接确认。
A74: chg_000071 | B74: 16_food_vendors | C74: ven_000022 | D74: notes | E74: 携程列表支持店名和人均参考价；精确地址、营业时间及是否适合项目推荐待核实。 | F74: 地址、坐标和电话来自高德地点页src_000083；营业时段11:00-14:00、17:00-21:00及人均约80元来自Trip.com页面src_000086。两个来源均为平台公开信息，非商家实时确认；正式推荐前复核。 | G74: data_correction | H74: 纠正此前引用泛列表作为该商家直接来源的问题，并补齐位置证据。 | I74: src_000083 | J74: 2026-10-22T01:16:33+08:00 | K74: 成员4（AI初步核查） | L74: 1 | M74: 2 | N74: pending_review | O74: 初步核查修正；未完成现场/商家直接确认。
A75: chg_000072 | B75: 16_food_vendors | C75: ven_000023 | D75: address | F75: 河南省开封市龙亭区北书店街59号 | G75: data_correction | H75: 补充高德地点页的精确地址。 | I75: src_000084 | J75: 2026-10-22T01:16:33+08:00 | K75: 成员4（AI初步核查） | L75: 1 | M75: 2 | N75: pending_review | O75: 初步核查修正；未完成现场/商家直接确认。
A76: chg_000073 | B76: 16_food_vendors | C76: ven_000023 | D76: lng | F76: 114.35623 | G76: data_correction | H76: 补充高德地点页坐标，按表格要求存经度。 | I76: src_000084 | J76: 2026-10-22T01:16:33+08:00 | K76: 成员4（AI初步核查） | L76: 1 | M76: 2 | N76: pending_review | O76: 初步核查修正；未完成现场/商家直接确认。
A77: chg_000074 | B77: 16_food_vendors | C77: ven_000023 | D77: lat | F77: 34.79904 | G77: data_correction | H77: 补充高德地点页坐标，按表格要求存纬度。 | I77: src_000084 | J77: 2026-10-22T01:16:33+08:00 | K77: 成员4（AI初步核查） | L77: 1 | M77: 2 | N77: pending_review | O77: 初步核查修正；未完成现场/商家直接确认。
A78: chg_000075 | B78: 16_food_vendors | C78: ven_000023 | D78: crs | F78: GCJ-02 | G78: data_correction | H78: 高德地图坐标按GCJ-02标注。 | I78: src_000084 | J78: 2026-10-22T01:16:33+08:00 | K78: 成员4（AI初步核查） | L78: 1 | M78: 2 | N78: pending_review | O78: 初步核查修正；未完成现场/商家直接确认。
A79: chg_000076 | B79: 16_food_vendors | C79: ven_000023 | D79: external_poi_id | F79: B017A0N74G | G79: data_correction | H79: 记录高德地图POI ID，便于回溯。 | I79: src_000084 | J79: 2026-10-22T01:16:33+08:00 | K79: 成员4（AI初步核查） | L79: 1 | M79: 2 | N79: pending_review | O79: 初步核查修正；未完成现场/商家直接确认。
A80: chg_000077 | B80: 16_food_vendors | C80: ven_000023 | D80: business_hours | F80: 06:30-13:30 | G80: data_correction | H80: 补充携程餐厅详情页显示的营业时段。 | I80: src_000085 | J80: 2026-10-22T01:16:33+08:00 | K80: 成员4（AI初步核查） | L80: 1 | M80: 2 | N80: pending_review | O80: 初步核查修正；未完成现场/商家直接确认。
A81: chg_000078 | B81: 16_food_vendors | C81: ven_000023 | D81: price_band | E81: 10-20元/人（携程列表显示人均约19元） | F81: 10-20元/人 | G81: data_correction | H81: 保留平台显示人均约19元对应的价格区间。 | I81: src_000085 | J81: 2026-10-22T01:16:33+08:00 | K81: 成员4（AI初步核查） | L81: 1 | M81: 2 | N81: pending_review | O81: 初步核查修正；未完成现场/商家直接确认。
A82: chg_000079 | B82: 16_food_vendors | C82: ven_000023 | D82: source_id | E82: src_000073 | F82: src_000084 | G82: data_correction | H82: 主来源改为直接支持门店名称、地址和坐标的高德地点页；营业时间、人均和菜品补充来源为src_000085。 | I82: src_000084 | J82: 2026-10-22T01:16:33+08:00 | K82: 成员4（AI初步核查） | L82: 1 | M82: 2 | N82: pending_review | O82: 初步核查修正；未完成现场/商家直接确认。
A83: chg_000080 | B83: 16_food_vendors | C83: ven_000023 | D83: notes | E83: 携程列表支持店名及四味菜候选；精确门牌、营业时段及当前供应待核实。 | F83: 地址、坐标和电话来自高德地点页src_000084；携程餐厅详情页src_000085显示营业时间06:30-13:30、人均约19元，特色菜含“四味烩菜”。平台信息仍需正式推荐前复核。 | G83: data_correction | H83: 纠正此前使用泛列表作为门店直接来源的问题，并补齐位置证据。 | I83: src_000084 | J83: 2026-10-22T01:16:33+08:00 | K83: 成员4（AI初步核查） | L83: 1 | M83: 2 | N83: pending_review | O83: 初步核查修正；未完成现场/商家直接确认。
A84: chg_000081 | B84: 15_food_items | C84: food_000021 | D84: intro_source_id | E84: src_000073 | F84: src_000085 | G84: data_correction | H84: 原泛列表来源未直接列出该店；改为携程餐厅详情页支持的菜品来源。 | I84: src_000085 | J84: 2026-10-22T01:16:33+08:00 | K84: 成员4（AI初步核查） | L84: 1 | M84: 2 | N84: pending_review | O84: 初步核查修正；未完成现场/商家直接确认。
A85: chg_000082 | B85: 15_food_items | C85: food_000021 | D85: intro | E85: 携程开封美食列表列出李记四味菜馆（书店街店），可作为四味菜商家与菜品的候选线索。 | F85: 携程餐厅详情页将李记四味菜馆（书店街店）的特色菜列为“四味烩菜”；本项目暂将“四味菜”作为候选标准名称，名称对应关系仍需人工确认。 | G85: data_correction | H85: 以直接菜单/特色菜页面替代不匹配的泛列表来源。 | I85: src_000085 | J85: 2026-10-22T01:16:33+08:00 | K85: 成员4（AI初步核查） | L85: 1 | M85: 2 | N85: pending_review | O85: 初步核查修正；未完成现场/商家直接确认。
A86: chg_000083 | B86: 15_food_items | C86: food_000021 | D86: notes | E86: 该列表未充分说明具体配方，正式介绍前需补充可靠资料。 | F86: 来源菜单使用“四味烩菜”而非完全相同的标准名称“四味菜”；暂作为候选，正式推荐前需核对命名和具体做法。 | G86: data_correction | H86: 标记标准菜名与来源菜名的差异。 | I86: src_000085 | J86: 2026-10-22T01:16:33+08:00 | K86: 成员4（AI初步核查） | L86: 1 | M86: 2 | N86: pending_review | O86: 初步核查修正；未完成现场/商家直接确认。
A87: chg_000084 | B87: 17_vendor_foods | C87: vf_000020 | D87: validation_status | E87: candidate | F87: pending_review | G87: data_correction | H87: 来源菜单显示“红薯泥”，标准菜品记录为“炒红薯泥”，名称/做法未完全一致。 | I87: src_000067 | J87: 2026-10-22T01:16:33+08:00 | K87: 成员4（AI初步核查） | L87: 1 | M87: 2 | N87: pending_review | O87: 初步核查修正；未完成现场/商家直接确认。
A88: chg_000085 | B88: 17_vendor_foods | C88: vf_000020 | D88: evidence_note | E88: 公开平台页面/推荐菜列表列有“红薯泥”；该证据仅支持候选关联，不等于商家当前实时供应，正式推荐前需以商家当前菜单或直接确认复核。 | F88: 公开平台页面/推荐菜列表列有“红薯泥”；该证据仅支持候选关联，不等于商家当前实时供应，正式推荐前需以商家当前菜单或直接确认复核。 初步核查：原菜单名称为“红薯泥”，与标准名称“炒红薯泥”不完全一致，待人工确认是否为同一道菜。 | G88: data_correction | H88: 明确来源菜名与标准名称的差异。 | I88: src_000067 | J88: 2026-10-22T01:16:33+08:00 | K88: 成员4（AI初步核查） | L88: 1 | M88: 2 | N88: pending_review | O88: 初步核查修正；未完成现场/商家直接确认。
A89: chg_000086 | B89: 17_vendor_foods | C89: vf_000043 | D89: evidence_source_id | E89: src_000081 | F89: src_000075 | G89: data_correction | H89: 优先使用直接对应门店的高德地点页，减少对2025历史榜单的依赖。 | I89: src_000075 | J89: 2026-10-22T01:16:33+08:00 | K89: 成员4（AI初步核查） | L89: 1 | M89: 2 | N89: pending_review | O89: 初步核查修正；未完成现场/商家直接确认。
A90: chg_000087 | B90: 17_vendor_foods | C90: vf_000043 | D90: evidence_note | E90: 公开平台页面/推荐菜列表列有“现做锅贴”；该证据仅支持候选关联，不等于商家当前实时供应，正式推荐前需以商家当前菜单或直接确认复核。 高德榜单介绍该店锅贴为现点现做；该榜单不是实时官方菜单，当前供应待门店核实。 | F90: 高德地点页确认店名为“邢家锅贴老店（大梁门总店）”；该关联仍只是候选，需以当前菜单确认。 | G90: data_correction | H90: 将证据说明改为与当前来源页面实际支持内容一致。 | I90: src_000075 | J90: 2026-10-22T01:16:33+08:00 | K90: 成员4（AI初步核查） | L90: 1 | M90: 2 | N90: pending_review | O90: 初步核查修正；未完成现场/商家直接确认。
A91: chg_000088 | B91: 17_vendor_foods | C91: vf_000044 | D91: evidence_source_id | E91: src_000081 | F91: src_000080 | G91: data_correction | H91: 优先使用直接对应门店的高德地点页，减少对2025历史榜单的依赖。 | I91: src_000080 | J91: 2026-10-22T01:16:33+08:00 | K91: 成员4（AI初步核查） | L91: 1 | M91: 2 | N91: pending_review | O91: 初步核查修正；未完成现场/商家直接确认。
A92: chg_000089 | B92: 17_vendor_foods | C92: vf_000044 | D92: evidence_note | E92: 公开平台页面/推荐菜列表列有“桶子鸡”；该证据仅支持候选关联，不等于商家当前实时供应，正式推荐前需以商家当前菜单或直接确认复核。 高德榜单将该门店与桶子鸡关联；当前商品供应及门店状态待核实。 | F92: 高德地点页店名包含“马豫兴桶子鸡”；该关联仍只是候选，需确认当前商品供应。 | G92: data_correction | H92: 将证据说明改为与当前来源页面实际支持内容一致。 | I92: src_000080 | J92: 2026-10-22T01:16:33+08:00 | K92: 成员4（AI初步核查） | L92: 1 | M92: 2 | N92: pending_review | O92: 初步核查修正；未完成现场/商家直接确认。
... A96: chg_000093 | B96: 17_vendor_foods | C96: vf_000046 | D96: evidence_note | E96: 公开平台页面/推荐菜列表列有“传统老式开封米线”；该证据仅支持候选关联，不等于商家当前实时供应，正式推荐前需以商家当前菜单或直接确认复核。 高德榜单描述该店米线搭配豆皮、海带、鹌鹑蛋、咖喱粉和麻油；配方需商家确认。 | F96: 公开平台页面/推荐菜列表列有“传统老式开封米线”；该证据仅支持候选关联，不等于商家当前实时供应，正式推荐前需以商家当前菜单或直接确认复核。 高德榜单描述该店米线搭配豆皮、海带、鹌鹑蛋、咖喱粉和麻油；配方需商家确认。 初步核查：该证据来自2025年历史榜单，不能证明当前营业或实时供应，待更新来源复核。 | G96: data_correction | H96: 明确历史榜单的时效限制。 | I96: src_000081 | J96: 2026-10-22T01:16:33+08:00 | K96: 成员4（AI初步核查） | L96: 1 | M96: 2 | N96: pending_review | O96: 初步核查修正；未完成现场/商家直接确认。
A97: chg_000094 | B97: 17_vendor_foods | C97: vf_000047 | D97: * | F97: {"relation_id": "vf_000047", "vendor_id": "ven_000028", "food_id": "food_000003", "evidence_source_id": "src_000063", "evidence_note": "商务部老字号数字博物馆页面明确列出宜生斋主营产品为桶子鸡、烧鸡；这支持候选供应关系，但不证明该店当前库存或当日供应。", "verified_at": "2026-10-22T01:16:33+08:00", "validation_status": "candidate", "seasonal_flag": "unknown", "available_from": null, "available_to": null, "reviewer": null, "version": 1, "notes": "记录时间为本轮查看来源时间，不代表商家已直接确认；当前供应仍待复核。"} | G97: record_addition | H97: 新增有公开来源支持的候选供应关系；未标记为已核实。 | I97: src_000063 | J97: 2026-10-22T01:16:33+08:00 | K97: 成员4（AI初步核查） | M97: 1 | N97: pending_review | O97: 候选关系，商家当前供应仍需确认。
A98: chg_000095 | B98: 17_vendor_foods | C98: vf_000048 | D98: * | F98: {"relation_id": "vf_000048", "vendor_id": "ven_000023", "food_id": "food_000021", "evidence_source_id": "src_000085", "evidence_note": "携程餐厅详情页将该店特色菜列为“四味烩菜”；本表标准菜名为“四味菜”，先建立待复核候选关联，需确认是否按同一菜品标准化。", "verified_at": "2026-10-22T01:16:33+08:00", "validation_status": "pending_review", "seasonal_flag": "unknown", "available_from": null, "available_to": null, "reviewer": null, "version": 1, "notes": "记录时间为本轮查看来源时间，不代表商家已直接确认；名称映射待人工复核。"} | G98: record_addition | H98: 新增有公开来源支持的候选供应关系；未标记为已核实。 | I98: src_000085 | J98: 2026-10-22T01:16:33+08:00 | K98: 成员4（AI初步核查） | M98: 1 | N98: pending_review | O98: 候选关系，商家当前供应仍需确认。
A99: chg_000096 | B99: 18_source_records | C99: src_000083 | D99: * | F99: https://ditu.amap.com/place/B0JKPHTQWF | G99: source_addition | H99: 为补齐商家位置、营业时段和菜品来源而新增直接来源记录。 | I99: src_000083 | J99: 2026-10-22T01:16:33+08:00 | K99: 成员4（AI初步核查） | M99: 1 | N99: pending_review | O99: 已记录URL与摘要，未保存本地网页快照。
A100: chg_000097 | B100: 18_source_records | C100: src_000084 | D100: * | F100: https://www.amap.com/place/B017A0N74G | G100: source_addition | H100: 为补齐商家位置、营业时段和菜品来源而新增直接来源记录。 | I100: src_000084 | J100: 2026-10-22T01:16:33+08:00 | K100: 成员4（AI初步核查） | M100: 1 | N100: pending_review | O100: 已记录URL与摘要，未保存本地网页快照。
A101: chg_000098 | B101: 18_source_records | C101: src_000085 | D101: * | F101: https://you.ctrip.com/food/165/7578447.html | G101: source_addition | H101: 为补齐商家位置、营业时段和菜品来源而新增直接来源记录。 | I101: src_000085 | J101: 2026-10-22T01:16:33+08:00 | K101: 成员4（AI初步核查） | M101: 1 | N101: pending_review | O101: 已记录URL与摘要，未保存本地网页快照。
A102: chg_000099 | B102: 18_source_records | C102: src_000086 | D102: * | F102: https://jp.trip.com/restaurant/china/kaifeng/detail/song-feng-ya-yan-restaurant-shuanglong-lane-branch-144559420/?rankingId=100900014673&source=uccrank | G102: source_addition | H102: 为补齐商家位置、营业时段和菜品来源而新增直接来源记录。 | I102: src_000086 | J102: 2026-10-22T01:16:33+08:00 | K102: 成员4（AI初步核查） | M102: 1 | N102: pending_review | O102: 已记录URL与摘要，未保存本地网页快照。
A103: chg_000100 | B103: 16_food_vendors | C103: ven_000017 | D103: price_band | E103: 10-20元/人（携程列表显示人均约11元） | F103: 10-20元/人 | G103: data_correction | H103: 价格区间字段只保留标准人民币区间；平台人均参考值保留在备注中。 | I103: src_000073 | J103: 2026-10-22T01:18:08+08:00 | K103: 成员4（AI初步核查） | L103: 1 | M103: 2 | N103: pending_review | O103: 第二轮初核补正；仍需人工/商家确认。
...

Sheet 90_校验规则
A1: 第一轮自动校验规则
A2: 校验脚本按issue_code输出到异常清单；删除、合并和降级必须同时写变更日志。
A4: 规则ID | B4: 适用范围 | C4: 检查项 | D4: 严重级别 | E4: 问题代码 | F4: 输出字段 | G4: 处理要求
A5: VAL-01 | B5: 全表 | C5: 主键唯一 | D5: ERROR | E5: DUPLICATE_PRIMARY_KEY | F5: 记录表名、记录ID、重复次数 | G5: 所有ID字段不得重复
A6: VAL-02 | B6: 全表 | C6: 整行重复检测 | D6: WARNING | E6: EXACT_DUPLICATE | F6: 列出重复组和原始来源 | G6: 只提示，不静默删除
A7: VAL-03 | B7: 全表 | C7: 必填字段非空 | D7: ERROR | E7: REQUIRED_FIELD_MISSING | F7: 记录表名、记录ID、字段名 | G7: 未知值与空值不能混为false或0
A8: VAL-04 | B8: 时间字段 | C8: 日期与ISO 8601格式 | D8: ERROR | E8: INVALID_DATETIME | F8: 保留原始值并记录解析失败原因 | G8: 日期时间必须带+08:00或明确timezone
A9: VAL-05 | B9: 14_show_sessions | C9: 开始时间不晚于结束时间 | D9: ERROR | E9: INVALID_TIME_INTERVAL | F9: 记录开始、结束和来源 | G9: 结束未知时应留空并标记missing，不得猜测
A10: VAL-06 | B10: 坐标字段 | C10: 经纬度范围有效 | D10: ERROR | E10: INVALID_COORDINATE_RANGE | F10: 记录原坐标、坐标系和字段 | G10: 经度[-180,180]，纬度[-90,90]
A11: VAL-07 | B11: 坐标字段 | C11: 坐标必须声明CRS | D11: ERROR | E11: COORDINATE_WITHOUT_CRS | F11: 记录坐标和缺失CRS | G11: 禁止混用WGS84/GCJ-02/像素坐标
A12: VAL-08 | B12: 跨表 | C12: 场所外键存在 | D12: ERROR | E12: BROKEN_PLACE_REFERENCE | F12: 记录源表、源记录、缺失place_id | G12: entrances/open_rules/stages指向有效places
A13: VAL-09 | B13: 跨表 | C13: 节目与场次关联 | D13: ERROR | E13: BROKEN_PROGRAM_OR_STAGE_REFERENCE | F13: 记录session_id、program_id、stage_id | G13: 场次必须关联有效节目；已填舞台必须存在
A14: VAL-10 | B14: 跨表 | C14: 商家与菜品关系 | D14: ERROR | E14: BROKEN_FOOD_RELATION | F14: 记录relation_id、vendor_id、food_id | G14: 关系两端必须存在
A15: VAL-11 | B15: 跨表 | C15: 来源ID有效 | D15: ERROR | E15: BROKEN_SOURCE_REFERENCE | F15: 记录源表、记录ID、缺失source_id | G15: 核心事实必须有可定位置来源
... A25: VAL-21 | B25: 全表 | C25: verified状态的条件必填 | D25: ERROR | E25: VERIFIED_FIELDS_MISSING | F25: 记录表名、ID、缺失verified_at或reviewer | G25: 只有verified记录要求核实时间与核验人

Sheet 91_状态与取值
A1: 状态与取值字典
A2: 状态必须表达事实可信度、使用权限和异常处理结果，不得用单一“完成/未完成”混合表达。
A4: 字段/分组 | B4: 取值 | C4: 中文含义 | D4: 使用规则
A5: validation_status | B5: candidate | C5: 候选数据 | D5: 已发现但未完成事实核实
A6: validation_status | B6: pending_review | C6: 待人工核实 | D6: 字段不完整或有冲突
A7: validation_status | B7: verified | C7: 已核实 | D7: 证据足以支持当前用途
A8: validation_status | B8: conflict | C8: 存在冲突 | D8: 多个来源矛盾，尚未裁定
A9: validation_status | B9: stale | C9: 已过期待复核 | D9: 超过建议复核周期
A10: validation_status | B10: expired | C10: 已失效 | D10: 明确不再适用
A11: validation_status | B11: cancelled | C11: 已取消 | D11: 场次或活动取消
A12: validation_status | B12: mock | C12: 模拟数据 | D12: 不得进入正式推荐
A13: validation_status | B13: rejected | C13: 已弃用 | D13: 确认错误或不可使用
A14: rights_status | B14: open_license | C14: 开放许可 | D14: 遵守许可与署名要求
A15: rights_status | B15: authorized_display | C15: 已授权展示 | D15: 仅限授权范围
... A65: relation_role | B65: other | C65: 其他关系 | D65: 无法归入以上用途

Sheet 99_使用说明
A1: 第一轮填写与导入说明
A2: 用于成员之间交接。先保证候选可追溯、关系可定位，再逐步提升核实状态。
A4: 项目 | B4: 规则 | C4: 操作说明
A5: 数据表 | B5: 先填主表，再填关系表 | C5: 顺序：places → entrances/open_rules → programs → sessions → foods/vendors/relations → sources/change_log
A6: ID规则 | B6: 前缀+6位序号 | C6: place=pl，入口=ent，规则=or，节目=prg，场次=ses，菜品=food，商家=ven，关系=vf，来源=src，变更=chg
A7: 唯一性 | B7: 名称不承担主键职责 | C7: 同名地点、分店、节目或场次必须使用不同稳定ID
A8: 时间 | B8: 日期、时间与timezone分开 | C8: 有具体日期和时区；不得只写15:30。未知结束时间留空
A9: 坐标 | B9: 坐标与CRS同时填写 | C9: WGS84/GCJ-02/BD-09/像素坐标不得混用；GCJ-02到WGS84须记录转换规则
A10: 单位 | B10: 统一单位 | C10: 距离用米，耗时用秒或分钟并在字段名体现，价格用人民币区间
A11: 状态 | B11: 先候选后核实 | C11: 不得把格式完整误判为事实真实；候选和已核实分开统计
A12: 来源 | B12: 核心事实必须有source_id | C12: source_records保留URL、获取时间、证据路径、权限与哈希
A13: 冲突 | B13: 不静默选择答案 | C13: 保留旧值、新值和来源，状态标conflict或pending_review
A14: 批量导入 | B14: 先备份后导入 | C14: 每次导入前保存原始文件，导入后运行校验脚本
A15: 变更 | B15: 覆盖前写change_log | C15: 记录old/new、原因、来源、版本和审批人
... A25: 图片视频质量 | B25: 保留原始元数据 | C25: 有拍摄时间、位置或设备信息时记录；无法确认时留空，不推测

Sheet 20_二次核查报告
A1: 核查对象 | B1: 核查项 | C1: 二次核查结果 | D1: 处理动作 | E1: 证据/来源 | F1: 当前状态 | G1: 备注
A2: 全表结构 | B2: 主键与外键 | C2: 通过：商家、菜品、关系、来源、变更日志主键均唯一；商家/菜品/供应关系来源引用有效；供应关系两端外键有效。 | D2: 重新执行唯一性和外键检查 | E2: 15_food_items、16_food_vendors、17_vendor_foods、18_source_records、19_change_log | F2: 通过 | G2: 当前条数：商家32、菜品26、供应关系48、来源105、变更日志341。
A3: ven_000030 三胜街田庆辉田记米线 | B3: 地址与坐标 | C3: 高德地点页给出三胜前街7号，坐标34.800376,114.356027，POI B0FFG02SUH | D3: 补地址、经纬度、坐标系、POI ID并登记来源 | E3: src_000103 | F3: pending_review | G3: 高德页面可见评价为2019年；当前营业状态仍需复核
A4: ven_000031 益品虾皇（鼎立总店） | B4: 地址缺失 | C4: 高德榜单有名称及POI链接标识B0FFHXMMZP，但详情页本轮无法打开；吉屋网另有同名商户位置线索，不能确认分店身份 | D4: 补POI标识；地址继续留空并写入待核实线索 | E4: src_000081；src_000104 | F4: pending_review | G4: 不将同名商户位置直接冒充鼎立总店地址
A5: ven_000026 梁山烤肉（东京总店） | B5: 门牌冲突 | C5: 携程页面餐厅信息区写万胜路8号，同页用户点评写万胜路1号，BOSS信息也列万胜路1号 | D5: 地址字段降为地标级描述；保留conflict状态 | E5: src_000098；src_000099 | F5: conflict | G5: 未联系商家确认前不作为精确导航地址
A6: ven_000020 李记五香豆沫 | B6: 门牌与坐标对应 | C6: 携程列丁角街2号；高德坐标与西司广场夜市（丁角街83号）坐标约相距14-15米 | D6: 备注标出坐标/门牌对应关系待确认 | E6: src_000093；src_000094；src_000105 | F6: pending_review | G6: 附近参考点不等于该商家自身位置
A7: ven_000021 宋园灌汤小笼包（黄河路店） | B7: 地址粒度 | C7: Trip.com列黄河大街北段81号、阳光新天地1号楼临街房；携程列星光天地对面 | D7: 保留较详细地址并说明尚缺高德精确POI坐标 | E7: src_000095；https://gs.ctrip.com/html5/you/foods/fooddetail/165/129872873.html | F7: pending_review | G7: 详细地址来自Trip.com公开列表，仍建议地图端复核
A8: 17_vendor_foods 全部关系 | B8: verified_at语义 | C8: 发现48条候选/待核实关系曾把网页访问时间误填为核实时间 | D8: 清空未核实关系的verified_at；访问时间留在18_source_records.accessed_at | E8: 17_vendor_foods；18_source_records | F8: 已修正 | G8: 当前候选关系不应填实际核实时间
A9: ven_000027 福兴斋清真食品厂 | B9: 是否为消费门店 | C9: 政府公示地址为生产主体厂址，不能证明游客可直接到店消费 | D9: 保留记录但维持pending_review，不计作已确认零售商家 | E9: src_000101 | F9: pending_review | G9: 需另找具体零售门店或从推荐门店池排除
A10: 全体商家 | B10: 当前事实核实状态 | C10: 本工作簿尚无商家记录达到verified；多数地址来自第三方平台，仍需人工确认当前营业/实际供应 | D10: 保留candidate/pending_review/conflict，不把候选数当作合格数 | E10: 高德、携程、去哪儿、公开目录等 | F10: 待人工核实 | G10: 平台页面可作为线索，不等于商家直接确认
A11: 证据归档 | B11: 网页快照/截图 | C11: 本轮记录了来源网址和证据摘要，但未保存所有页面的本地截图或HTML快照 | D11: 正式交付前按团队规范补存可合法保存的证据 | E11: 18_source_records | F11: 待补 | G11: 当前source记录不能冒充本地原始快照

Sheet 21_第三轮核查报告
A1: 商家ID | B1: 商家名称 | C1: 地址核查结论 | D1: 坐标/POI核查结论 | E1: 时效性与状态 | F1: 主要来源ID | G1: 下一步动作
A2: ven_000001 | B2: 第一楼·中华老字号（寺后街总店） | C2: 高德与携程均支持寺后街8号 | D2: 高德坐标已补：34.794059,114.351924；POI B017A00HWY | E2: 携程页面可访问；高德评价较早，营业状态未由商家确认 | F2: src_000106；src_000064 | G2: 可保留候选；电话确认当前营业时间
A3: ven_000002 | B3: 黄家老店（宋城路店） | C3: 高德支持宋城路凤凰城1号楼 | D3: 高德坐标已补：34.785167,114.324778；POI B017A00L40 | E3: 高德可见评价较早；当前营业状态待确认 | F3: src_000107；src_000065 | G3: 可保留候选；地图端复核入口
A4: ven_000003 | B4: 黄家老店（晋安路店） | C4: Trip.com支持晋安路中段宏泰怡园1号楼底商、武夷夜市南头 | D4: 未取得可靠坐标，未推算 | E4: Trip.com页面显示10:30-21:00和电话；当前营业状态仍需确认 | F4: src_000112；src_000066 | G4: 在高德App按店名/电话定位后补坐标
A5: ven_000004 | B5: 楼中楼酒店（汴梁小宋城店） | C5: 携程与百度路线页均支持小宋城小吃城一楼擂台东侧6/7号附近 | D5: 未取得可靠经纬度 | E5: 携程页面显示10:00-14:00、17:00-21:00；营业状态未由商家确认 | F5: src_000067 | G5: 地图端定位具体入口后补坐标
A6: ven_000005 | B6: 中兴楼（汴京路店） | C6: 高德支持汴京路43号 | D6: 高德坐标已补：34.793215,114.370321；POI B017A000DA | E6: 携程有营业时段；高德可见评价较早 | F6: src_000108；src_000068 | G6: 可保留候选；电话确认营业状态
A7: ven_000006 | B7: 梅利汴京烤鸭·开封豫菜地标店（东司门店） | C7: 携程支持解放路与曹门大街交叉口东约60米路南 | D7: 未取得东司门店的可靠坐标；不得使用东大街店坐标 | E7: 高德找到的东大街店地址不同，属于另一分店 | F7: src_000069；src_000115 | G7: 按东司门店名称/电话单独定位后补坐标
A8: ven_000007 | B8: 稻香居锅贴（宋都御街店） | C8: 高德支持宋都御街73号 | D8: 高德坐标已补：34.800888,114.352005；POI B017A00K1Y | E8: 高德评价较早；携程列营业时段10:00-20:00 | F8: src_000109；src_000070 | G8: 确认当前是否营业，避免仅凭旧评价判断
A9: ven_000008 | B9: 兴盛德花生老店（中山路店） | C9: 携程支持相国寺街道中山路北段84号 | D9: 本轮未取得可靠坐标 | E9: 携程页面列08:00-21:00；当前营业状态仍需确认 | F9: src_000071 | G9: 高德地图端核对具体店铺后补坐标
A10: ven_000009 | B10: 李小记羊肉胡辣汤（清真店） | C10: 携程给出苹果园东/中路交叉口往南约20米；高德写劳动路苹东社区，描述有差异 | D10: 高德坐标已补：34.807061,114.380358；POI B017A0NJMD；同电话支持同一商家的可能性 | E10: 携程和高德电话相同，但入口位置仍需人工核实 | F10: src_000110；src_000072 | G10: 在高德App核对地图针是否位于携程描述的交叉口附近
A11: ven_000010 | B11: 邢家锅贴老店（大梁门总店） | C11: 高德支持西门大街198号、大梁门东约50米路北 | D11: 已有高德坐标34.801001,114.335170；POI B0FFG9U3L7 | E11: 页面可访问但评价较早，营业状态未知 | F11: src_000075 | G11: 确认当前营业状态和开放时段
A12: ven_000011 | B12: 邢家锅贴老店（苹果园店） | C12: 高德支持东环北路40号；携程也支持该地址 | D12: 现有坐标34.807511,114.374048；POI B017A0NNWI；本轮页面未重新显示坐标 | E12: 携程列10:00-14:00、17:00-21:00；坐标需在App中重新确认 | F12: src_000076；src_000067 | G12: 在高德App核对坐标和入口
... A33: ven_000032 | B33: 楼上楼灌汤包子馆（大梁路店） | C33: 高德支持航天大酒店对面、大梁路与武夷路交叉口东南角 | D33: 已有坐标34.801561,114.318807；POI B0GRGOROMS | E33: 可见评价为2020年，当前营业状态需复核 | F33: src_000082 | G33: 确认当前营业和实际入口
A36: 平台检索结论与限制
A37: 高德地图 | B37: 已直接复核多个公开地点页，可用于地址、坐标、POI ID交叉核验；部分地点页可见评价较早，不能据此证明当前仍营业。
A38: 携程/Trip.com/去哪儿 | B38: 可核对地址、营业时段、电话、近期点评；第三方平台信息可能滞后，且同一页面内用户游记地址可能与详情地址不同。
A39: 美团/大众点评 | B39: 本轮公开检索未对所有店铺取得可稳定访问的精确地址页面；部分页面会触发验证，不将无法访问的内容当作已核实。
A40: 抖音 | B40: 检索到开封美食相关公开视频，但未找到足以独立确认多数具体门店地址的官方定位证据；普通视频/评论只作为线索。
A41: 小红书 | B41: 公开网页检索没有取得可交叉确认本批大多数门店精确地址的稳定页面；不以搜索不到等同于商家不存在。
A42: 证据留存 | B42: 本轮来源表记录URL、访问时间和内容摘要；未保存全部网页截图或HTML快照，因此仍需按团队证据要求补存可合法保存的原始证据。
A43: 核验口径 | B43: 本工作簿没有把“页面存在”视为“商家当前营业”，也没有把“地址有内容”视为“地址已核实”；没有商家直接确认的记录不升级为verified。

Sheet 22_media_assets
A1: 媒体资产 media_assets
A2: 图片、视频、全景等一个原始文件一行。先登记文件与权限，再建立业务关联。
A3: media_id | B3: media_type | C3: content_role | D3: title | E3: description | F3: file_name | G3: file_path | H3: original_url | I3: source_page_url | J3: creator | K3: publisher | L3: published_at | M3: captured_at | N3: place_id | O3: capture_lng | P3: capture_lat | Q3: capture_crs | R3: file_availability | S3: mime_type | T3: file_size_bytes | U3: width_px | V3: height_px | W3: duration_seconds | X3: contains_identifiable_people | Y3: privacy_status | Z3: watermark_present | AA3: checksum_sha256 | AB3: derivative_of_media_id | AC3: rights_status | AD3: license_name | AE3: credit_line | AF3: usage_scope | AG3: source_id | AH3: validation_status | AI3: publication_status | AJ3: verified_at | AK3: reviewer | AL3: version | AM3: notes
A4: media_000001 | B4: image | C4: cover | D4: 园区俯瞰 | E4: 清明上河园园区俯瞰，含拂云阁、临水大殿、水心榭等园区建筑与水面。 | F4: 清明上河园_园区俯瞰_官网_20261022.jpg | G4: evidence/media/清明上河园/清明上河园_园区俯瞰_官网_20261022.jpg | H4: https://www.qingmings.com/images/index_q_02_2.jpg | I4: https://www.qingmings.com/ | K4: 清明上河园（中国开封清明上河园股份有限公司） | M4: 2026-10-22T21:04:33+08:00 | N4: pl_000001 | R4: stored | S4: image/jpeg | T4: 342877 | U4: 1408 | V4: 610 | X4: unknown | Y4: unknown | Z4: false | AA4: 3a9546a221db35d15fc0e753721fda16fd2dc236e99cabf0d6549fcba8154e7b | AC4: public_view_only | AE4: 清明上河园官网 | AF4: 仅校内课程演示，不公开传播、不商业使用 | AG4: src_000001 | AH4: candidate | AI4: restricted | AK4: 成员1 | AL4: 1 | AM4: 官网首页图集；远景有少量游客；仅校内演示。
A5: media_000002 | B5: image | C5: scene | D5: 夜景灯光 | E5: 清明上河园夜间水面与建筑灯光景观。 | F5: 清明上河园_夜景灯光_官网_20261022.jpg | G5: evidence/media/清明上河园/清明上河园_夜景灯光_官网_20261022.jpg | H5: https://www.qingmings.com/images/index_q_05.jpg | I5: https://www.qingmings.com/ | K5: 清明上河园（中国开封清明上河园股份有限公司） | M5: 2026-10-22T21:04:33+08:00 | N5: pl_000001 | R5: stored | S5: image/jpeg | T5: 215861 | U5: 850 | V5: 610 | X5: false | Y5: not_applicable | Z5: false | AA5: f6e1e42faf0e3b07c219c4a3c0fb14f009d9dc3df23e66d1994a0412556b8c2b | AC5: public_view_only | AE5: 清明上河园官网 | AF5: 仅校内课程演示，不公开传播、不商业使用 | AG5: src_000001 | AH5: candidate | AI5: restricted | AK5: 成员1 | AL5: 1 | AM5: 官网首页图集；未发现人物。
A6: media_000003 | B6: image | C6: scene | D6: 水心榭 | E6: 清明上河园水心榭与临水建筑。 | F6: 清明上河园_水心榭_官网_20261022.jpg | G6: evidence/media/清明上河园/清明上河园_水心榭_官网_20261022.jpg | H6: https://console.qmsyun.com/admin/uploadfile/website/04jianzu/2-1751956445503.jpg | I6: https://www.qingmings.com/q.php | K6: 清明上河园（中国开封清明上河园股份有限公司） | M6: 2026-10-22T21:04:33+08:00 | N6: pl_000001 | R6: stored | S6: image/jpeg | T6: 1046135 | U6: 4158 | V6: 2778 | X6: unknown | Y6: unknown | Z6: false | AA6: 73ec46bc72df7f32ab12e2204934019ae26c3b845d0e72c60aa71832f23406db | AC6: public_view_only | AE6: 清明上河园官网 | AF6: 仅校内课程演示，不公开传播、不商业使用 | AG6: src_000004 | AH6: candidate | AI6: restricted | AK6: 成员1 | AL6: 1 | AM6: 官网景区介绍图集；平台上有少量小人影；仅校内演示。
A7: media_000004 | B7: image | C7: scene | D7: 临水大殿 | E7: 临水大殿（宣和殿、宣德殿）与水面景观。 | F7: 清明上河园_临水大殿_官网_20261022.jpg | G7: evidence/media/清明上河园/清明上河园_临水大殿_官网_20261022.jpg | H7: https://console.qmsyun.com/admin/uploadfile/website/04jianzu/2-1751959032508.jpg | I7: https://www.qingmings.com/q.php | K7: 清明上河园（中国开封清明上河园股份有限公司） | M7: 2026-10-22T21:04:33+08:00 | N7: pl_000001 | R7: stored | S7: image/jpeg | T7: 1008990 | U7: 6804 | V7: 4536 | X7: false | Y7: not_applicable | Z7: false | AA7: 57dfb13fdc7867306b389803b3b3e7f9e23f1e7648d36b8171df6671ec46791d | AC7: public_view_only | AE7: 清明上河园官网 | AF7: 仅校内课程演示，不公开传播、不商业使用 | AG7: src_000004 | AH7: candidate | AI7: restricted | AK7: 成员1 | AL7: 1 | AM7: 官网景区介绍图集；未发现人物。
A8: media_000005 | B8: image | C8: scene | D8: 拂云阁 | E8: 拂云阁与水面游船，黄昏景观。 | F8: 清明上河园_拂云阁_官网_20261022.jpg | G8: evidence/media/清明上河园/清明上河园_拂云阁_官网_20261022.jpg | H8: https://console.qmsyun.com/admin/uploadfile/website/04jianzu/2-1751854439807.jpg | I8: https://www.qingmings.com/q.php | K8: 清明上河园（中国开封清明上河园股份有限公司） | M8: 2026-10-22T21:04:33+08:00 | N8: pl_000001 | R8: stored | S8: image/jpeg | T8: 1026850 | U8: 4948 | V8: 3299 | X8: unknown | Y8: unknown | Z8: false | AA8: 564d1ae99d84afd7d8fb148fdcdc9d18c16d71dd2fa3f31bb98bd6149865f382 | AC8: public_view_only | AE8: 清明上河园官网 | AF8: 仅校内课程演示，不公开传播、不商业使用 | AG8: src_000004 | AH8: candidate | AI8: restricted | AK8: 成员1 | AL8: 1 | AM8: 官网景区介绍图集；水面有船工，人物很小；仅校内演示。
A9: media_000006 | B9: image | C9: scene | D9: 双亭桥 | E9: 双亭桥与水面、游船。 | F9: 清明上河园_双亭桥_官网_20261022.jpg | G9: evidence/media/清明上河园/清明上河园_双亭桥_官网_20261022.jpg | H9: https://console.qmsyun.com/admin/uploadfile/website/04jianzu/2-1751935944732.jpg | I9: https://www.qingmings.com/q.php | K9: 清明上河园（中国开封清明上河园股份有限公司） | M9: 2026-10-22T21:04:33+08:00 | N9: pl_000001 | R9: stored | S9: image/jpeg | T9: 1018926 | U9: 5472 | V9: 3648 | X9: false | Y9: not_applicable | Z9: false | AA9: faf139f354339a686bf900d098dd1779c778eba2148196cd54c8777cce9c4f24 | AC9: public_view_only | AE9: 清明上河园官网 | AF9: 仅校内课程演示，不公开传播、不商业使用 | AG9: src_000004 | AH9: candidate | AI9: restricted | AK9: 成员1 | AL9: 1 | AM9: 官网景区介绍图集；未发现人物。
A10: media_000007 | B10: image | C10: scene | D10: 丹台宫 | E10: 丹台宫庭院与灯笼、雕像景观。 | F10: 清明上河园_丹台宫_官网_20261022.jpg | G10: evidence/media/清明上河园/清明上河园_丹台宫_官网_20261022.jpg | H10: https://console.qmsyun.com/admin/uploadfile/website/04jianzu/2-1689038339998.jpg | I10: https://www.qingmings.com/q.php | K10: 清明上河园（中国开封清明上河园股份有限公司） | M10: 2026-10-22T21:04:33+08:00 | N10: pl_000001 | R10: stored | S10: image/jpeg | T10: 269272 | U10: 768 | V10: 578 | X10: false | Y10: not_applicable | Z10: false | AA10: 5a73bdd1e231b9549c2e7c531e546802b0191c7d394c173eeb5b0ff985c29aeb | AC10: public_view_only | AE10: 清明上河园官网 | AF10: 仅校内课程演示，不公开传播、不商业使用 | AG10: src_000004 | AH10: candidate | AI10: restricted | AK10: 成员1 | AL10: 1 | AM10: 官网景区介绍图集；未发现人物。
A11: media_000008 | B11: image | C11: scene | D11: 虹桥 | E11: 虹桥及桥上人流，远景。 | F11: 清明上河园_虹桥_官网_20261022.jpg | G11: evidence/media/清明上河园/清明上河园_虹桥_官网_20261022.jpg | H11: https://console.qmsyun.com/admin/uploadfile/website/04jianzu/2-1751853680646.jpg | I11: https://www.qingmings.com/q.php | K11: 清明上河园（中国开封清明上河园股份有限公司） | M11: 2026-10-22T21:04:33+08:00 | N11: pl_000001 | R11: stored | S11: image/jpeg | T11: 1024713 | U11: 6000 | V11: 4000 | X11: true | Y11: required | Z11: false | AA11: 1e31e502a2aa010c1a74db04cb0c14bbf65ba4efc360d36c5d2d2d32b1d54c2c | AC11: public_view_only | AE11: 清明上河园官网 | AF11: 仅校内课程演示，不公开传播、不商业使用 | AG11: src_000004 | AH11: candidate | AI11: restricted | AK11: 成员1 | AL11: 1 | AM11: 官网景区介绍图集；桥上有大量游客，无主要人物；仅校内演示，公开使用前需处理。
A12: media_000009 | B12: video | C12: performance | D12: 包公迎宾（官方节目视频） | E12: 官方节目视频（页面内嵌，未下载）。 | F12: v_1393.mp4 | H12: https://console.qmsyun.com/admin/uploadfile/website/video/1393/v.mp4 | I12: https://www.qingmings.com/q_show.php | K12: 清明上河园（中国开封清明上河园股份有限公司） | M12: 2026-10-22T21:04:33+08:00 | N12: pl_000001 | R12: linked_only | S12: video/mp4 | X12: unknown | Y12: required | Z12: unknown | AC12: public_view_only | AE12: 清明上河园官网 | AF12: 仅校内课程演示，不公开传播、不商业使用 | AG12: src_000003 | AH12: candidate | AI12: restricted | AK12: 成员1 | AL12: 1 | AM12: 官方节目页内嵌视频；未下载，仅保留链接；仅校内演示。
A13: media_000010 | B13: video | C13: performance | D13: 大宋·东京保卫战（官方节目视频） | E13: 官方节目视频（页面内嵌，未下载）。 | F13: v_1423.mp4 | H13: https://console.qmsyun.com/admin/uploadfile/website/video/1423/v.mp4 | I13: https://www.qingmings.com/q_show.php | K13: 清明上河园（中国开封清明上河园股份有限公司） | M13: 2026-10-22T21:04:33+08:00 | N13: pl_000001 | R13: linked_only | S13: video/mp4 | X13: unknown | Y13: required | Z13: unknown | AC13: public_view_only | AE13: 清明上河园官网 | AF13: 仅校内课程演示，不公开传播、不商业使用 | AG13: src_000003 | AH13: candidate | AI13: restricted | AK13: 成员1 | AL13: 1 | AM13: 官方节目页内嵌视频；未下载，仅保留链接；仅校内演示。
A14: media_000011 | B14: image | C14: map_evidence | D14: 清园寻胜图（官方导览图） | E14: 清明上河园官方导览图，标注园区主要建筑、水系、道路、出入口与停车区域。 | F14: 清明上河园_官方导览图_20261022.jpg | G14: evidence/media/清明上河园/清明上河园_官方导览图_20261022.jpg | H14: http://www.qingmings.com/images/20191213baidubaike/2.jpg | I14: http://www.qingmings.com/2019baidubaoke.php | K14: 清明上河园（中国开封清明上河园股份有限公司） | M14: 2026-10-22T21:32:06+08:00 | N14: pl_000001 | R14: stored | S14: image/jpeg | T14: 173113 | U14: 700 | V14: 444 | X14: false | Y14: not_applicable | Z14: false | AA14: 49e4e46cddce665650fa55579c2eb9ac94e6f1e131330847f5db3fdcb375f7b3 | AC14: public_view_only | AE14: 清明上河园官网 | AF14: 仅校内课程演示，不公开传播、不商业使用 | AG14: src_000117 | AH14: candidate | AI14: restricted | AK14: 成员1 | AL14: 1 | AM14: 官网专题页图集；地图类素材，无人物；原图分辨率700×444，文字较小；如需高清建议向景区索取纸质《游园秘笈》。
A15: media_000012 | B15: image | C15: cover | D15: 夜景大门 | E15: 万岁山武侠城夜间入口区域，牌楼灯组与广场游客。 | F15: 万岁山_夜景大门_官网_20261022.jpg | G15: evidence/media/万岁山/万岁山_夜景大门_官网_20261022.jpg | H15: https://resource.dasongwuxiacheng.com/file-bucket/fca69d8e7c6340e8a7ff390a72a85396.jpg | I15: http://www.wansuishan.com.cn/website/pc/index.html | K15: 开封万岁山武侠城 | M15: 2026-10-22T21:43:43+08:00 | N15: pl_000002 | R15: stored | S15: image/jpeg | T15: 1007597 | U15: 2000 | V15: 1124 | X15: true | Y15: required | Z15: false | AA15: 74134f5adaa3abb91991cadbcead3f508d8a45791d51ed1c5bf5e298c31de14a | AC15: public_view_only | AE15: 万岁山武侠城官网 | AF15: 仅校内课程演示，不公开传播、不商业使用 | AG15: src_000010 | AH15: candidate | AI15: restricted | AK15: 成员1 | AL15: 1 | AM15: 官网首页轮播图；夜景宣传图，天空中的月亮和星点可能为后期合成；画面有游客，公开使用前需处理；仅校内演示。
A16: media_000013 | B16: image | C16: performance | D16: 打铁花 | E16: 《打铁花》夜间实景演出，艺人将铁水击打形成漫天火花。 | F16: 万岁山_打铁花_官网_20261022.jpg | G16: evidence/media/万岁山/万岁山_打铁花_官网_20261022.jpg | H16: https://resource.dasongwuxiacheng.com/file-bucket/b6d63de3a9784259a8bd073ce00c813d.jpg | I16: http://www.wansuishan.com.cn/website/pc/index.html | K16: 开封万岁山武侠城 | M16: 2026-10-22T21:43:43+08:00 | N16: pl_000002 | R16: stored | S16: image/jpeg | T16: 831567 | U16: 2000 | V16: 1333 | X16: true | Y16: required | Z16: false | AA16: 3df6fe280bee1d7e30c5450dbc9e4fac10db8027b92f77373bb95acb0a65e135 | AC16: public_view_only | AE16: 万岁山武侠城官网 | AF16: 仅校内课程演示，不公开传播、不商业使用 | AG16: src_000010 | AH16: candidate | AI16: restricted | AK16: 成员1 | AL16: 1 | AM16: 官网首页轮播图；演员面部可见，公开使用前需处理；仅校内演示。
A17: media_000014 | B17: image | C17: scene | D17: 仙侠奇境区夜景 | E17: 仙侠奇境区夜间鸟瞰，灯组、水面与园区建筑。 | F17: 万岁山_仙侠奇境区夜景_官网_20261022.png | G17: evidence/media/万岁山/万岁山_仙侠奇境区夜景_官网_20261022.png | H17: https://resource.dasongwuxiacheng.com/file-bucket/0e3cf66737e5411aa9c17e3f80619de1.png | I17: http://www.wansuishan.com.cn/website/pc/index.html | K17: 开封万岁山武侠城 | M17: 2026-10-22T21:43:43+08:00 | N17: pl_000002 | R17: stored | S17: image/png | T17: 1411266 | U17: 2000 | V17: 1124 | X17: unknown | Y17: unknown | Z17: false | AA17: c57c8614285fc782db102e7e8b3898928c94f1ebafd1b94c3995ac117c90bfc6 | AC17: public_view_only | AE17: 万岁山武侠城官网 | AF17: 仅校内课程演示，不公开传播、不商业使用 | AG17: src_000010 | AH17: candidate | AI17: restricted | AK17: 成员1 | AL17: 1 | AM17: 官网首页“每一处都别有洞天”栏目配图；夜景宣传图，星空可能为后期合成；画面远处有少量游客；仅校内演示。
A18: media_000015 | B18: image | C18: scene | D18: 武侠影视街区 | E18: 武侠影视街区实景演出《城北枪声》，演员与围观游客。 | F18: 万岁山_武侠影视街区_官网_20261022.jpg | G18: evidence/media/万岁山/万岁山_武侠影视街区_官网_20261022.jpg | H18: https://resource.dasongwuxiacheng.com/file-bucket/716b2e0510a34a31989746ef78c14d21.jpg | I18: http://www.wansuishan.com.cn/website/pc/index.html | K18: 开封万岁山武侠城 | M18: 2026-10-22T21:43:43+08:00 | N18: pl_000002 | R18: stored | S18: image/jpeg | T18: 8634706 | U18: 5472 | V18: 3648 | X18: true | Y18: required | Z18: false | AA18: c44600c7413c7b3cfdc72536b7607d2f9ccbb160f6a1084f1b10ca46310d397a | AC18: public_view_only | AE18: 万岁山武侠城官网 | AF18: 仅校内课程演示，不公开传播、不商业使用 | AG18: src_000010 | AH18: candidate | AI18: restricted | AK18: 成员1 | AL18: 1 | AM18: 官网首页“每一处都别有洞天”栏目配图；画面有演员和游客，公开使用前需处理。
A19: media_000016 | B19: image | C19: scene | D19: 十里洋场区夜景 | E19: 十里洋场区夜间《百乐门》演出与霓虹街景。 | F19: 万岁山_十里洋场区夜景_官网_20261022.png | G19: evidence/media/万岁山/万岁山_十里洋场区夜景_官网_20261022.png | H19: https://resource.dasongwuxiacheng.com/file-bucket/5e34e2fd56334aad8952050309b1df8c.png | I19: http://www.wansuishan.com.cn/website/pc/index.html | K19: 开封万岁山武侠城 | M19: 2026-10-22T21:43:43+08:00 | N19: pl_000002 | R19: stored | S19: image/png | T19: 1133551 | U19: 2000 | V19: 1123 | X19: true | Y19: required | Z19: false | AA19: d14e7d3847fc37b10fa9b4caf72aba96448d4b7d1d610d8097f45caa158d4ab5 | AC19: public_view_only | AE19: 万岁山武侠城官网 | AF19: 仅校内课程演示，不公开传播、不商业使用 | AG19: src_000010 | AH19: candidate | AI19: restricted | AK19: 成员1 | AL19: 1 | AM19: 官网首页“每一处都别有洞天”栏目配图；画面有演员和游客，公开使用前需处理。
A20: media_000017 | B20: image | C20: scene | D20: 江湖狂欢艺术区 | E20: 江湖狂欢艺术区夜间发光仿古建筑。 | F20: 万岁山_江湖狂欢艺术区_官网_20261022.jpg | G20: evidence/media/万岁山/万岁山_江湖狂欢艺术区_官网_20261022.jpg | H20: https://resource.dasongwuxiacheng.com/file-bucket/64f08200ed4649bb8347a798100e3c33.jpg | I20: http://www.wansuishan.com.cn/website/pc/index.html | K20: 开封万岁山武侠城 | M20: 2026-10-22T21:43:43+08:00 | N20: pl_000002 | R20: stored | S20: image/jpeg | T20: 942011 | U20: 2000 | V20: 1320 | X20: false | Y20: not_applicable | Z20: false | AA20: 3aedc6ef028152bcab824cc8fe16a6242a4d6a434a69e34f06125bb9fd269a98 | AC20: public_view_only | AE20: 万岁山武侠城官网 | AF20: 仅校内课程演示，不公开传播、不商业使用 | AG20: src_000010 | AH20: candidate | AI20: restricted | AK20: 成员1 | AL20: 1 | AM20: 官网首页轮播图；夜景宣传图，星点可能为后期合成；未发现人物；仅校内演示。
A21: media_000018 | B21: image | C21: performance | D21: 三打祝家庄 | E21: 《三打祝家庄》实景马战演出，看台与演区。 | F21: 万岁山_三打祝家庄_官网_20261022.jpg | G21: evidence/media/万岁山/万岁山_三打祝家庄_官网_20261022.jpg | H21: https://resource.dasongwuxiacheng.com/file-bucket/e7c92d5189d34bbab43cfe8259f789bc.jpg | I21: http://www.wansuishan.com.cn/website/pc/index.html | K21: 开封万岁山武侠城 | M21: 2026-10-22T21:43:43+08:00 | N21: pl_000002 | R21: stored | S21: image/jpeg | T21: 812006 | U21: 1700 | V21: 956 | X21: true | Y21: required | Z21: false | AA21: 04086227c1d86f42283955e3a8e5aeb2c7b9fc347cd119c3f91ba7a53c19fe9e | AC21: public_view_only | AE21: 万岁山武侠城官网 | AF21: 仅校内课程演示，不公开传播、不商业使用 | AG21: src_000010 | AH21: candidate | AI21: restricted | AK21: 成员1 | AL21: 1 | AM21: 官网首页轮播图；画面有大量观众，公开使用前需处理；仅校内演示。
A22: media_000019 | B22: image | C22: scene | D22: 山水田园区 | E22: 山水田园区入口牌楼与生肖雕塑。 | F22: 万岁山_山水田园区_官网_20261022.png | G22: evidence/media/万岁山/万岁山_山水田园区_官网_20261022.png | H22: https://resource.dasongwuxiacheng.com/file-bucket/d5fb934a28b64d7d95a54d33bae4ff44.png | I22: http://www.wansuishan.com.cn/website/pc/index.html | K22: 开封万岁山武侠城 | M22: 2026-10-22T21:43:43+08:00 | N22: pl_000002 | R22: stored | S22: image/png | T22: 1581961 | U22: 2000 | V22: 1333 | X22: true | Y22: required | Z22: false | AA22: 5a39de3dda7756f068dc0beceac261c789c4df7666124f807636df7cc98a8b81 | AC22: public_view_only | AE22: 万岁山武侠城官网 | AF22: 仅校内课程演示，不公开传播、不商业使用 | AG22: src_000010 | AH22: candidate | AI22: restricted | AK22: 成员1 | AL22: 1 | AM22: 官网首页“每一处都别有洞天”栏目配图；画面有游客背影，公开使用前需处理。
A23: media_000020 | B23: image | C23: map_evidence | D23: 万岁山导览图（官方地图） | E23: 官方导览图，标注西大门、南大门、中门、东大门、水浒区入口、仙侠区入口、江湖艺术区入口及演出场地。 | F23: 万岁山_官方导览图_20261022.png | G23: evidence/media/万岁山/万岁山_官方导览图_20261022.png | H23: https://resource.dasongwuxiacheng.com/file-bucket/4a9824c58c4a4a969e1fb8858792e595.png | I23: http://www.wansuishan.com.cn/website/pc/index.html#/service | K23: 开封万岁山武侠城 | M23: 2026-10-22T21:43:43+08:00 | N23: pl_000002 | R23: stored | S23: image/png | T23: 622109 | U23: 2000 | V23: 737 | X23: false | Y23: not_applicable | Z23: false | AA23: eab948605a741a5a4676a1fd09b1b324c769be355e0f771693d771f15db6e31a | AC23: public_view_only | AE23: 万岁山武侠城官网 | AF23: 仅校内课程演示，不公开传播、不商业使用 | AG23: src_000119 | AH23: candidate | AI23: restricted | AK23: 成员1 | AL23: 1 | AM23: 官网侠客服务→智慧地图；地图类素材，无人物；原图2000×737。
A24: media_000021 | B24: video | C24: other | D24: 人人都说自己是万岁山（官方宣传视频） | E24: 官网影像中心视频列表中的官方宣传视频。 | F24: 人人都说自己是万岁山.mp4 | H24: https://resource.dasongwuxiacheng.com/file-bucket/7df31e3cfa9a4f5ea4f3b496e8187bdc.mp4 | I24: http://www.wansuishan.com.cn/website/pc/index.html#/imgCenter | K24: 开封万岁山武侠城 | M24: 2026-10-22T21:43:43+08:00 | N24: pl_000002 | R24: linked_only | S24: video/mp4 | T24: 116119277 | X24: unknown | Y24: required | Z24: unknown | AC24: public_view_only | AE24: 万岁山武侠城官网 | AF24: 仅校内课程演示，不公开传播、不商业使用 | AG24: src_000118 | AH24: candidate | AI24: restricted | AK24: 成员1 | AL24: 1 | AM24: 官网视频中心；未下载，仅保留链接；文件约110.7MB；仅校内演示。
A25: media_000022 | B25: video | C25: other | D25: 万岁山武侠城（官方宣传视频） | E25: 官网影像中心视频列表中的官方宣传视频。 | F25: 万岁山武侠城.mp4 | H25: https://resource.dasongwuxiacheng.com/file-bucket/d62f98ad67c84f6d8d669aa52c56c4a2.mp4 | I25: http://www.wansuishan.com.cn/website/pc/index.html#/imgCenter | K25: 开封万岁山武侠城 | M25: 2026-10-22T21:43:43+08:00 | N25: pl_000002 | R25: linked_only | S25: video/mp4 | T25: 221310286 | X25: unknown | Y25: required | Z25: unknown | AC25: public_view_only | AE25: 万岁山武侠城官网 | AF25: 仅校内课程演示，不公开传播、不商业使用 | AG25: src_000118 | AH25: candidate | AI25: restricted | AK25: 成员1 | AL25: 1 | AM25: 官网视频中心；未下载，仅保留链接；文件约211.1MB；仅校内演示。
A26: media_000023 | B26: image | C26: cover | D26: 府门全景 | E26: 开封府府门及门前广场全景，含石狮、城墙与入口。 | F26: 开封府_府门全景_官网_20261022.png | G26: evidence/media/开封府/开封府_府门全景_官网_20261022.png | H26: http://www.kaifengfu.cn/uploads/image/20261001/17908231631535962.png | I26: http://www.kaifengfu.cn/news/view.asp?id=485 | K26: 开封府（开封“开封府”旅游开发有限公司） | M26: 2026-10-22T21:58:17+08:00 | N26: pl_000003 | R26: stored | S26: image/png | T26: 5473389 | U26: 4096 | V26: 1024 | X26: true | Y26: required | Z26: false | AA26: 5f8e642cdb7d8574add8b071e832ce18182233504b1ea413f9ea902e53205ba9 | AC26: public_view_only | AE26: 开封府官网 | AF26: 仅校内课程演示，不公开传播、不商业使用 | AG26: src_000122 | AH26: candidate | AI26: restricted | AK26: 成员1 | AL26: 1 | AM26: 官网国庆新闻图；广场和城墙上有人群，公开使用前需处理；仅校内演示。
A27: media_000024 | B27: image | C27: scene | D27: 府门夜景光影 | E27: 开封府府门夜间光影秀投影。 | F27: 开封府_府门夜景光影_官网_20261022.jpg | G27: evidence/media/开封府/开封府_府门夜景光影_官网_20261022.jpg | H27: http://www.kaifengfu.cn/uploads/image/20261001/17908230846621534.jpg | I27: http://www.kaifengfu.cn/news/view.asp?id=485 | K27: 开封府（开封“开封府”旅游开发有限公司） | M27: 2026-10-22T21:58:17+08:00 | N27: pl_000003 | R27: stored | S27: image/jpeg | T27: 258476 | U27: 1600 | V27: 889 | X27: false | Y27: not_applicable | Z27: false | AA27: ac09337b6526ff0042bd7aedaabaecbd8c9bc2de731ac65a185314f2dc9a8dbe | AC27: public_view_only | AE27: 开封府官网 | AF27: 仅校内课程演示，不公开传播、不商业使用 | AG27: src_000122 | AH27: candidate | AI27: restricted | AK27: 成员1 | AL27: 1 | AM27: 官网国庆新闻图；未发现人物；仅校内演示。
A28: media_000025 | B28: image | C28: performance | D28: 盘鼓迎宾 | E28: 开封府府门广场盘鼓迎宾演出。 | F28: 开封府_盘鼓迎宾_官网_20261022.jpg | G28: evidence/media/开封府/开封府_盘鼓迎宾_官网_20261022.jpg | H28: http://www.kaifengfu.cn/uploads/image/20261001/17908227489930479.jpg | I28: http://www.kaifengfu.cn/news/view.asp?id=485 | K28: 开封府（开封“开封府”旅游开发有限公司） | M28: 2026-10-22T21:58:17+08:00 | N28: pl_000003 | R28: stored | S28: image/jpeg | T28: 515220 | U28: 1600 | V28: 1200 | X28: true | Y28: required | Z28: false | AA28: 25d9e6af278600de86871152edb0900a9158817cd3357d7f8cfeb117522dce19 | AC28: public_view_only | AE28: 开封府官网 | AF28: 仅校内课程演示，不公开传播、不商业使用 | AG28: src_000122 | AH28: candidate | AI28: restricted | AK28: 成员1 | AL28: 1 | AM28: 官网国庆新闻图；演员和游客面部可见，公开使用前需处理；仅校内演示。
A29: media_000026 | B29: image | C29: scene | D29: 大堂内景 | E29: 开封府正厅（大堂）内景，悬“正大光明”匾，设府尹公案。 | F29: 开封府_大堂内景_官网_20261022.jpg | G29: evidence/media/开封府/开封府_大堂内景_官网_20261022.jpg | H29: http://www.kaifengfu.cn/kaifengfu/g17/pano_f.jpg | I29: http://www.kaifengfu.cn/kaifengfu | K29: 开封府（开封“开封府”旅游开发有限公司） | M29: 2026-10-22T21:58:17+08:00 | N29: pl_000003 | R29: stored | S29: image/jpeg | T29: 656696 | U29: 1500 | V29: 1500 | X29: false | Y29: not_applicable | Z29: false | AA29: ac90c835392ddca111d8f953ea952d6d74a4bca1f69183b8d9fd816355f9c1f9 | AC29: public_view_only | AE29: 开封府官网 | AF29: 仅校内课程演示，不公开传播、不商业使用 | AG29: src_000123 | AH29: candidate | AI29: restricted | AK29: 成员1 | AL29: 1 | AM29: 官网全景游园“正厅（内）”场景；未发现人物；仅校内演示。
A30: media_000027 | B30: image | C30: scene | D30: 梅花堂 | E30: 梅花堂外观，堂前立青铜鼎。 | F30: 开封府_梅花堂_官网_20261022.jpg | G30: evidence/media/开封府/开封府_梅花堂_官网_20261022.jpg | H30: http://www.kaifengfu.cn/kaifengfu/g8/pano_f.jpg | I30: http://www.kaifengfu.cn/kaifengfu | K30: 开封府（开封“开封府”旅游开发有限公司） | M30: 2026-10-22T21:58:17+08:00 | N30: pl_000003 | R30: stored | S30: image/jpeg | T30: 459327 | U30: 1500 | V30: 1500 | X30: false | Y30: not_applicable | Z30: false | AA30: f268e851e245960011b5c5f1690b267cef1a27bf9f75d2cab63e1f92602352a8 | AC30: public_view_only | AE30: 开封府官网 | AF30: 仅校内课程演示，不公开传播、不商业使用 | AG30: src_000123 | AH30: candidate | AI30: restricted | AK30: 成员1 | AL30: 1 | AM30: 官网全景游园“梅花堂”场景；未发现人物；仅校内演示。
A31: media_000028 | B31: image | C31: scene | D31: 清心楼 | E31: 清心楼外观，楼内设包公铜像与历任府尹事迹展。 | F31: 开封府_清心楼_官网_20261022.jpg | G31: evidence/media/开封府/开封府_清心楼_官网_20261022.jpg | H31: http://www.kaifengfu.cn/kaifengfu/g11/pano_f.jpg | I31: http://www.kaifengfu.cn/kaifengfu | K31: 开封府（开封“开封府”旅游开发有限公司） | M31: 2026-10-22T21:58:17+08:00 | N31: pl_000003 | R31: stored | S31: image/jpeg | T31: 548997 | U31: 1500 | V31: 1500 | X31: false | Y31: not_applicable | Z31: false | AA31: 7919c4abc59bf7d9c8339d0584e1aa1121568619084d8ab01cea0be4ab221be5 | AC31: public_view_only | AE31: 开封府官网 | AF31: 仅校内课程演示，不公开传播、不商业使用 | AG31: src_000123 | AH31: candidate | AI31: restricted | AK31: 成员1 | AL31: 1 | AM31: 官网全景游园“清心楼（外）”场景；未发现人物；仅校内演示。
A32: media_000029 | B32: image | C32: scene | D32: 明礼院拱奎楼 | E32: 明礼院拱奎楼，教育科举文化区主体建筑。 | F32: 开封府_明礼院拱奎楼_官网_20261022.jpg | G32: evidence/media/开封府/开封府_明礼院拱奎楼_官网_20261022.jpg | H32: http://www.kaifengfu.cn/kaifengfu/g10/pano_f.jpg | I32: http://www.kaifengfu.cn/kaifengfu | K32: 开封府（开封“开封府”旅游开发有限公司） | M32: 2026-10-22T21:58:17+08:00 | N32: pl_000003 | R32: stored | S32: image/jpeg | T32: 432658 | U32: 1500 | V32: 1500 | X32: false | Y32: not_applicable | Z32: false | AA32: 68308b98826236844f035c590080b3e4f2006970322737c2761c67da39a83ec5 | AC32: public_view_only | AE32: 开封府官网 | AF32: 仅校内课程演示，不公开传播、不商业使用 | AG32: src_000123 | AH32: candidate | AI32: restricted | AK32: 成员1 | AL32: 1 | AM32: 官网全景游园“明礼院”场景；未发现人物；仅校内演示。
A33: media_000030 | B33: image | C33: scene | D33: 三清殿 | E33: 天庆观三清殿及殿前太极八卦图铺地。 | F33: 开封府_三清殿_官网_20261022.jpg | G33: evidence/media/开封府/开封府_三清殿_官网_20261022.jpg | H33: http://www.kaifengfu.cn/kaifengfu/g6/pano_f.jpg | I33: http://www.kaifengfu.cn/kaifengfu | K33: 开封府（开封“开封府”旅游开发有限公司） | M33: 2026-10-22T21:58:17+08:00 | N33: pl_000003 | R33: stored | S33: image/jpeg | T33: 627946 | U33: 1500 | V33: 1500 | X33: false | Y33: not_applicable | Z33: false | AA33: a768738d82c45962709fdeefdda71b89b2370544d9e8e3d6bd4cd9b1ed81af15 | AC33: public_view_only | AE33: 开封府官网 | AF33: 仅校内课程演示，不公开传播、不商业使用 | AG33: src_000123 | AH33: candidate | AI33: restricted | AK33: 成员1 | AL33: 1 | AM33: 官网全景游园“三清殿”场景；未发现人物；仅校内演示。
A34: media_000031 | B34: image | C34: map_evidence | D34: 开封府景区导览图（官方地图） | E34: 官方导览图，标注府门、仪门、大堂、梅花堂、清心楼、明礼院、天庆观、潜龙宫等建筑与出入口。 | F34: 开封府_官方导览图_20261022.jpg | G34: evidence/media/开封府/开封府_官方导览图_20261022.jpg | H34: http://www.kaifengfu.cn/uploads/image/20240826/17246388279793699.jpg | I34: http://www.kaifengfu.cn/daolan | K34: 开封府（开封“开封府”旅游开发有限公司） | M34: 2026-10-22T21:58:17+08:00 | N34: pl_000003 | R34: stored | S34: image/jpeg | T34: 367992 | U34: 1646 | V34: 1280 | X34: false | Y34: not_applicable | Z34: false | AA34: 056443f0cc629ba338cceaf5ae3bf0c7b40985f448cf867cc96b517dbca20868 | AC34: public_view_only | AE34: 开封府官网 | AF34: 仅校内课程演示，不公开传播、不商业使用 | AG34: src_000121 | AH34: candidate | AI34: restricted | AK34: 成员1 | AL34: 1 | AM34: 官网在线导览页；地图类素材，无人物；原图1646×1280。
A35: media_000032 | B35: image | C35: map_evidence | D35: 清明上河园小程序导览图（北半部） | E35: 官方小程序导览图北半部，标注演出点位、道路与园区建筑。 | F35: 清明上河园_官方小程序导览图_20261022_1.png | G35: evidence/media/清明上河园/清明上河园_官方小程序导览图_20261022_1.png | K35: 清明上河园（中国开封清明上河园股份有限公司） | M35: 2026-10-22T22:04:57+08:00 | N35: pl_000001 | R35: stored | S35: image/png | T35: 1866047 | U35: 786 | V35: 1704 | X35: false | Y35: not_applicable | Z35: false | AA35: 22e9a7257f17afa73829a0fce38733ee5c95cbaa1a11f60225cfcced5676c1e4 | AC35: public_view_only | AE35: 清明上河园官方小程序 | AF35: 仅校内课程演示，不公开传播、不商业使用 | AG35: src_000124 | AH35: candidate | AI35: restricted | AK35: 成员1 | AL35: 1 | AM35: 用户提供的官方小程序截图；含演出点位标记；作为已有官方导览图的补充。
A36: media_000033 | B36: image | C36: map_evidence | D36: 清明上河园小程序导览图（南半部） | E36: 官方小程序导览图南半部，标注演出点位、道路与园区建筑。 | F36: 清明上河园_官方小程序导览图_20261022_2.png | G36: evidence/media/清明上河园/清明上河园_官方小程序导览图_20261022_2.png | K36: 清明上河园（中国开封清明上河园股份有限公司） | M36: 2026-10-22T22:04:57+08:00 | N36: pl_000001 | R36: stored | S36: image/png | T36: 1871290 | U36: 786 | V36: 1704 | X36: false | Y36: not_applicable | Z36: false | AA36: e502f7813ef3ff70a1607c6e15fa79682104f21ee465aef4571dfff172911a4a | AC36: public_view_only | AE36: 清明上河园官方小程序 | AF36: 仅校内课程演示，不公开传播、不商业使用 | AG36: src_000124 | AH36: candidate | AI36: restricted | AK36: 成员1 | AL36: 1 | AM36: 用户提供的官方小程序截图；含演出点位标记；与北半部截图配套。
A37: media_000034 | B37: video | C37: other | D37: 清明上河园全攻略（官方抖音宣传视频） | E37: 清明上河园官方抖音号发布的综合攻略宣传视频。 | F37: douyin_7283343905708330259.mp4 | H37: https://v.douyin.com/GSyFQAMOHwc/ | I37: https://v.douyin.com/GSyFQAMOHwc/ | K37: 清明上河园（中国开封清明上河园股份有限公司） | M37: 2026-10-22T22:04:57+08:00 | N37: pl_000001 | R37: linked_only | S37: video/mp4 | X37: unknown | Y37: required | Z37: unknown | AC37: public_view_only | AE37: 清明上河园（中国开封清明上河园股份有限公司）官方抖音 | AF37: 仅校内课程演示，不公开传播、不商业使用 | AG37: src_000125 | AH37: candidate | AI37: restricted | AK37: 成员1 | AL37: 1 | AM37: 官方抖音宣传视频；抖音反爬，未下载；文件名按视频ID生成，非原始文件名；仅校内演示。
A38: media_000035 | B38: video | C38: other | D38: 一步一江湖 一幕一传奇（官方抖音宣传视频） | E38: 万岁山武侠城官方抖音号发布的宣传视频。 | F38: douyin_7557286795680009499.mp4 | H38: https://v.douyin.com/PbkzPZFzk5Y/ | I38: https://v.douyin.com/PbkzPZFzk5Y/ | K38: 开封万岁山武侠城 | M38: 2026-10-22T22:04:57+08:00 | N38: pl_000002 | R38: linked_only | S38: video/mp4 | X38: unknown | Y38: required | Z38: unknown | AC38: public_view_only | AE38: 开封万岁山武侠城官方抖音 | AF38: 仅校内课程演示，不公开传播、不商业使用 | AG38: src_000126 | AH38: candidate | AI38: restricted | AK38: 成员1 | AL38: 1 | AM38: 官网已有2条宣传视频，此条为官方抖音补充；抖音反爬，未下载；文件名按视频ID生成；仅校内演示。
A39: media_000036 | B39: image | C39: cover | D39: 龙亭大殿 | E39: 龙亭大殿外观，高台殿式建筑，黄琉璃瓦覆顶，前有蟠龙御道与72级台阶。 | F39: 龙亭_龙亭大殿_官网_20261022.jpg | G39: evidence/media/龙亭/龙亭_龙亭大殿_官网_20261022.jpg | H39: http://29714201.s21i.faiusr.com/2/ABUIABACGAAg-piulwYo0KHO_AEwgAg4qwU.jpg | I39: http://www.kfltjq.com/sys-nd/7.html | K39: 开封市龙亭景区 | M39: 2026-10-22T22:05:38+08:00 | N39: pl_000004 | R39: stored | S39: image/jpeg | T39: 535827 | U39: 1024 | V39: 683 | X39: true | Y39: required | Z39: false | AA39: 34da87fbaf89760632a436566aab2ea58e1bcc7aac1401b3ba9ec0fa390b292d | AC39: public_view_only | AE39: 开封市龙亭景区官网 | AF39: 仅校内课程演示，不公开传播、不商业使用 | AG39: src_000127 | AH39: candidate | AI39: restricted | AK39: 成员1 | AL39: 1 | AM39: 官网龙亭大殿页配图；台阶和广场有少量游客，公开使用前需处理；仅校内演示。
A40: media_000037 | B40: image | C40: scene | D40: 嵩呼 | E40: 嵩呼牌坊，黄琉璃瓦顶、彩绘斗拱，悬挂红灯笼。 | F40: 龙亭_嵩呼_官网_20261022.jpg | G40: evidence/media/龙亭/龙亭_嵩呼_官网_20261022.jpg | H40: http://29714201.s21i.faiusr.com/2/ABUIABACGAAgga32wwYo9ozlyQMw8QQ41QM.jpg | I40: http://www.kfltjq.com/sys-nd/12.html | K40: 开封市龙亭景区 | M40: 2026-10-22T22:05:38+08:00 | N40: pl_000004 | R40: stored | S40: image/jpeg | T40: 420460 | U40: 625 | V40: 469 | X40: false | Y40: not_applicable | Z40: false | AA40: 5a1518f55c4307f4d170e87a4b1a10cc2173bb4276e28fa916abf0676e59074b | AC40: public_view_only | AE40: 开封市龙亭景区官网 | AF40: 仅校内课程演示，不公开传播、不商业使用 | AG40: src_000128 | AH40: candidate | AI40: restricted | AK40: 成员1 | AL40: 1 | AM40: 官网嵩呼页配图；未发现人物；仅校内演示。
A41: media_000038 | B41: image | C41: scene | D41: 潘杨二湖 | E41: 潘杨二湖与龙亭中轴线鸟瞰，东为潘家湖、西为杨家湖。 | F41: 龙亭_潘杨二湖_官网_20261022.jpg | G41: evidence/media/龙亭/龙亭_潘杨二湖_官网_20261022.jpg | H41: http://29714201.s21i.faiusr.com/2/ABUIABACGAAg-6v2wwYonIr8jwUw8QQ4twM.jpg | I41: http://www.kfltjq.com/sys-nd/11.html | K41: 开封市龙亭景区 | M41: 2026-10-22T22:05:38+08:00 | N41: pl_000004 | R41: stored | S41: image/jpeg | T41: 379459 | U41: 625 | V41: 439 | X41: unknown | Y41: unknown | Z41: false | AA41: 0e0f89fe7338665b98ddb52f413a4bce5ef367c2af6bb4c23bf55cc70f4e5e61 | AC41: public_view_only | AE41: 开封市龙亭景区官网 | AF41: 仅校内课程演示，不公开传播、不商业使用 | AG41: src_000129 | AH41: candidate | AI41: restricted | AK41: 成员1 | AL41: 1 | AM41: 官网潘杨二湖页配图；远景有少量游客；仅校内演示。
A42: media_000039 | B42: image | C42: scene | D42: 照壁 | E42: 照壁（萧墙）与圆形拱门，前立石碑。 | F42: 龙亭_照壁_官网_20261022.jpg | G42: evidence/media/龙亭/龙亭_照壁_官网_20261022.jpg | H42: http://29714201.s21i.faiusr.com/2/ABUIABACGAAgy5uulwYolY-C2wMwgAg4qwU.jpg | I42: http://www.kfltjq.com/sys-nd/10.html | K42: 开封市龙亭景区 | M42: 2026-10-22T22:05:38+08:00 | N42: pl_000004 | R42: stored | S42: image/jpeg | T42: 559749 | U42: 1024 | V42: 683 | X42: true | Y42: required | Z42: false | AA42: ab6390aa461c871aa32e4a5d8e0ab814098dfa826f2c1fc37c7cf486e57926e5 | AC42: public_view_only | AE42: 开封市龙亭景区官网 | AF42: 仅校内课程演示，不公开传播、不商业使用 | AG42: src_000130 | AH42: candidate | AI42: restricted | AK42: 成员1 | AL42: 1 | AM42: 官网照壁页配图；门洞附近有游客，公开使用前需处理；仅校内演示。
A43: media_000040 | B43: image | C43: scene | D43: 朝门 | E43: 朝门与门前石狮，冬季雪景。 | F43: 龙亭_朝门_官网_20261022.jpg | G43: evidence/media/龙亭/龙亭_朝门_官网_20261022.jpg | H43: http://29714201.s21i.faiusr.com/2/ABUIABACGAAglZqulwYohsaQ5QYwgAg4gAY.jpg | I43: http://www.kfltjq.com/sys-nd/9.html | K43: 开封市龙亭景区 | M43: 2026-10-22T22:05:38+08:00 | N43: pl_000004 | R43: stored | S43: image/jpeg | T43: 653079 | U43: 1024 | V43: 768 | X43: true | Y43: required | Z43: false | AA43: 91a92fe063214341eb079aadc80883d0085e241e49631f8d5613778f254cb5d7 | AC43: public_view_only | AE43: 开封市龙亭景区官网 | AF43: 仅校内课程演示，不公开传播、不商业使用 | AG43: src_000131 | AH43: candidate | AI43: restricted | AK43: 成员1 | AL43: 1 | AM43: 官网朝门页配图；画面有游客背影，公开使用前需处理；仅校内演示。
A44: media_000041 | B44: image | C44: scene | D44: 凝芳苑雪景 | E44: 凝芳苑门楼雪景，门前一对石狮。 | F44: 龙亭_凝芳苑雪景_官网_20261022.jpg | G44: evidence/media/龙亭/龙亭_凝芳苑雪景_官网_20261022.jpg | H44: http://29714201.s21i.faiusr.com/2/ABUIABACGAAg1pmulwYogO6EwAUwgAg4gAY.jpg | I44: http://www.kfltjq.com/sys-nd/8.html | K44: 开封市龙亭景区 | M44: 2026-10-22T22:05:38+08:00 | N44: pl_000004 | R44: stored | S44: image/jpeg | T44: 760194 | U44: 1024 | V44: 768 | X44: false | Y44: not_applicable | Z44: false | AA44: 08ee5b29f2046814665b502eac9931d32ee4ad3e7d7158026ea83e0f595845ca | AC44: public_view_only | AE44: 开封市龙亭景区官网 | AF44: 仅校内课程演示，不公开传播、不商业使用 | AG44: src_000132 | AH44: candidate | AI44: restricted | AK44: 成员1 | AL44: 1 | AM44: 官网凝芳苑页配图；未发现人物；仅校内演示。
A45: media_000042 | B45: image | C45: scene | D45: 龙亭大殿日落 | E45: 龙亭大殿与潘杨二湖日落鸟瞰。 | F45: 龙亭_龙亭大殿日落_官网_20261022.jpg | G45: evidence/media/龙亭/龙亭_龙亭大殿日落_官网_20261022.jpg | H45: http://29714201.s21i.faiusr.com/2/ABUIABACGAAg-6r2wwYooPvUSDDxBDihAw.jpg | I45: http://www.kfltjq.com/sys-nd/7.html | K45: 开封市龙亭景区 | M45: 2026-10-22T22:05:38+08:00 | N45: pl_000004 | R45: stored | S45: image/jpeg | T45: 330349 | U45: 625 | V45: 417 | X45: unknown | Y45: unknown | Z45: false | AA45: b75b429b762f4964a3d93d972365742e27c47e4865f84db5eb5fc727c28367ba | AC45: public_view_only | AE45: 开封市龙亭景区官网 | AF45: 仅校内课程演示，不公开传播、不商业使用 | AG45: src_000127 | AH45: candidate | AI45: restricted | AK45: 成员1 | AL45: 1 | AM45: 官网龙亭大殿页配图；画面有大量小尺寸游客，公开使用前需确认；仅校内演示。
A46: media_000043 | B46: image | C46: map_evidence | D46: 龙亭景区导览图（官方地图） | E46: 官方手绘导览图，标注南门/北门入口、龙亭大殿、照壁、朝门、嵩呼、潘杨二湖、玉带桥、梅园、凝芳苑等建筑与水系。 | F46: 龙亭_官方导览图_20261022.jpg | G46: evidence/media/龙亭/龙亭_官方导览图_20261022.jpg | H46: http://29714201.s21i.faiusr.com/2/ABUIABACGAAg6efquQYoyLrXhgQw-hg47hE.jpg | I46: http://www.kfltjq.com/sys-nd/16.html | K46: 开封市龙亭景区 | M46: 2026-10-22T22:05:38+08:00 | N46: pl_000004 | R46: stored | S46: image/jpeg | T46: 1236476 | U46: 3198 | V46: 2286 | X46: false | Y46: not_applicable | Z46: false | AA46: 0aeb35ced32a0d6cf07d80d42f99f43ad54eae02f33d873545cd89e07074dad3 | AC46: public_view_only | AE46: 开封市龙亭景区官网 | AF46: 仅校内课程演示，不公开传播、不商业使用 | AG46: src_000018 | AH46: candidate | AI46: restricted | AK46: 成员1 | AL46: 1 | AM46: 官网游园指南页配图；地图类素材，无人物；原图3198×2286。
A47: media_000044 | B47: video | C47: other | D47: 雨落红墙，古韵更浓（官方抖音宣传视频） | E47: 开封府官方抖音号发布的红墙古建宣传视频。 | F47: douyin_7673057975774350634.mp4 | H47: https://v.douyin.com/S8N4b7oze6E/ | I47: https://v.douyin.com/S8N4b7oze6E/ | K47: 开封府（开封“开封府”旅游开发有限公司） | M47: 2026-10-22T22:26:09+08:00 | N47: pl_000003 | R47: linked_only | S47: video/mp4 | X47: unknown | Y47: required | Z47: unknown | AC47: public_view_only | AE47: 开封府官方抖音 | AF47: 仅校内课程演示，不公开传播、不商业使用 | AG47: src_000133 | AH47: candidate | AI47: restricted | AK47: 成员1 | AL47: 1 | AM47: 官方抖音宣传视频；抖音反爬，未下载；文件名按视频ID生成，非原始文件名；仅校内演示。
A48: media_000045 | B48: video | C48: other | D48: 千年铁塔，铸就千年古都（官方抖音宣传视频） | E48: 开封文旅官方抖音号发布的铁塔宣传视频。 | F48: douyin_7444896986681101609.mp4 | H48: https://v.douyin.com/p55bUJ-j_Gk/ | I48: https://v.douyin.com/p55bUJ-j_Gk/ | K48: 开封市文化广电和旅游局（开封文旅） | M48: 2026-10-22T22:26:09+08:00 | N48: pl_000006 | R48: linked_only | S48: video/mp4 | X48: unknown | Y48: required | Z48: unknown | AC48: public_view_only | AE48: 开封文旅官方抖音 | AF48: 仅校内课程演示，不公开传播、不商业使用 | AG48: src_000134 | AH48: candidate | AI48: restricted | AK48: 成员1 | AL48: 1 | AM48: 开封文旅官方抖音；不是铁塔景区自有账号，属于文旅部门官方渠道；反爬未下载；文件名按视频ID生成。
A49: media_000046 | B49: image | C49: scene | D49: 天下第一塔雪景 | E49: “天下第一塔”石碑与雪中开封铁塔。 | F49: 铁塔_天下第一塔雪景_文旅局_20261022.jpg | G49: evidence/media/铁塔/铁塔_天下第一塔雪景_文旅局_20261022.jpg | H49: https://wgl.kaifeng.gov.cn/kfswhgdhlyj/swgljtpxw/2005540395316277248/HfgARhCN.jpg | I49: https://wgl.kaifeng.gov.cn/kfswhgdhlyj/swgljtpxw/pc/content/content_2005540395316277248.html | K49: 开封市文化广电和旅游局 | M49: 2026-10-22T22:26:09+08:00 | N49: pl_000006 | R49: stored | S49: image/jpeg | T49: 269250 | U49: 1080 | V49: 810 | X49: false | Y49: not_applicable | Z49: false | AA49: 56583fa73151ed2c2a239bfc34e0d0aa81cdf2029cdeedaeb7fb8dae482b71da | AC49: public_view_only | AE49: 河南省文化和旅游厅/开封市文化广电和旅游局 | AF49: 仅校内课程演示，不公开传播、不商业使用 | AG49: src_000138 | AH49: candidate | AI49: restricted | AK49: 成员1 | AL49: 1 | AM49: 开封市文广旅局冬日文章；未发现明显人物；仅校内演示。
A50: media_000048 | B50: image | C50: scene | D50: 荷花与铁塔 | E50: 从室内门洞看荷花与铁塔，北宋古莲与千年铁塔同框。 | F50: 铁塔_荷花与铁塔_文旅厅_20261022.jpg | G50: evidence/media/铁塔/铁塔_荷花与铁塔_文旅厅_20261022.jpg | H50: https://xcoss.henan.gov.cn/typtfile/img/20260717/a421ea22c51d41e3a21906c7034e1b95.jpg | I50: https://hct.henan.gov.cn/2026/07-17/3376661.html | K50: 河南省文化和旅游厅 | M50: 2026-10-22T22:26:09+08:00 | N50: pl_000006 | R50: stored | S50: image/jpeg | T50: 105934 | U50: 1080 | V50: 810 | X50: unknown | Y50: unknown | Z50: false | AA50: cff0a4292090fd7678e173e0c4154862acfcc9498072c3b18d60a08253e304e4 | AC50: public_view_only | AE50: 河南省文化和旅游厅/开封市文化广电和旅游局 | AF50: 仅校内课程演示，不公开传播、不商业使用 | AG50: src_000135 | AH50: candidate | AI50: restricted | AK50: 成员1 | AL50: 1 | AM50: 河南省文旅厅古莲文章；门洞外有少量人物；仅校内演示。
A51: media_000049 | B51: image | C51: scene | D51: 荷花池亭 | E51: 铁塔景区荷花池与临水亭榭，水面有雾森。 | F51: 铁塔_荷花池亭_文旅厅_20261022.jpg | G51: evidence/media/铁塔/铁塔_荷花池亭_文旅厅_20261022.jpg | H51: https://xcoss.henan.gov.cn/typtfile/img/20260717/55cd4dc3a98a4a63ad3092b6d8b5433b.jpg | I51: https://hct.henan.gov.cn/2026/07-17/3376661.html | K51: 河南省文化和旅游厅 | M51: 2026-10-22T22:26:09+08:00 | N51: pl_000006 | R51: stored | S51: image/jpeg | T51: 119514 | U51: 1080 | V51: 810 | X51: unknown | Y51: unknown | Z51: false | AA51: e3d82ace583bee4e75dc34a4234a4c4e894ca0a69a5e5b1af522a5597134face | AC51: public_view_only | AE51: 河南省文化和旅游厅/开封市文化广电和旅游局 | AF51: 仅校内课程演示，不公开传播、不商业使用 | AG51: src_000135 | AH51: candidate | AI51: restricted | AK51: 成员1 | AL51: 1 | AM51: 河南省文旅厅古莲文章；亭内有游客；仅校内演示。
A52: media_000051 | B52: image | C52: scene | D52: 铁塔与荷花远景 | E52: 荷花池远景中的开封铁塔。 | F52: 铁塔_铁塔与荷花远景_文旅局_20261022.jpg | G52: evidence/media/铁塔/铁塔_铁塔与荷花远景_文旅局_20261022.jpg | H52: http://wgl.kaifeng.gov.cn/kfswhgdhlyj/swgljgzdt/2076587234084564992/HvjWZ8v9.jpg | I52: http://wgl.kaifeng.gov.cn/kfswhgdhlyj/swgljgzdt/pc/content/content_2076587234084564992.html | K52: 开封市文化广电和旅游局 | M52: 2026-10-22T22:26:09+08:00 | N52: pl_000006 | R52: stored | S52: image/jpeg | T52: 95738 | U52: 1080 | V52: 537 | X52: false | Y52: not_applicable | Z52: false | AA52: c251294020ae4d8df6c45199a3b43de1e2bcb17aa03a9b5a9353ad0a56cebd59 | AC52: public_view_only | AE52: 河南省文化和旅游厅/开封市文化广电和旅游局 | AF52: 仅校内课程演示，不公开传播、不商业使用 | AG52: src_000136 | AH52: candidate | AI52: restricted | AK52: 成员1 | AL52: 1 | AM52: 开封市文广旅局夏季文章；未发现明显人物；仅校内演示。
